Workbook
Name _ftnref3: 'Carbon Reduction Plan Report'!$A$64
Name OLE_LINK2: '2024 Results Graphs'!#REF!
Name OLE_LINK3: '2024 Results Graphs'!#REF!

Sheet General Info
A1: Please complete relevant areas/fields when applicable. If you require assistance please email: info@sustainquality.co.uk
A3: Login details
A4: Login details
A5: Password
A6: send email to confirm before allowing access
A8: Contact Name
A9: Email
A10: Location (country)
A11: How many organisations?
A13: Organisation Details
A14: Organisation Name
A15: Organisation Address (Registered address)
A16: Sector | D16: Private, Public, Third | E16: we may introduce a paywall if private and public start to use it
A17: Sub-sector | F17: The four main Sub Sectors of an economy are:
A18: Industry (SIC if available) | D18: https://companieshouse.blog.gov.uk/2021/10/12/choosing-a-standard-industrial-classification-sic-code-for-your-company/ | F18: Primary sector: Represents companies that are involved in extracting natural resources and agriculture.
A19: How many buildings to be assessed? | F19: Secondary sector: Companies involved in manufacturing, construction, and processing producing goods that use the resources obtained from companies within the primary sector.
A20: Would you like to include events (if yes - check line 72 for data entry for each event)? | F20: Tertiary sector: Companies that provide services such as entertainment, financial, and retailers.
A21: How many events would you like to include? | D21: events treated as 'new buildings' | F21: Quaternary sector: Involves knowledge-based activities such as information technology, research, and development, as well as consulting services and education.
A23: Full Address - Asset 1 | C23: Description
A24: Is it the Registered office? | C24: (YES or NO)
A25: Name of Asset/Property Group
A26: note: the name of the asset entered here will appear above the assets address on any certificates produced for this asset. Certificate shows a maximum of 28 characters.
A27: Address line 1
A28: Address line 2
A29: note: address line 1 and 2 will be combined as a single line on the certificate and a maximum of 28 charcters will be shown
A30: Address line 3
A31: Address line 4
A32: Note: Address line 3 and 4 will be continued as a single line on the certificate and a maximum of 28 characters will be shown
A33: Town/City
A34: County/Region/State
A35: Post code
A36: Building floor Area (m2) | C36: =C60 -> 0 | D36: Please complete Asset dimensions below
A37: Include in the offset calculation?
A39: Basic building details - Asset 1 | C39: Description
A40: Name of the organisation or peson that owns the asset
A41: Name of the organisation or peson that manages the tenancy of the asset
A42: Name of the organisation or peson that occupies/leases the asset
A43: Assest Description (up to 500 characters)
A44: Add other stakeholders (Sustainability Consultant, MEP, partners…)
A46: General information - Asset 1 | C46: Description
A47: Building type (e.g. community group, office, theatre, museum, gallery, gym, cinema)
A48: Asset Subtype (head quarters, main office, warehouse, supporting building…)
A49: Construction Year
A50: Year of the latest major refurbshiment
A51: Is there a café/restaurant based in the building included in the assessment (Y/N)
A54: Occupancy - Asset 1 | C54: Description
A55: Number of occupants - Number of Full time Employee (FTE) in the building
A56: Annual operational days
A57: Daily operational hours
A59: Asset dimensions - Asset 1 | C59: Description
A60: Gross internal area (GIA scope only - m2)
A61: Measurement standard | C61: Code of Measuring Practice (RICS)
A62: Non-lettable area (m2)
A63: Gross lettable area (m2)
A64: planning restrictions (listed?) | D64: i.e.: The Building is Grade II listed
A65: Width (external façade) (m)
A66: Length (external façade) (m)
A67: Height (floor-to-floor height) (m) | D67: *Please note: Some measurements are averages like i.e. the ceiling height. Façade height and length is challenging to map out due to the nature and shape of the building therefore we have provided the longest sections on both but the true number will be higher.
A68: Number of floors above ground
A69: Number of floors below ground
A70: Area covered by hard lanscaping (m2)
A71: Area Covered by soft lanscaping (m2)
A74: EVENTS - General information
A75: Name of the event
A76: Duration | D76: days
A77: Participants
A78: Number of employes for the event
A79: Include in the offset calculation?
A81: EVENTS - Mobility (Employees) | C81: Unit/notes | D81: Mobility (Guests) | F81: Unit/notes
A82: Number of people arriving by car | D82: Number of people arriving by car | F82: Not applicable? Anyway, it would be useful to calculate if there are data available.
A83: Average distance travelled (car) | D83: Average distance travelled (car) | F83: Not applicable? Anyway, it would be useful to calculate if there are data available.
A84: Number of persons travelling by public transport | D84: Number of persons travelling by public transport | F84: Not applicable? Anyway, it would be useful to calculate if there are data available.
A85: Average distance travelled (public transport) | D85: Average distance travelled (public transport) | F85: Not applicable? Anyway, it would be useful to calculate if there are data available.
A86: Number of short-haul flights (up to 3 hours) | D86: Number of short-haul flights (up to 3 hours) | F86: Not applicable? Anyway, it would be useful to calculate if there are data available.
A87: Number of medium-haul fligths (3-6 hours) | D87: Number of medium-haul fligths (3-6 hours) | F87: Not applicable? Anyway, it would be useful to calculate if there are data available.
A88: Number of long-haul flights (more than 6h) | D88: Number of long-haul flights (more than 6h) | F88: Not applicable? Anyway, it would be useful to calculate if there are data available.
A89: Percentage businees class flights | D89: Percentage businees class flights | F89: Not applicable? Anyway, it would be useful to calculate if there are data available.
A91: EVENTS - Accommodation | D91: Catering
A92: Number of people staying overnight in 2-3 stars hotel | D92: Amount of meals, not vegerarian | F92: unit per person
A93: Number overnight stays in 2-3 star hotels | D93: Amount of vegetarian meals | F93: unit per person
A94: Number of people staying overnight in 4 stars hotel | D94: Amount of snacks
A95: Number overnight stays in 4 stars hotels | D95: Water/soft drinks | F95: litres
A96: Number of people staying overnight in 4 stars hotel | D96: Coffee | F96: cup
A97: Number overnight stays in 4 stars hotels | D97: Tea | F97: cup
D98: Wine | F98: litres
D99: Beer | F99: litres
D100: Spirits | F100: litres
A102: Energy | D102: Materials
A103: Power consumption | C103: KWh | D103: Printed | F103: Kg or ream
A104: Green energy | B104: (YES or NO) | D104: Plastics | F104: Kg
D105: Recyclable material | F105: Kg
D106: Wood, carton, paper and plant-based materials | F106: Kg
D107: Area of stand | F107: m2 if applicable

Sheet Assessment Scope
A1: Please complete relevant areas/fields when applicable. If you require assistance please emai:l info@sustainquality.co.uk
A3: Organisation Details
A4: Organisation Name (Client/owner) | C4: ='General Info'!C14 -> 0
A5: Organisation Address (head quarters/Main address) | C5: ='General Info'!C15 -> 0
A6: How many buildings included/assessed? | C6: ='General Info'!C19 -> 0
A8: General NOTES - All assets or clearly state which assets | C8: Description
A9: Extra note to the reports 1 | D9: User to input text (any words/character limit?)
A10: Extra note to the reports 2 | D10: User to input text (any words/character limit?)
A12: Quantified Carbon Emissions | C12: (Yes or No) | D12: Notes and justificaiton | E12: Check results graph tab line125 If marked Yes should show in the Quantified - if marked Non should show in the non-quantified | M12: Check list | O12: Data included
A13: Base year | D13: Add commentary regarding your Baseline Emissions as required: e.g. historic baseline which deviates from the requirements under this measure (e.g. no prior Scope 3 emissions reporting), where there is no previous reporting and the creation of a new baseline due to substantial organisational change or restructuring] | E13: Year | M13: Base year
A14: Commitiment to achieve Net Zero | E14: Year
A15: Energy | C15: Yes | E15: This will unlock the respective tab | M15: Energy
A16: Water | C16: yes | M16: Water
A17: Waste | C17: No | M17: Waste
A18: Business and Staff Travel | C18: Yes | M18: Business and Staff Travel
A19: Refrigerant | C19: No | M19: Refrigerant
A20: Hotel Stay | C20: No | M20: Hotel Stay
A21: Working from Home | C21: Yes | M21: Working from Home
A22: Materials | C22: No | M22: Materials
A23: Carbon Reduction Plan | M23: Carbon Reduction Plan
A24: Off set strategy
A25: Are there specific processing or activities that emiits carbon not listed above? If yes, please elaborate and submitt for review and implementation
O26: SUBMIT ASSESSMENT FOR REVIEW
A27: Standards Policies in Place (All assets or clearly state which assets)? | C27: (Yes or No)
A28: Environment Policy (accredited to ISO 14001) | F28: https://www.iso.org/standard/60857.html
A29: Human Rights Policy
A30: Sustainable Procurement Policy (ISO 20400) | F30: https://www.iso.org/standard/63026.html
A31: Energy Audit (ISO5002) | F31: https://www.iso.org/standard/60088.html
A32: Has the orgnisation not utilised any ozone-depletio substances (ODS - GRI Commitment)? | D32: As of January 2010, in line with the Montreal Protocol, ODS were prohibted and severely controlled. As such this organisation has no affiliation or use with these substances and are committed to reduce atmospheric emissions in this way.
A33: Add other standard required
A35: International Standards | C35: (Yes or No) | D35: Which Assets?
A36: Eco Audit action plan | F36: https://www.citybridgefoundation.org.uk/funding/eco-audits
A37: BREEAM In-use Part 2 | F37: https://bregroup.com/products/breeam/breeam-technical-standards/breeam-in-use/
A38: Carbon Reduction Plan | F38: https://assets.publishing.service.gov.uk/media/60ba4d208fa8f57ce980b5b7/PPN_0621_Technical_standard_for_the_Completion_of_Carbon_Reduction_Plans__2_.pdf
A39: Science Based Targets | E39: under development | F39: https://sciencebasedtargets.org
A40: CIBSE BENCHMARK | E40: under development | F40: https://www.cibse.org/knowledge-research/knowledge-resources/knowledge-toolbox/benchmarking-registration
A41: Fitwell | E41: under development | F41: https://www.fitwel.org
A42: CRREM (EU) | E42: under development | F42: https://www.crrem.eu
A43: NABERS UK (offices only) | E43: under development | F43: https://bregroup.com/products/nabers-uk/
A44: GRESB | E44: under development | F44: https://www.gresb.com/
A45: LEEDS O&M | E45: under development | F45: https://www.usgbc.org/leed/rating-systems/existing-buildings
A46: Well Standard | E46: under development | F46: https://standard.wellcertified.com/well
A47: Eco Church | E47: under development | F47: https://ecochurch.arocha.org.uk
A48: GHG Protocol | E48: under development | F48: https://ghgprotocol.org
A49: SASB | E49: under development | F49: https://sasb.org
A50: SFDR | E50: under development | F50: https://finance.ec.europa.eu/regulation-and-supervision/financial-services-legislation/implementing-and-delegated-acts/sustainable-finance-disclosures-regulation_en#:~:text=The%20Sustainable%20Finance%20Disclosures%20Regulation,laid%20down%20in%20the%20directive.
... A52: EU Taxonomy | E52: under development | F52: https://finance.ec.europa.eu/sustainable-finance/tools-and-standards/eu-taxonomy-sustainable-activities_en
A53: Ska rating | F53: https://skarating.org
A54: Add other standard required | E54: under development

Sheet Energy
A1: ENERGY USE
B2: Two options (19 - Calendar or 19 - Financial | F2: conv facto from gov 2023
A3: Period | B3: April 2019 - March 2020 | C3: April 2020 - March 2021 | D3: April 2021 - March 2022 | E3: April 2022 - March 2023 | F3: April 2023 - March 2024 | G3: April 2024 - March 2025 | H3: financial year/ full year - specify the months of data provided
A4: Data Input | B4: Two options (Montly or Annual)
A5: If annual | B5: CONSUMPTION | C5: CONSUMPTION | D5: CONSUMPTION | E5: CONSUMPTION | F5: CONSUMPTION
A6: Mains electricity use | H6: kWh | I6: Electricity use in kWh can be found on your electricity bills.
A7: Mains gas use | H7: kWh | I7: Gas use in kWh can be found on your gas bills.
A8: Diesel use | H8: Litres | I8: If the venue uses diesel powered generators as part of its permanent energy supply, provide the amount of diesel used.
A9: Bottled gas use | H9: litres | I9: LPG gas bottles (Propane & Butane)
A10: Oil use | H10: litres | I10: If the venue uses oil powered generators as part of its permanent energy supply, provide the amount of oil used.
A11: Other (specify i.e District Heating) | H11: kWh or % | I11: Please find energy used from district heating
A12: Provide conversion factor for other | H12: Unit | I12: Please provide document confirming the converstion factor of the district heating
A13: Onsite renewable energy | H13: kWh | I13: If you have any renewable energy sources on your building, such as photovoltaic (PV) panels, provide the kWh of energy produced.
A16: Energy supplier
A17: Electricity supplier | I17: Provide the electricty supplier company name
A19: Green electricity tariff | H19: yes/no/don’t know | I19: All suppliers in the UK get at least some of their electricity from renewable sources and most offer what's known as 'green' tariff electricity. If you are on such tariff, it means one of two things: 1 - The supplier promises to match your usage with generation from renewable sources, and invest in additional generation or contribute to envrionmental schemes that lower carbon dioxide emissions (a 'green' tariff with additionality) 2 - The supplier promises to match your usage with generation from renewable sources, but doens't offer any additional envrionmental benefits (a 'green' tariff without additionality)
A21: Energy use notes
A22: Green electricity tariff details | I22: If you use one, please give details of your green electricity tariff supplier and the tariff name. A green electricity tariff is a tariff that the enery suppler claims has environmental benefits.
A24: Energy notes | I24: Please add any notes about your data sources and assumptions fo energy estimates
A28: Custom Emissions
A29: Description | H29: Emissions (kg CO2e) | K29: If you have calculated your emissions elswhere, please include them here.
A32: Attach files
A33: Please attach energy bills (a sample including the first and the last bill during the period
A37: CLICK HERE TO SUBMIT FOR REVIEW
A39: If monthly
A40: If Finacial Year
A41: Montly Input | B41: April | C41: May | D41: June | E41: July | F41: August | G41: September | H41: October | I41: November | J41: December | K41: January | L41: February | M41: March | N41: Total
A42: Mains electricity use | N42: =SUM(B42:M42) -> 0
A43: Mains gas use | N43: =SUM(B43:M43) -> 0
A44: Diesel use | N44: =SUM(B44:M44) -> 0
A45: Bottled gas use | N45: =SUM(B45:M45) -> 0
A46: Oil use | N46: =SUM(B46:M46) -> 0
A47: Other (specify i.e District Heating) | N47: =SUM(B47:M47) -> 0
A48: Provide conversion factor for other | N48: =SUM(B48:M48) -> 0
A49: Onsite renewable energy | N49: =SUM(B49:M49) -> 0
A51: If Calendar Year
A52: Montly Input | B52: January | C52: February | D52: March | E52: April | F52: May | G52: June | H52: July | I52: August | J52: September | K52: October | L52: November | M52: December | N52: Total
A53: Mains electricity use | N53: =SUM(B53:M53) -> 0
A54: Mains gas use | N54: =SUM(B54:M54) -> 0
A55: Diesel use | N55: =SUM(B55:M55) -> 0
A56: Bottled gas use | N56: =SUM(B56:M56) -> 0
A57: Oil use | N57: =SUM(B57:M57) -> 0
A58: Other (specify i.e District Heating) | N58: =SUM(B58:M58) -> 0
A59: Provide conversion factor for other | N59: =SUM(B59:M59) -> 0
A60: Onsite renewable energy | N60: =SUM(B60:M60) -> 0

Sheet Water
A1: WATER CONSUMPTION
C2: Two options (19 - Calendar or 19 - Financial
A3: Period | C3: April 2019 - March 2020 | D3: April 2020 - March 2021 | E3: April 2021 - March 2022 | F3: April 2022 - March 2023 | G3: April 2023 - March 2024 | H3: April 2024 - March 2025 | I3: financial year/ full year - specify the months of data provided
A4: Data Input | C4: Two options (Montly or Annual)
A5: If annual | C5: CONSUMPTION | D5: CONSUMPTION | E5: CONSUMPTION | F5: CONSUMPTION | G5: CONSUMPTION | H5: CONSUMPTION
A6: Water use | I6: m3 | J6: Water use in m3 can be found on your water bills. If it is in litres, divide by 1,000. For venue hire, the venue should provide the submeter reading.
A8: Wastewater | I8: m3 | J8: Sewerage or wastewater in m3 can be found on your water or sewerage bills. It it is in litres, divide by 1,000. If you can't find sewerage data, then assume it's the same as your water use.
A11: Water notes | J11: Please add notes related to water data sources and assumptions
A14: Custom Emissions
A15: Description | I15: Emissions (kg CO2e) | K15: If you have calculated your emissions elswhere, please include them here.
A18: Attach files
A19: Please attach water bills (a sample including the first and the last bill during the period
A23: CLICK HERE TO SUBMIT FOR REVIEW
A25: If monthly
A26: If Finacial Year
A27: Montly Input | B27: April | C27: May | D27: June | E27: July | F27: August | G27: September | H27: October | I27: November | J27: December | K27: January | L27: February | M27: March | N27: Total
A28: Water Use | N28: =SUM(B28:M28) -> 0
A29: Waste Water | N29: =SUM(B29:M29) -> 0
A31: If Calendar Year
A32: Montly Input | B32: January | C32: February | D32: March | E32: April | F32: May | G32: June | H32: July | I32: August | J32: September | K32: October | L32: November | M32: December | N32: Total
A33: Water Use | N33: =SUM(B33:M33) -> 0
A34: Waste Water | N34: =SUM(B34:M34) -> 0

Sheet Waste 
A1: WASTE GENERATION
C2: Two options (19 - Calendar or 19 - Financial
A3: Period | C3: April 2019 - March 2020 | D3: April 2020 - March 2021 | E3: April 2021 - March 2022 | F3: April 2022 - March 2023 | G3: April 2023 - March 2024 | H3: April 2024 - March 2025 | I3: financial year/ full year - specify the months of data provided
A4: Data Input | C4: Two options (Montly or Annual)
C5: Data input in tonnes only - Go to Waste Calculator if data is in Bag, Litres or Kilograms
A7: If annual | C7: CONSUMPTION | D7: CONSUMPTION | E7: CONSUMPTION | F7: CONSUMPTION | G7: CONSUMPTION | H7: CONSUMPTION
A8: Waste to landfill | I8: Unit | K8: Tonnage can be found on the bills from your waste contractor. If not, estimate the number of black bin bags sent to landfill each week. | M8: UNIT CONVERSION
N9: bags --> kg | O9: litres --> kg | P9: KG to Tonnes
A10: Waste to energy | I10: Unit | K10: Tonnage can be found on the bills from your waste contractor. If not, estimate the number of black bin bags sent to landfill each week. | M10: General Waste | N10: 5.0192308 | O10: 0.08365385 | P10: 0.001
M11: Recycling | N11: 4.0980392 | O11: 0.06830065 | P11: 0.001
A12: Waste to recycling | I12: Unit | K12: Tonnage can be found on the bills from your waste contractor. If not, estimate the number of black bin bags sent to landfill each week. | M12: Mixed Food | N12: 19.057692 | O12: 0.3176281 | P12: 0.001
A14: Waste to composting | I14: Unit | K14: Tonnage can be found on the bills from your waste contractor. If not, estimate the number of black bin bags sent to landfill each week.
A19: Waste notes | K19: Please add notes related to waste data sources and assumptions
A23: Custom Emissions
A24: Description | I24: Emissions (kg CO2e) | K24: If you have calculated your emissions elswhere, please include them here.
A27: Attach files
A28: Please attach waste bills/tickets/reports (a sample including the first and the last bill during the period
A33: CLICK HERE TO SUBMIT FOR REVIEW
A35: If monthly
A36: If Finacial Year
A37: Montly Input | B37: April | C37: May | D37: June | E37: July | F37: August | G37: September | H37: October | I37: November | J37: December | K37: January | L37: February | M37: March | N37: Total
A38: Waste to landfill | N38: =SUM(B38:M38) -> 0
A39: Waste to energy | N39: =SUM(B39:M39) -> 0
A40: Waste to recycling | N40: =SUM(B40:M40) -> 0
A41: Waste to composting | N41: =SUM(B41:M41) -> 0
A43: If Calendar Year
A44: Montly Input | B44: January | C44: February | D44: March | E44: April | F44: May | G44: June | H44: July | I44: August | J44: September | K44: October | L44: November | M44: December | N44: Total
A45: Waste to landfill | N45: =SUM(B45:M45) -> 0
A46: Waste to energy | N46: =SUM(B46:M46) -> 0
A47: Waste to recycling | N47: =SUM(B47:M47) -> 0
A48: Waste to composting | N48: =SUM(B48:M48) -> 0

Sheet Business & Staff Travel
B1: BUSINESS TRAVEL
D2: Two options (19 - Calendar or 19 - Financial
B3: Period | D3: April 2019 - March 2020 | E3: April 2020 - March 2021 | F3: April 2021 - March 2022 | G3: April 2022 - March 2023 | H3: April 2023 - March 2024 | I3: April 2024 - March 2025 | J3: financial year/ full year - specify the months of data provided | M3: April 2019 - March 2020 | N3: April 2020 - March 2021 | O3: April 2021 - March 2022 | P3: April 2022 - March 2023 | Q3: April 2023 - March 2024 | R3: April 2024 - March 2025 | S3: financial year/ full year - specify the months of data provided
B4: Data Input | D4: Two options (Montly or Annual)
B5: Unit input | D5: Miles or KM
B6: How do you define domestic, short-haul, long-haul and international flights?
B7: Broadly speaking the definition of domestic flights, are those within the UK, short-haul are those within Europe, long-haul are outside of Europe and international flights are those between non-UK destinations. A full list of countries and their assignment to either long-haul or short-haul is provided in the Haul_definition tab.
B9: Please complete the data in Km and remove the 0. If your data is in Miles, please complete the column Miles and the calculator will convert KM to Miles using 1.60934
B10: If your vehicle is not listed please contact info@sustainquality.co.uk
B12: Business Travel | D12: KM | K12: MILES TO KM | M12: MILES
K13: 1.60934
A14: Business Travel (SCOPE 3) | B14: Car (small) | Petrol | D14: =$K$13*M14 -> 0 | E14: =$K$13*N14 -> 0 | F14: =$K$13*O14 -> 0 | G14: =$K$13*P14 -> 0 | H14: =$K$13*Q14 -> 0
B15: Car (medium) | Petrol | D15: =$K$13*M15 -> 0 | E15: =$K$13*N15 -> 0 | F15: =$K$13*O15 -> 0 | G15: =$K$13*P15 -> 0 | H15: =$K$13*Q15 -> 0
B16: Car (large) | Petrol | D16: =$K$13*M16 -> 0 | E16: =$K$13*N16 -> 0 | F16: =$K$13*O16 -> 0 | G16: =$K$13*P16 -> 0 | H16: =$K$13*Q16 -> 0
B17: Car (average) | Petrol | D17: =$K$13*M17 -> 0 | E17: =$K$13*N17 -> 0 | F17: =$K$13*O17 -> 0 | G17: =$K$13*P17 -> 0 | H17: =$K$13*Q17 -> 0
B18: Car (small) | Diesel | D18: =$K$13*M18 -> 0 | E18: =$K$13*N18 -> 0 | F18: =$K$13*O18 -> 0 | G18: =$K$13*P18 -> 0 | H18: =$K$13*Q18 -> 0
B19: Car (medium) | Diesel | D19: =$K$13*M19 -> 0 | E19: =$K$13*N19 -> 0 | F19: =$K$13*O19 -> 0 | G19: =$K$13*P19 -> 0 | H19: =$K$13*Q19 -> 0
B20: Car (large) | Diesel | D20: =$K$13*M20 -> 0 | E20: =$K$13*N20 -> 0 | F20: =$K$13*O20 -> 0 | G20: =$K$13*P20 -> 0 | H20: =$K$13*Q20 -> 0
B21: Car (average) | Diesel | D21: =$K$13*M21 -> 0 | E21: =$K$13*N21 -> 0 | F21: =$K$13*O21 -> 0 | G21: =$K$13*P21 -> 0 | H21: =$K$13*Q21 -> 0
B22: Car (small) | Hybrid | D22: =$K$13*M22 -> 0 | E22: =$K$13*N22 -> 0 | F22: =$K$13*O22 -> 0 | G22: =$K$13*P22 -> 0 | H22: =$K$13*Q22 -> 0
B23: Car (medium) | Hybrid | D23: =$K$13*M23 -> 0 | E23: =$K$13*N23 -> 0 | F23: =$K$13*O23 -> 0 | G23: =$K$13*P23 -> 0 | H23: =$K$13*Q23 -> 0
B24: Car (large) | Hybrid | D24: =$K$13*M24 -> 0 | E24: =$K$13*N24 -> 0 | F24: =$K$13*O24 -> 0 | G24: =$K$13*P24 -> 0 | H24: =$K$13*Q24 -> 0
B25: Car (average) | Hybrid | D25: =$K$13*M25 -> 0 | E25: =$K$13*N25 -> 0 | F25: =$K$13*O25 -> 0 | G25: =$K$13*P25 -> 0 | H25: =$K$13*Q25 -> 0
B26: Car (small) | Plug-in Hybrid | D26: =$K$13*M26 -> 0 | E26: =$K$13*N26 -> 0 | F26: =$K$13*O26 -> 0 | G26: =$K$13*P26 -> 0 | H26: =$K$13*Q26 -> 0
... B53: International (to/from non-UK) - business class | D53: =$K$13*M53 -> 0 | E53: =$K$13*N53 -> 0 | F53: =$K$13*O53 -> 0 | G53: =$K$13*P53 -> 0 | H53: =$K$13*Q53 -> 0
A54: Freighting goods (SCOPE 3) | B54: Average Van (up to 3.5 tonnes) (diesel) | D54: =$K$13*M54 -> 0 | E54: =$K$13*N54 -> 0 | F54: =$K$13*O54 -> 0 | G54: =$K$13*P54 -> 0 | H54: =$K$13*Q54 -> 0
B55: Average Van (up to 3.5 tonnes) (petrol) | D55: =$K$13*M55 -> 0 | E55: =$K$13*N55 -> 0 | F55: =$K$13*O55 -> 0 | G55: =$K$13*P55 -> 0 | H55: =$K$13*Q55 -> 0
B56: HGVs (diesel) | D56: =$K$13*M56 -> 0 | E56: =$K$13*N56 -> 0 | F56: =$K$13*O56 -> 0 | G56: =$K$13*P56 -> 0 | H56: =$K$13*Q56 -> 0
B57: Refrigerated HGVs (diesel) | D57: =$K$13*M57 -> 0 | E57: =$K$13*N57 -> 0 | F57: =$K$13*O57 -> 0 | G57: =$K$13*P57 -> 0 | H57: =$K$13*Q57 -> 0
B58: Freight flights (Domestic to/from UK) | D58: =$K$13*M58 -> 0 | E58: =$K$13*N58 -> 0 | F58: =$K$13*O58 -> 0 | G58: =$K$13*P58 -> 0 | H58: =$K$13*Q58 -> 0
B59: Freight flights (Short-haul to/from UK) | D59: =$K$13*M59 -> 0 | E59: =$K$13*N59 -> 0 | F59: =$K$13*O59 -> 0 | G59: =$K$13*P59 -> 0 | H59: =$K$13*Q59 -> 0
B60: Freight flights (Long haul to/from UK) | D60: =$K$13*M60 -> 0 | E60: =$K$13*N60 -> 0 | F60: =$K$13*O60 -> 0 | G60: =$K$13*P60 -> 0 | H60: =$K$13*Q60 -> 0
B61: Freight flights (International to/from UK) | D61: =$K$13*M61 -> 0 | E61: =$K$13*N61 -> 0 | F61: =$K$13*O61 -> 0 | G61: =$K$13*P61 -> 0 | H61: =$K$13*Q61 -> 0
B62: Rail (freight train) | D62: =$K$13*M62 -> 0 | E62: =$K$13*N62 -> 0 | F62: =$K$13*O62 -> 0 | G62: =$K$13*P62 -> 0 | H62: =$K$13*Q62 -> 0
B63: Cargo Ship (Bulk carrier) | D63: =$K$13*M63 -> 0 | E63: =$K$13*N63 -> 0 | F63: =$K$13*O63 -> 0 | G63: =$K$13*P63 -> 0 | H63: =$K$13*Q63 -> 0
B64: Cargo Ship (General cargo) | D64: =$K$13*M64 -> 0 | E64: =$K$13*N64 -> 0 | F64: =$K$13*O64 -> 0 | G64: =$K$13*P64 -> 0 | H64: =$K$13*Q64 -> 0
B65: Cargo Ship (Container ship) | D65: =$K$13*M65 -> 0 | E65: =$K$13*N65 -> 0 | F65: =$K$13*O65 -> 0 | G65: =$K$13*P65 -> 0 | H65: =$K$13*Q65 -> 0
B66: Cargo Ship (Vehicle transport) | D66: =$K$13*M66 -> 0 | E66: =$K$13*N66 -> 0 | F66: =$K$13*O66 -> 0 | G66: =$K$13*P66 -> 0 | H66: =$K$13*Q66 -> 0
B67: Cargo Ship (Refrigerated cargo) | D67: =$K$13*M67 -> 0 | E67: =$K$13*N67 -> 0 | F67: =$K$13*O67 -> 0 | G67: =$K$13*P67 -> 0 | H67: =$K$13*Q67 -> 0
A68: Staff Commute (SCOPE 3) | B68: Car (small) | Petrol | D68: =$K$13*M68 -> 0 | E68: =$K$13*N68 -> 0 | F68: =$K$13*O68 -> 0 | G68: =$K$13*P68 -> 0 | H68: =$K$13*Q68 -> 0
B69: Car (medium) | Petrol | D69: =$K$13*M69 -> 0 | E69: =$K$13*N69 -> 0 | F69: =$K$13*O69 -> 0 | G69: =$K$13*P69 -> 0 | H69: =$K$13*Q69 -> 0
B70: Car (large) | Petrol | D70: =$K$13*M70 -> 0 | E70: =$K$13*N70 -> 0 | F70: =$K$13*O70 -> 0 | G70: =$K$13*P70 -> 0 | H70: =$K$13*Q70 -> 0
B71: Car (average) | Petrol | D71: =$K$13*M71 -> 0 | E71: =$K$13*N71 -> 0 | F71: =$K$13*O71 -> 0 | G71: =$K$13*P71 -> 0 | H71: =$K$13*Q71 -> 0
B72: Car (small) | Diesel | D72: =$K$13*M72 -> 0 | E72: =$K$13*N72 -> 0 | F72: =$K$13*O72 -> 0 | G72: =$K$13*P72 -> 0 | H72: =$K$13*Q72 -> 0
B73: Car (medium) | Diesel | D73: =$K$13*M73 -> 0 | E73: =$K$13*N73 -> 0 | F73: =$K$13*O73 -> 0 | G73: =$K$13*P73 -> 0 | H73: =$K$13*Q73 -> 0
B74: Car (large) | Diesel | D74: =$K$13*M74 -> 0 | E74: =$K$13*N74 -> 0 | F74: =$K$13*O74 -> 0 | G74: =$K$13*P74 -> 0 | H74: =$K$13*Q74 -> 0
B75: Car (average) | Diesel | D75: =$K$13*M75 -> 0 | E75: =$K$13*N75 -> 0 | F75: =$K$13*O75 -> 0 | G75: =$K$13*P75 -> 0 | H75: =$K$13*Q75 -> 0
B76: Car (small) | Hybrid | D76: =$K$13*M76 -> 0 | E76: =$K$13*N76 -> 0 | F76: =$K$13*O76 -> 0 | G76: =$K$13*P76 -> 0 | H76: =$K$13*Q76 -> 0
B77: Car (medium) | Hybrid | D77: =$K$13*M77 -> 0 | E77: =$K$13*N77 -> 0 | F77: =$K$13*O77 -> 0 | G77: =$K$13*P77 -> 0 | H77: =$K$13*Q77 -> 0
B78: Car (large) | Hybrid | D78: =$K$13*M78 -> 0 | E78: =$K$13*N78 -> 0 | F78: =$K$13*O78 -> 0 | G78: =$K$13*P78 -> 0 | H78: =$K$13*Q78 -> 0
B79: Car (average) | Hybrid | D79: =$K$13*M79 -> 0 | E79: =$K$13*N79 -> 0 | F79: =$K$13*O79 -> 0 | G79: =$K$13*P79 -> 0 | H79: =$K$13*Q79 -> 0
B80: Car (small) | Plug-in Hybrid | D80: =$K$13*M80 -> 0 | E80: =$K$13*N80 -> 0 | F80: =$K$13*O80 -> 0 | G80: =$K$13*P80 -> 0 | H80: =$K$13*Q80 -> 0
... B107: International (to/from non-UK) - business class | D107: =$K$13*M107 -> 0 | E107: =$K$13*N107 -> 0 | F107: =$K$13*O107 -> 0 | G107: =$K$13*P107 -> 0 | H107: =$K$13*Q107 -> 0
A108: Private vehicle for business use (SCOPE 2) | B108: Car (small) | Petrol | D108: =$K$13*M108 -> 0 | E108: =$K$13*N108 -> 0 | F108: =$K$13*O108 -> 0 | G108: =$K$13*P108 -> 0 | H108: =$K$13*Q108 -> 0
B109: Car (medium) | Petrol | D109: =$K$13*M109 -> 0 | E109: =$K$13*N109 -> 0 | F109: =$K$13*O109 -> 0 | G109: =$K$13*P109 -> 0 | H109: =$K$13*Q109 -> 0
B110: Car (large) | Petrol | D110: =$K$13*M110 -> 0 | E110: =$K$13*N110 -> 0 | F110: =$K$13*O110 -> 0 | G110: =$K$13*P110 -> 0 | H110: =$K$13*Q110 -> 0
B111: Car (average) | Petrol | D111: =$K$13*M111 -> 0 | E111: =$K$13*N111 -> 0 | F111: =$K$13*O111 -> 0 | G111: =$K$13*P111 -> 0 | H111: =$K$13*Q111 -> 0
B112: Car (small) | Diesel | D112: =$K$13*M112 -> 0 | E112: =$K$13*N112 -> 0 | F112: =$K$13*O112 -> 0 | G112: =$K$13*P112 -> 0 | H112: =$K$13*Q112 -> 0
B113: Car (medium) | Diesel | D113: =$K$13*M113 -> 0 | E113: =$K$13*N113 -> 0 | F113: =$K$13*O113 -> 0 | G113: =$K$13*P113 -> 0 | H113: =$K$13*Q113 -> 0
B114: Car (large) | Diesel | D114: =$K$13*M114 -> 0 | E114: =$K$13*N114 -> 0 | F114: =$K$13*O114 -> 0 | G114: =$K$13*P114 -> 0 | H114: =$K$13*Q114 -> 0
B115: Car (average) | Diesel | D115: =$K$13*M115 -> 0 | E115: =$K$13*N115 -> 0 | F115: =$K$13*O115 -> 0 | G115: =$K$13*P115 -> 0 | H115: =$K$13*Q115 -> 0
B116: Car (small) | Hybrid | D116: =$K$13*M116 -> 0 | E116: =$K$13*N116 -> 0 | F116: =$K$13*O116 -> 0 | G116: =$K$13*P116 -> 0 | H116: =$K$13*Q116 -> 0
B117: Car (medium) | Hybrid | D117: =$K$13*M117 -> 0 | E117: =$K$13*N117 -> 0 | F117: =$K$13*O117 -> 0 | G117: =$K$13*P117 -> 0 | H117: =$K$13*Q117 -> 0
B118: Car (large) | Hybrid | D118: =$K$13*M118 -> 0 | E118: =$K$13*N118 -> 0 | F118: =$K$13*O118 -> 0 | G118: =$K$13*P118 -> 0 | H118: =$K$13*Q118 -> 0
B119: Car (average) | Hybrid | D119: =$K$13*M119 -> 0 | E119: =$K$13*N119 -> 0 | F119: =$K$13*O119 -> 0 | G119: =$K$13*P119 -> 0 | H119: =$K$13*Q119 -> 0
B120: Car (small) | Plug-in Hybrid | D120: =$K$13*M120 -> 0 | E120: =$K$13*N120 -> 0 | F120: =$K$13*O120 -> 0 | G120: =$K$13*P120 -> 0 | H120: =$K$13*Q120 -> 0
... B123: Car (average) | Plug-in Hybrid | D123: =$K$13*M123 -> 0 | E123: =$K$13*N123 -> 0 | F123: =$K$13*O123 -> 0 | G123: =$K$13*P123 -> 0 | H123: =$K$13*Q123 -> 0
A124: Company fleet and leased vehicles (SCOPE 1) | B124: Average Van (up to 3.5 tonnes) (diesel) | D124: =$K$13*M124 -> 0 | E124: =$K$13*N124 -> 0 | F124: =$K$13*O124 -> 0 | G124: =$K$13*P124 -> 0 | H124: =$K$13*Q124 -> 0
B125: Average Van (up to 3.5 tonnes) (petrol) | D125: =$K$13*M125 -> 0 | E125: =$K$13*N125 -> 0 | F125: =$K$13*O125 -> 0 | G125: =$K$13*P125 -> 0 | H125: =$K$13*Q125 -> 0
B126: HGVs (diesel) | D126: =$K$13*M126 -> 0 | E126: =$K$13*N126 -> 0 | F126: =$K$13*O126 -> 0 | G126: =$K$13*P126 -> 0 | H126: =$K$13*Q126 -> 0
B127: Refrigerated HGVs (diesel) | D127: =$K$13*M127 -> 0 | E127: =$K$13*N127 -> 0 | F127: =$K$13*O127 -> 0 | G127: =$K$13*P127 -> 0 | H127: =$K$13*Q127 -> 0
B128: Freight flights (Domestic to/from UK) | D128: =$K$13*M128 -> 0 | E128: =$K$13*N128 -> 0 | F128: =$K$13*O128 -> 0 | G128: =$K$13*P128 -> 0 | H128: =$K$13*Q128 -> 0
B129: Freight flights (Short-haul to/from UK) | D129: =$K$13*M129 -> 0 | E129: =$K$13*N129 -> 0 | F129: =$K$13*O129 -> 0 | G129: =$K$13*P129 -> 0 | H129: =$K$13*Q129 -> 0
B130: Freight flights (Long haul to/from UK) | D130: =$K$13*M130 -> 0 | E130: =$K$13*N130 -> 0 | F130: =$K$13*O130 -> 0 | G130: =$K$13*P130 -> 0 | H130: =$K$13*Q130 -> 0
B131: Freight flights (International to/from UK) | D131: =$K$13*M131 -> 0 | E131: =$K$13*N131 -> 0 | F131: =$K$13*O131 -> 0 | G131: =$K$13*P131 -> 0 | H131: =$K$13*Q131 -> 0
B132: Rail (freight train) | D132: =$K$13*M132 -> 0 | E132: =$K$13*N132 -> 0 | F132: =$K$13*O132 -> 0 | G132: =$K$13*P132 -> 0 | H132: =$K$13*Q132 -> 0
B133: Cargo Ship (Bulk carrier) | D133: =$K$13*M133 -> 0 | E133: =$K$13*N133 -> 0 | F133: =$K$13*O133 -> 0 | G133: =$K$13*P133 -> 0 | H133: =$K$13*Q133 -> 0
B134: Cargo Ship (General cargo) | D134: =$K$13*M134 -> 0 | E134: =$K$13*N134 -> 0 | F134: =$K$13*O134 -> 0 | G134: =$K$13*P134 -> 0 | H134: =$K$13*Q134 -> 0
B135: Cargo Ship (Container ship) | D135: =$K$13*M135 -> 0 | E135: =$K$13*N135 -> 0 | F135: =$K$13*O135 -> 0 | G135: =$K$13*P135 -> 0 | H135: =$K$13*Q135 -> 0
B136: Cargo Ship (Vehicle transport) | D136: =$K$13*M136 -> 0 | E136: =$K$13*N136 -> 0 | F136: =$K$13*O136 -> 0 | G136: =$K$13*P136 -> 0 | H136: =$K$13*Q136 -> 0
... B153: Car (average) | Plug-in Hybrid | D153: =$K$13*M153 -> 0 | E153: =$K$13*N153 -> 0 | F153: =$K$13*O153 -> 0 | G153: =$K$13*P153 -> 0 | H153: =$K$13*Q153 -> 0
B161: CLICK HERE TO SUBMIT FOR REVIEW

Sheet Refrigerants
A1: REFRIGERANTS
A2: Top ups made to air conditioning units - Many refrigeration, fire protection and air conditioning equipment contain a type of F gas (Fluorinated greenhouse gas), which has a large carbon footprint. Please include the type and quantity of top up that has been done during the reporting year. You can find this information in the service sheets provided by your air conditioning or refrigeration contractor
C4: Two options (19 - Calendar or 19 - Financial
A5: Period | C5: April 2019 - March 2020 | D5: April 2020 - March 2021 | E5: April 2021 - March 2022 | F5: April 2022 - March 2023 | G5: April 2023 - March 2024 | H5: April 2024 - March 2025 | I5: financial year/ full year - specify the months of data provided
A6: Data Input | C6: Two options (Montly or Annual) - Is it applicable?
A8: R404A
A10: R404A | I10: Kg
A12: Notes
A14: R407A
A16: R407A | I16: Kg
A18: Notes
A20: R407C
A22: R407C | I22: Kg
A24: Notes
A26: R408A
A28: R408A | I28: Kg
A30: Notes
A33: R410A
A35: R410A | I35: Kg
A37: Notes
A40: R134a
A42: R134a | I42: Kg
A44: Notes
A48: Other Refrigerant:
A50: Emission Type 1
A52: Notes
A54: Emission Factor
A58: Attach files
A59: Please attach Refrigerant charge receipts/spreadsheets/reports (a sample including the first and the last bill during the period
A63: CLICK HERE TO SUBMIT FOR REVIEW

Sheet Hotel Stay
A1: Hotel Stay
C2: Two options (19 - Calendar or 19 - Financial
A3: Period | C3: April 2019 - March 2020 | D3: April 2020 - March 2021 | E3: April 2021 - March 2022 | F3: April 2022 - March 2023 | G3: April 2023 - March 2024 | H3: April 2024 - March 2025 | I3: financial year/ full year - specify the months of data provided
A4: Data Input | C4: Two options (Montly or Annual)
C6: CONSUMPTION | D6: CONSUMPTION | E6: CONSUMPTION | F6: CONSUMPTION | G6: CONSUMPTION
A7: Hotel Stay UK | I7: nights
A8: Hotel Stay London | I8: nights
A11: Hotel Notes | J11: Please add notes related to Hotel data sources and assumptions
A14: Custom Emissions
A15: Description - if other country | I15: Emissions (kg CO2e) | K15: If you have calculated your emissions elswhere, please include them here.
A18: Attach files
A19: Please attach hotel receipts/spreadsheets/reports (a sample including the first and the last bill during the period
A23: CLICK HERE TO SUBMIT FOR REVIEW
A25: If monthly
A26: If Finacial Year
A27: Montly Input | B27: April | C27: May | D27: June | E27: July | F27: August | G27: September | H27: October | I27: November | J27: December | K27: January | L27: February | M27: March | N27: Total
A28: Hotel Stay UK | N28: =SUM(B28:M28) -> 0
A29: Hotel Stay London | N29: =SUM(B29:M29) -> 0
A31: If Calendar Year
A32: Montly Input | B32: January | C32: February | D32: March | E32: April | F32: May | G32: June | H32: July | I32: August | J32: September | K32: October | L32: November | M32: December | N32: Total
A33: Hotel Stay UK | N33: =SUM(B33:M33) -> 0
A34: Hotel Stay London | N34: =SUM(B34:M34) -> 0

Sheet Working from Home
A1: Working from Home
C2: Two options (19 - Calendar or 19 - Financial
A3: Period | C3: April 2019 - March 2020 | D3: April 2020 - March 2021 | E3: April 2021 - March 2022 | F3: April 2022 - March 2023 | G3: April 2023 - March 2024 | H3: April 2024 - March 2025 | I3: financial year/ full year - specify the months of data provided
A4: Actual/FTE | C4: Confirm if hours are actual or FTE
A5: Data Input | C5: Two options (Montly or Annual)
C6: CONSUMPTION | D6: CONSUMPTION | E6: CONSUMPTION | F6: CONSUMPTION | G6: CONSUMPTION
A7: Working from home | G7: 4179.6 | I7: working hours
A10: Working from home Notes | J10: Please add notes related to working from home data sources and assumptions
A13: Custom Emissions
A14: Description | I14: Emissions (kg CO2e) | K14: If you have calculated your emissions elswhere, please include them here.
A17: Attach files
A18: Please attach receipts/spreadsheets/reports (a sample including the first and the last bill during the period
A24: CLICK HERE TO SUBMIT FOR REVIEW
A26: If monthly
A27: If Finacial Year
A28: Montly Input | B28: April | C28: May | D28: June | E28: July | F28: August | G28: September | H28: October | I28: November | J28: December | K28: January | L28: February | M28: March | N28: Total
A29: Working from home | N29: =SUM(B29:M29) -> 0
A31: If Calendar Year
A32: Montly Input | B32: January | C32: February | D32: March | E32: April | F32: May | G32: June | H32: July | I32: August | J32: September | K32: October | L32: November | M32: December | N32: Total
A33: Working from home | N33: =SUM(B33:M33) -> 0

Sheet Material Use
A1: Material Use
C2: Two options (19 - Calendar or 19 - Financial
A3: Period | C3: April 2019 - March 2020 | D3: April 2020 - March 2021 | E3: April 2021 - March 2022 | F3: April 2022 - March 2023 | G3: April 2023 - March 2024 | H3: April 2024 - March 2025 | I3: financial year/ full year - specify the months of data provided
A5: Please complete the data in Tonnes and remove the 0. If your data is in KG, please complete the column KG and the calculator will convert KG to Tonnes /1000
A6: If your vehicle is not listed please contact info@sustainquality.co.uk
C8: Tonnes | J8: KG to Tonnes | L8: KG
A9: Average construction (primary material production)
A10: Aggregates (primary material production)
A11: Aggregates (re-used)
A12: Aggregates (closed-loop)
A13: Asphalt (primary material production)
A14: Asphalt (re-used)
A15: Asphalt (closed-loop)
A16: Bricks (primary material production)
A17: Concrete (primary material production)
A18: Concrete (closed-loop)
A19: Other?
A23: Materials Notes | J23: Please add notes related to Material data sources and assumptions
A26: Custom Emissions
A27: Description | I27: Emissions (kg CO2e) | K27: If you have calculated your emissions elswhere, please include them here.
A30: Attach files
A31: Please attach materials EPD/ISO certificates/delivery note/receipts/spreadsheets/reports (a sample including the first and the last bill during the period
A37: CLICK HERE TO SUBMIT FOR REVIEW

Sheet Elements Tab Energy...
B3: The same tab for all elements
B4: Energy | C4: Water | D4: Waste | E4: Business and Staff tavel | G4: refrigerants | H4: Hotel Stay | I4: Working from Home

Sheet Carbon Reduction Plan
A1: Notes
A2: Please use column F to write the strategies / plans for the next years that may reduce the carbon emissions - for example ASHP, PV panels, off set, lighting….as per CRP template
A3: Please input the estimated % reduction for each year - column D
A5: Completed Carbon Reduction initiatives
A6: [Instructions:
A7: Briefly provide details of some of your completed carbon reduction projects. This is for information only.
A8: This may include environmental management measures such as certification schemes like ISO14001 or PAS 2060, signing up to SBTI or specific measures you have taken such as; the adoption of LED/PIR lighting controls, changes to policy resulting in a reduction in company travel and flights or the electrification of the company fleet.]
A10: Future (Planned) Carbon Reduction Initiatives
A11: Instructions: Briefly provide details of some of any likely/proposed future carbon reduction projects. This is for information only.]
A15: CARBON REDUCTION PLAN
B16: Years | C16: Current Emissions | D16: Reduction (%) | E16: Future Emissions | F16: Carbon Reduction Measures (Incl Scope 1,2,3) | H16: Notes | J16: References
B17: 2020 | C17: FROM CALCS | D17: - | H17: Completed Actions
B18: 2021 | C18: FROM CALCS | D18: =C18/C17 -> #VALUE! | H18: Completed Actions
B19: 2022 | C19: FROM CALCS | D19: =C19/C18 -> #VALUE! | H19: Completed Actions
B20: 2022/2023 | C20: ='2024 Results Graphs'!E84 -> 0 | D20: 0.5 | E20: =C20-C20*D20 -> 0 | H20: Data input - refer to Results
B21: 2030 | C21: =E20 -> 0 | D21: 0.3 | E21: =C21-C21*D21 -> 0 | H21: 50% reduction? - UK target | J21: The UK has set the most ambitious target to reduce carbon emissions by 68% by 2030 compared to 1990 levels – and is the only major economy to have set a target of 77% for 2035
B22: 2031 | C22: =E21 -> 0 | D22: 0.3 | E22: =C22-C22*D22 -> 0 | J22: https://www.gov.uk/government/news/pm-recommits-uk-to-net-zero-by-2050-and-pledges-a-fairer-path-to-achieving-target-to-ease-the-financial-burden-on-british-families#:~:text=The%20UK%20has%20set%20the,target%20of%2077%25%20for%202035.
B23: 2032 | C23: =E22 -> 0 | D23: 0.3 | E23: =C23-C23*D23 -> 0
B24: 2033 | C24: =E23 -> 0 | D24: 0.3 | E24: =C24-C24*D24 -> 0
B25: 2034 | C25: =E24 -> 0 | D25: 0.3 | E25: =C25-C25*D25 -> 0
B26: 2035 | C26: =E25 -> 0 | D26: 0.3 | E26: =C26-C26*D26 -> 0
B27: 2036 | C27: =E26 -> 0 | D27: 0.3 | E27: =C27-C27*D27 -> 0
B28: 2037 | C28: =E27 -> 0 | D28: 0.3 | E28: =C28-C28*D28 -> 0
B29: 2038 | C29: =E28 -> 0 | D29: 0.3 | E29: =C29-C29*D29 -> 0
B30: 2040 | C30: =E29 -> 0 | D30: 0.3 | E30: =C30-C30*D30 -> 0
B31: 2041 | C31: =E30 -> 0 | D31: 0.3 | E31: =C31-C31*D31 -> 0
B32: 2042 | C32: =E31 -> 0 | D32: 0.3 | E32: =C32-C32*D32 -> 0
B33: 2043 | C33: =E32 -> 0 | D33: 0.3 | E33: =C33-C33*D33 -> 0
B34: 2044 | C34: =E33 -> 0 | D34: 0.3 | E34: =C34-C34*D34 -> 0
... B39: 2049 | C39: =E38 -> 0 | D39: 0.3 | E39: =C39-C39*D39 -> 0
B40: 2050 | C40: =E39 -> 0 | D40: 0.3 | E40: =C40-C40*D40 -> 0 | H40: Net Zero | J40: https://www.gov.uk/government/news/pm-recommits-uk-to-net-zero-by-2050-and-pledges-a-fairer-path-to-achieving-target-to-ease-the-financial-burden-on-british-families#:~:text=The%20UK%20has%20set%20the,target%20of%2077%25%20for%202035.
B61: NOTES FOR REPORT
A69: Attach files
A70: Please attach delivery note/receipts/spreadsheets/reports (a sample including the first and the last bill during the period
A78: CLICK HERE TO SUBMIT FOR REVIEW

Sheet BREEAM IN USE Part 2
A1: BIU tracker | B1: 0
A3: Part 2 - Management Performance
A5: Management
A6: Credit issue | B6: Credit name | C6: Question | E6: Credits Available | F6: Answer (mark with a 'X') | G6: Download Template | H6: Attach file
A7: MAN01 | B7: Building user guide | C7: Has relevant information from the building user guide been made accessible to all buiding users? | D7: A- not answered | E7: 0
D8: B- YES | E8: 0
D9: C - NO | E9: 2 | G9: Link to template
A10: MAN02 | B10: Management engagement and feedback | C10: What processes are in place to ensure good communication between building managers, building users, and neighbours? | D10: A - not answered | E10: 0
D11: B - Formal communication between building management and building users | E11: 1
D12: C - Regular meetings between building management and building users | E12: 2
D13: D - Building users are provided with information relating to environmental policies and performance of the asset | E13: 1
D14: E - Proactive engagement with neighbours and community, including a procedure that deals with any complaints relating to the asset and associated operations | E14: 1
D15: F - Occupant satisfaction surveyrs conducted by building management | E15: 2
D16: G - Occupant satisfaction surveys conducted by a third party | E16: 4
A17: MAN03 | B17: Maintenance policies and procedures | C17: Which of the following maintenace policies and procedures are in place? | D17: A - not answered | E17: 0
D18: B - A full set of operations and maintencance (O&M) manuals available and accessible by building management/facilities management staff | E18: 1
D19: C - a proactive maintenance policy/procedure for the external site | E19: 2
D20: D - a proactive maintenance policy/procedure for the building fabric | E20: 2
D21: E - a proactive maintenance policy/procedure for heating, ventilation and cooling (HVAC) sustems, as applicable, and hot water | E21: 2
D22: F - a proactive maintenance policy/procedure for lighting | E22: 2
D23: G - Regular review of the Building Management Systems by suitably qualified staff from the in-house Facilities Management team | E23: 2
D24: H - Regular review of the Building Management System by an accredited third party auditor | E24: 4
A25: MAN04 | B25: Environmental policies and procedures | C25: Has an environmental policy or plan been developed by the building management organisation? | D25: A- not answered | E25: 0
D26: B - the building management organisation has developed and implemented an environmental policy or plan | E26: 2 | G26: Link to template
D27: C - The environmental management policy or plan has been accredited to ISO 14001 or equivalent standards | E27: 2
D28: D - Improvement targets have been set for energy, water and waste/recycling | E28: 2 | G28: Link to template
D29: E - The environmental management policy or plan addresses resilience and climate risks | E29: Exemplary | G29: Link to template
A30: MAN05 | B30: Green lease | C30: Are green lease agreements/contracts with tenants in place? | D30: A - not answered | E30: 0
D31: B - no | E31: 0
D32: C - Yes for >25% of tenants, including sharing of environmental performance data | E32: 1
D33: D - Yes for >25% of tenants, including sharing of environmental performance data and targets for Energy, and Water or Waste reduction | E33: 2
D34: E - Yes for >50% of tenants, including sharing of environmental performance data | E34: 2
D35: F - Yes for >50% of tenants, including sharing of environmental performance data and targets for Energy, and Water use or Waste reduction | E35: 3
D36: G - E - Yes for >75% of tenants, including sharing of environmental performance data | E36: 3
D37: H - Yes for >75% of tenants, including sharing of environmental performance data and targets for Energy, and Water use or Waste reduction | E37: 4
A40: Health and Wellbeing
A41: Credit issue | B41: Credit name | C41: Question | E41: Credits Available | F41: Answer (mark with a 'X')
A42: HEA14 | B42: Thermal Comfort | C42: Is the thermal comfort of asset users in occupied spaces regularly monitored? | D42: A - not answered | E42: 0
D43: B - No | E43: 0
D44: C - Yes, through temperature measurement | E44: 2
D45: D - Yes, through detailed thermal comfort measurement and analysis | E45: 4
D46: E - Yes, through occupant thermal satisfaction surveys | E46: 4
A47: HEA15 | B47: Smoking policy | C47: Is there a policy that prohibits smoking inside the asset and directly outsite of the asset? | D47: A - not answered | E47: 0
D48: B - No | E48: 0
D49: C - Yes | E49: 1
A50: HEA16 | B50: Indoor air quality management | C50: Are there management processes in place to help maintain good level of indoor air quality within the asset? | D50: A - not answered | E50: 0
D51: B - No | E51: 0
D52: C - Yes, provision of information or training to asset users on how to operate and manage the asset's ventilation systems | E52: 1
D53: D - Yes, procedures and plans for cleaning the interior of the asset | E53: 1
D54: E - Yes, procedures and plans for inspecting the cleanliness of an for cleaing ventilation system components | E54: 1
D55: F - Yes, procurement policies and operation and maintenace procedures specify products that have low or no emissions of pollutants to air | E55: 1
D56: G - Yes, procedures and plans for regularly monitoring indoor air quality in occupied spaces | E56: 1
D57: H - Yes, procedures and plans that minimise the impacts on the asset's indoor air quality during maintenace, redecoration, refurbishment or construction activities on the asset | E57: 1
A58: HEA17 | B58: Acoustic conditions | C58: Has the acoustic environment in occupied space been evaluated in terms of sound insulation, indoor ambient noise level and room acoustics? | D58: A - not answered | E58: 0
D59: B - No | E59: 0
D60: C - Sound insulation performance standards are achieved in 50% of occupied space | E60: 1
D61: D - Indoor ambient noise level performance standards are achieved 50% of occupied space | E61: 1
D62: E - Room acoustic performance standards are achieved 50% of occupied space | E62: 1
D63: F - Sound insulation performance standards are achieved in 80% of occupied space | E63: 2
D64: G - Indoor ambient noise level performance standards are achieved 80% of occupied space | E64: 2
D65: H - Room acoustic performance standards are achieved 80% of occupied space | E65: 2
A66: HEA18 | B66: Legionella risk management | C66: Has an assessment of the asset's water systmes been performed to identify the potential risk of exposure to legionella bacteria and, if so, are management processes in place to prevent or control the risk? | D66: A - not answered | E66: 0
D67: B - No | E67: 0
D68: C - Yes | E68: 4
A69: HEA19 | B69: Drinking water management | C69: Are the number and location of drinking water outlets regularly reviewed? | D69: A - not answered | E69: 0
D70: B - No | E70: 0
D71: C - Yes | E71: 2
A74: Energy
A75: Credit issue | B75: Credit name | C75: Question | E75: Units | F75: Start date | G75: End date | H75: Amount | J75: Provide Breakdown | K75: Amount | L75: Unit
A76: Ene19 | B76: Energy consumption | C76: Annually, how much energy is consumed by the asset in kWh per year (as metered in the reporting period)? Please enter date of the annual reporting period for consumption data. | D76: Grid supply electricity | E76: kWh/year | H76: ='2 Input data Summary SQ'!H3 -> 0 | I76: 2023 data | J76: Heated swimming pools On-site laundry Gym Restaurants Casino | L76: kWh/year
D77: Natural gas | E77: kWh/year | H77: ='2 Input data Summary SQ'!H4 -> 0 | I77: 2023 data
D78: Burning oil/kerosene | E78: kWh/year
D79: Gas oil | E79: kWh/year
D80: Fuel oil | E80: kWh/year
D81: Diesel | E81: kWh/year
D82: Petrol | E82: kWh/year
D83: LPG | E83: kWh/year
D84: Other petroleum gas | E84: kWh/year
D85: Coal | E85: kWh/year
D86: Biodiesel | E86: kWh/year
D87: Landfill gas | E87: kWh/year
D88: Other biogas | E88: kWh/year
D89: Wood | E89: kWh/year
... D92: Disctrict cooling | E92: kWh/year
A93: Ene20 | B93: Carbon intensity district heating and cooling | C93: 1 - If known, what is the carbon intensity of the district heating system in KgCO2eq/kWh delivered heat? | D93: - | E93: KgCO2eq/kWh
C94: 2 - If known, what is the carbon intensity of the district heating system in KgCO2eq/kWh delivered cooling? | D94: - | E94: KgCO2eq/kWh
A95: Ene21 | B95: Renewable electricity generated | C95: 1 - What is the quantity of electricity generated by on-site and community renewable energy schemes in kWh per year (as metered in the reporting period)? | D95: - | E95: kWh/year
C96: 2 - What is the net quantity of electricity exported off site in kWh per year (as metered in the reporting period)? | D96: - | E96: KWh/year
A97: Ene22 | B97: Energy Audit | C97: Has an energy audit been carried out for the asset? | D97: A - not answered | E97: 0
D98: B- no energy audit has been carried out | E98: 0
D99: C - Yes, an energy audit has been carried out | E99: 2
D100: D - Yes, an energy audit has been carried out, and all measures with a payback time of 5 years or less have been implemented. | E100: 3
D101: E - Yes, an energy audit has been carried out, and all measures with a payback time of 10 years or less have been implemented. | E101: 4
A102: Ene23 | B102: Energy consumption reporting | C102: What happned to asset energy consumption data? | D102: A - not answered | E102: 0
D103: B - asset energy consumption data not collected. | E103: 0
D104: C - Asset energy consumption data collected and compared against asset targets | E104: 2
D105: D - Asset energy consumption data collected and compared against asset targets and reported on internally | E105: 3 | G105: Link to template
D106: E - Asset energy consumption data collected and compared against asset targets and reported on internally and published in an annual public report | E106: 4
A107: Ene24 | B107: Reduction of carbon emissions | C107: What has been the average annual reduction in CO2 emissions of the asset over the last 3 years? | D107: A - ≥5% | E107: 1
D108: B - ≥10% | E108: 2
...

Sheet Eco Audit action plan
A4: Date of the Eco Audit
A5: Name of the Eco Auditor
A9: Priority | B9: Further Action | C9: Cost Implication | D9: Impact | E9: SDG | F9: Date | G9: Progress
A10: Environmental and Procurement Policy
A11: Short Term | B11: Develop the Environmental Policy in full and ensure it is reviewed annually. | C11: £ | D11: High
A12: Short Term | B12: Communicate to the public on any outcomes/improvements in sustainability practices, on the website or in annual reports. | C12: £ | D12: Low
A13: Ongoing | B13: Appoint a dedicated individual to oversee ethical purchases and purchase certified items. | C13: ££ | D13: Medium
A15: Energy
A16: Ongoing | B16: Monitor energy consumption in the form of a spreadsheet or through bills. | C16: £ | D16: High
A17: Medium Term | B17: Replace single-glazed windows with double-glazed windows. | C17: ££££ | D17: Low
A18: Medium Term | B18: Integrate PIR systems on all appropriate lights. | C18: ££££ | D18: Medium
A19: Medium Term | B19: Replace all lights with LED bulbs. | C19: £££ | D19: High
A20: Short Term | B20: Carry out pre-feasibility studies for solar panels. | C20: £ | D20: Low
A21: Waste
A22: Ongoing | B22: Monitor the waste generation of the charity consistently and accurately. | C22: £ | D22: High
A23: Short Term | B23: Place recycling bins in all spaces. | C23: ££ | D23: Low
A24: Short Term | B24: Increase labelling of waste bins. | C24: £ | D24: Medium
A25: Water
A26: Long Term | B26: Ensure that all water appliances throughout all buildings are water efficient. | C26: £ | D26: High
A27: Ongoing | B27: Consider starting to monitor water consumption and wastewater through online spreadsheets. | C27: £ | D27: Low
A28: Health and Wellbeing
A29: Medium Term | B29: Increase indoor plants throughout all spaces. | C29: ££ | D29: High
A30: Short Term | B30: Investigate the addition of a green roof. | C30: £ | D30: Low
A31: Medium Term | B31: Implement Circadian lighting in the appropriate areas. | C31: £££ | D31: High
A32: Travel
A33: Medium Term | B33: Install bicycle storage. | C33: ££ | D33: High
A34: Short Term | B34: Carry out a travel survey to have a better understanding of how staff and visitors travel to the centre. | C34: £ | D34: Low
A35: ADD TAILOR MADE SECTION FOR SPECIFIC ORGANISATION
A37: to include the cost implication (we may need explain £, ££, £££, ££££, £££££)
A38: to include the SDG for each section
A41: CLICK HERE TO SUBMIT FOR REVIEW

Sheet Offset - live projects
A2: Offset
A4: Based on the available data, this report assesses the total emissions of
A6: ='1x2 Carbon Emissions KgCO2e SQ'!H197 -> 0 | B6: tonnes of CO2e. during the period of
A7: ='1x2 Carbon Emissions KgCO2e SQ'!H193 -> 2023
A9: The emissions can be offset through chossing one of the proposed strategies below to achieve Carbon Neutrality.
A13: Projects to Offset
A15: Verified Carbon Standard (VCS)
A17: The Verified Carbon Standard (VCS) is an offset certification program managed by Verra. It is a widely supported, with projects worldwide. VCS is focused wholly on removing and reducing greenhouse gas (GHG) emissions, and there are strict guidelines that projects have to meet to be verified under the VCS program.
A19: The VCS issues a Voluntary Carbon Unit (VCU) to approved programs, and an awarded VCU represents the removal or reduction of one tonne of GHG emissions. These VCUs are what we purchase on the global carbon market and allocate to you when you purchase a carbon offset.
A21: The basic criteria for an approved project include:
A22: Real: all GHG emission reduction or removal by the project must be proven to have genuinely taken place.
A23: Measurable: emissions reductions or removal must be measured and quantified using accurate measurement methods against a credibly established baseline.
A24: Additional: all GHG removals and reductions should be over an established baseline to ensure that any removals or reductions are because of the project being in place.
A25: Conservative: in case of any uncertainty in measurement, lower values will be recorded and used to ensure there is no over-estimation of VCUs.
A26: Independently audited: an accredited team with experience in the relevant field and country needs to verify all GHG emission reductions and removals.
A27: Transparent: all data collected and recorded should be appropriately disclosed to the public so that users can make informed decisions with confidence. This information about each project is available in the Verra Project registry, along with a list of all VCS certified projects.
... A32: Potential offset project from Verified Carbon Standard (VCS):
A34: Project name | B34: Housing Decarbonisation in the UK | C34: OPTION 2 Housing Decarbonisation in the UK | D34: OPTION 3 Housing Decarbonisation in the UK
A35: Project description | B35: This project facilitates the decarbonisation of housing stock in the United Kingdom. Emission reductions are generated by reductions in fossil fuel consumption in dwellings that are decarbonised compared to baseline consumption. The aggregated emissions from fossil fuel consumption of dwellings in the United Kingdom make up a significant component of greenhouse gas emissions; they also pose a significant opportunity to reduce real emissions. | C35: This project facilitates the decarbonisation of housing stock in the United Kingdom. Emission reductions are generated by reductions in fossil fuel consumption in dwellings that are decarbonised compared to baseline consumption. The aggregated emissions from fossil fuel consumption of dwellings in the United Kingdom make up a significant component of greenhouse gas emissions; they also pose a significant opportunity to reduce real emissions. | D35: This project facilitates the decarbonisation of housing stock in the United Kingdom. Emission reductions are generated by reductions in fossil fuel consumption in dwellings that are decarbonised compared to baseline consumption. The aggregated emissions from fossil fuel consumption of dwellings in the United Kingdom make up a significant component of greenhouse gas emissions; they also pose a significant opportunity to reduce real emissions.
A36: Link | B36: https://registry.verra.org/app/projectDetail/VCS/2649 | C36: https://registry.verra.org/app/projectDetail/VCS/2649 | D36: https://registry.verra.org/app/projectDetail/VCS/2649
A38: Mark here your option
A41: Gold Standard Verified Reduction (VERs)
A43: The Gold Standard was developed in 2003 by the World Wide Fund for Nature (WWF). It is an international offset program administered by the Gold Standard Foundation based in Geneve, Switzerland. Compared to the VCS, the Gold Standard has additional requirements when certifying a project. The requirements for a Gold Standard certification are:
A44: The project should reduce or remove one of the three eligible GHGs: methane, carbon dioxide, and nitrous oxide. The measurement of this removal has similar criteria to that of the VCS outlined above.
A45: The project should be achieving its goal by supplying renewable energy, reducing end-user energy usage, afforestation, reforestation, or agriculture.
A46: The project should not be applying for another certification to prevent double counting.
A47: The additional GHC emission reduction or removal should be documented and should be occurring because of the project.
A48: The project should be contributing to at least three of the Sustainable Development Goals
A50: The final assessment criterium is particularly important. It means that in addition to reducing or removing GHG emissions, a Gold Standard certified project also benefits the local population’s financial, social, and environmental outcomes.
A52: Potential offset projects from Gold Standard Renewable Energy Projects (VERs) are presented below.
A54: Project name | B54: FPD Robotic E-Waste Recycling Project | C54: 30 MW Wind Power Project at Surajbari, Guajarat in India | D54: BK Energia Itacoatiara Project
A55: Project description | B55: FPD will work locally in the collection of E-waste and segregate them through an automated robotic arm developed by FPD. After segregation, the components are then processed to separate metals and plastics which are used as replacements for virgin materials in new production units. This project is implemented in the host country-United Kingdom. | C55: The proposed project activity comprises of installation and operation of fifty (50) numbers of 600 kW Wind Electricity Generators (WEGs) having a combined wind power generation capacity of 30 MW at Surajbari creek covering Chandrodi, Khodasar, Rajasthali and Naransari villages of Kutch district in Gujarat state, India. The annual estimated energy generation out of the project activity is about 60,444 MWh. | D55: The project generates electricity with a thermoelectric power plant (see picture below) using wood waste from an FSC1-certified forest and a wood processing company in the city of Itacoatiara, in the State of Amazonas, Brazil. The electricity is generated with a high-pressure boiler (42 bar – 420° C) and a multiple-stage condensing steam turbine coupled with a 9 MWelt generator.
A57: Link | B57: https://registry.goldstandard.org/projects/details/3584 | C57: https://registry.goldstandard.org/projects/details/2603 | D57: https://registry.goldstandard.org/projects/details/1181
A60: Please Mark here your option
A65: Carbon Neutrality
A66: Carbon neutrality means having a balance between emitting carbon and absorbing carbon from the atmosphere in carbon sinks. Removing carbon oxide from the atmosphere and then storing it is known as carbon sequestration. In order to achieve net zero emissions, all worldwide greenhouse gas (GHG) emissions will have to be counterbalanced by carbon sequestration.
A68: Carbon sink is any system that absorbs more carbon than it emits. The main natural carbon sinks are soil, forests and oceans. According to estimates, natural sinks remove between 9.5 and 11 Gt of CO2 per year. Annual global CO2 emissions reached 36.0 Gt in 2020.
A70: To date, no artificial carbon sinks are able to remove carbon from the atmosphere on the necessary scale to fight global warming.
A72: The carbon stored in natural sinks such as forests is released into the atmosphere through forest fires, changes in land use or logging. This is why it is essential to reduce carbon emissions in order to reach climate neutrality.

Sheet 2024 Results Graphs
A4: Calculation | B4: 2024
B7: SCOPE 1 | D7: SCOPE 2 | F7: SCOPE 3
A8: KG CO2e | B8: =F81 -> 0 | D8: =F82 -> 0 | F8: =F83 -> 1395.0719
B25: 2024
B26: Energy | C26: Water | D26: Waste | E26: Transport | F26: Refrigerants | G26: Home Working | H26: Hotel Stay (UK) | I26: Materials Use
B27: =F52 -> 0 | C27: =F53 -> 0 | D27: =F54 -> 0 | E27: =F55 -> 0 | F27: =F56 -> 0 | G27: =F57 -> 1395.0719 | H27: =F58 -> 0 | I27: =F59 -> 0
B42: 2024 Renewable energy Generation
B43: ='1x2 Carbon Emissions KgCO2e SQ'!I10 -> 0 | C43: KG CO2e saved
A49: Annual summary KG of CO2e
B51: 2020 | C51: 2021 | D51: 2022 | E51: 2023 | F51: 2024
A52: Energy | B52: ='1x2 Carbon Emissions KgCO2e SQ'!E183 -> 0 | C52: ='1x2 Carbon Emissions KgCO2e SQ'!F183 -> 0 | D52: ='1x2 Carbon Emissions KgCO2e SQ'!G183 -> 0 | E52: ='1x2 Carbon Emissions KgCO2e SQ'!H183 -> 0 | F52: ='1x2 Carbon Emissions KgCO2e SQ'!I183 -> 0
A53: Water | B53: ='1x2 Carbon Emissions KgCO2e SQ'!E184 -> 0 | C53: ='1x2 Carbon Emissions KgCO2e SQ'!F184 -> 0 | D53: ='1x2 Carbon Emissions KgCO2e SQ'!G184 -> 0 | E53: ='1x2 Carbon Emissions KgCO2e SQ'!H184 -> 0 | F53: ='1x2 Carbon Emissions KgCO2e SQ'!I184 -> 0
A54: Waste | B54: ='1x2 Carbon Emissions KgCO2e SQ'!E185 -> 0 | C54: ='1x2 Carbon Emissions KgCO2e SQ'!F185 -> 0 | D54: ='1x2 Carbon Emissions KgCO2e SQ'!G185 -> 0 | E54: ='1x2 Carbon Emissions KgCO2e SQ'!H185 -> 0 | F54: ='1x2 Carbon Emissions KgCO2e SQ'!I185 -> 0
A55: Transport | B55: ='1x2 Carbon Emissions KgCO2e SQ'!E186 -> 0 | C55: ='1x2 Carbon Emissions KgCO2e SQ'!F186 -> 0 | D55: ='1x2 Carbon Emissions KgCO2e SQ'!G186 -> 0 | E55: ='1x2 Carbon Emissions KgCO2e SQ'!H186 -> 0 | F55: ='1x2 Carbon Emissions KgCO2e SQ'!I186 -> 0
A56: Refrigerants | B56: ='1x2 Carbon Emissions KgCO2e SQ'!E187 -> 0 | C56: ='1x2 Carbon Emissions KgCO2e SQ'!F187 -> 0 | D56: ='1x2 Carbon Emissions KgCO2e SQ'!G187 -> 0 | E56: ='1x2 Carbon Emissions KgCO2e SQ'!H187 -> 0 | F56: ='1x2 Carbon Emissions KgCO2e SQ'!I187 -> 0
A57: Home Working | B57: ='1x2 Carbon Emissions KgCO2e SQ'!E188 -> 0 | C57: ='1x2 Carbon Emissions KgCO2e SQ'!F188 -> 0 | D57: ='1x2 Carbon Emissions KgCO2e SQ'!G188 -> 0 | E57: ='1x2 Carbon Emissions KgCO2e SQ'!H188 -> 0 | F57: ='1x2 Carbon Emissions KgCO2e SQ'!I188 -> 1395.0719
A58: Hotel Stay (UK) | B58: ='1x2 Carbon Emissions KgCO2e SQ'!E189 -> 0 | C58: ='1x2 Carbon Emissions KgCO2e SQ'!F189 -> 0 | D58: ='1x2 Carbon Emissions KgCO2e SQ'!G189 -> 0 | E58: ='1x2 Carbon Emissions KgCO2e SQ'!H189 -> 0 | F58: ='1x2 Carbon Emissions KgCO2e SQ'!I189 -> 0
A59: Materials Use | B59: ='1x2 Carbon Emissions KgCO2e SQ'!E190 -> 0 | C59: ='1x2 Carbon Emissions KgCO2e SQ'!F190 -> 0 | D59: ='1x2 Carbon Emissions KgCO2e SQ'!G190 -> 0 | E59: ='1x2 Carbon Emissions KgCO2e SQ'!H190 -> 0 | F59: ='1x2 Carbon Emissions KgCO2e SQ'!I190 -> 0
A60: Total | B60: =SUM(B52:B59) -> 0 | C60: =SUM(C52:C59) -> 0 | D60: =SUM(D52:D59) -> 0 | E60: =SUM(E52:E59) -> 0 | F60: =SUM(F52:F59) -> 1395.0719
A80: Carbon Emissions Scope Summary | B80: 2020 | C80: 2021 | D80: 2022 | E80: 2023 | F80: 2024
A81: Scope 1 | B81: ='1x2 Carbon Emissions KgCO2e SQ'!E194 -> 0 | C81: ='1x2 Carbon Emissions KgCO2e SQ'!F194 -> 0 | D81: ='1x2 Carbon Emissions KgCO2e SQ'!G194 -> 0 | E81: ='1x2 Carbon Emissions KgCO2e SQ'!H194 -> 0 | F81: ='1x2 Carbon Emissions KgCO2e SQ'!I194 -> 0
A82: Scope 2 | B82: ='1x2 Carbon Emissions KgCO2e SQ'!E195 -> 0 | C82: ='1x2 Carbon Emissions KgCO2e SQ'!F195 -> 0 | D82: ='1x2 Carbon Emissions KgCO2e SQ'!G195 -> 0 | E82: ='1x2 Carbon Emissions KgCO2e SQ'!H195 -> 0 | F82: ='1x2 Carbon Emissions KgCO2e SQ'!I195 -> 0
A83: Scope 3 | B83: ='1x2 Carbon Emissions KgCO2e SQ'!E196 -> 0 | C83: ='1x2 Carbon Emissions KgCO2e SQ'!F196 -> 0 | D83: ='1x2 Carbon Emissions KgCO2e SQ'!G196 -> 0 | E83: ='1x2 Carbon Emissions KgCO2e SQ'!H196 -> 0 | F83: ='1x2 Carbon Emissions KgCO2e SQ'!I196 -> 1395.0719
A84: Total | B84: =SUM(B81:B83) -> 0 | C84: =SUM(C81:C83) -> 0 | D84: =SUM(D81:D83) -> 0 | E84: =SUM(E81:E83) -> 0 | F84: =SUM(F81:F83) -> 1395.0719
A102: GRI Carbon Emission Criteria Confirmation for Scope 1, Scope 2 and Scope 3
A103: 2. Gases included in the calculation | B103: CO2e
A104: 3. Base year for the calculation, including: the rationale for choosing it; emissions in the base year; the context for any signficiant changes in emissions that triggered reculculations of base year emissions. | B104: ='Assessment Scope'!L20 -> 0
A105: 4. Source of emission factors. | B105: GOV UK
A106: 5. Standards, methodologies, assumptions, and/or calculation tools used. | B106: The GHG Protocol was used in consultation with the UK Government's Conversion Factors. The methodology was as follows: (1) Input data in relevant units; (2) Covert to all appropriate units (e.g., bags -> litre -> kilograms; miles -> kms); (3) Multiply the data by the UK Government's Conversion Factors. The sources of the Scottish Environmental Protection Agency were consulted to convert bags to litres to kilograms/
A110: 2024 Summary
A111: Scope | B111: Carbon Emission Source | C111: Input Data | D111: Input Data Unit | F111: Carbon Emissions (KgCO2e)
A112: 1 | B112: Natural gas used for company facilities | C112: ='2 Input data Summary SQ'!H4 -> 0 | D112: kWh | F112: ='1x2 Carbon Emissions KgCO2e SQ'!H4 -> 0
B113: Refrigerants | C113: =SUM('2 Input data Summary SQ'!H157:H163) -> 0 | D113: KG | F113: =SUM('1x2 Carbon Emissions KgCO2e SQ'!H157:H163) -> 0
B114: Company fleet & leased vehicles | C114: =SUM('2 Input data Summary SQ'!H127:H156) -> 0 | D114: Km | F114: =SUM('1x2 Carbon Emissions KgCO2e SQ'!H127:H156) -> 0
A115: 2 | B115: Electricity used for company facilities (incl. Transmission losses) | C115: ='2 Input data Summary SQ'!H3+'2 Input data Summary SQ'!H7 -> 0 | D115: kWh | F115: ='1x2 Carbon Emissions KgCO2e SQ'!H3+'1x2 Carbon Emissions KgCO2e SQ'!H7 -> 0
B116: Private vehicle for business use | C116: =SUM('2 Input data Summary SQ'!H111:H126) -> 0 | D116: Km | F116: =SUM('1x2 Carbon Emissions KgCO2e SQ'!H111:H126) -> 0
A117: 3 | B117: Business travel | C117: =SUM('2 Input data Summary SQ'!H17:H56) -> 0 | D117: Km | F117: =SUM('1x2 Carbon Emissions KgCO2e SQ'!H17:H56) -> 0
B118: Staff commute | C118: =SUM('1x2 Carbon Emissions KgCO2e SQ'!H71:H110) -> 0 | D118: Km | F118: =SUM('1x2 Carbon Emissions KgCO2e SQ'!H71:H110) -> 0
B119: Freighting goods | C119: =SUM('1x2 Carbon Emissions KgCO2e SQ'!H57:H70) -> 0 | D119: Km | F119: =SUM('1x2 Carbon Emissions KgCO2e SQ'!H57:H70) -> 0
B120: Water (consumption and wastewater) | C120: =SUM('2 Input data Summary SQ'!H11:H12) -> 0 | D120: M3 | F120: =SUM('1x2 Carbon Emissions KgCO2e SQ'!H11:H12) -> 0
B121: Waste (landfill, paper, compost, energy etc) | C121: =SUM('1x2 Carbon Emissions KgCO2e SQ'!H13:H16) -> 0 | D121: KG | F121: =SUM('1x2 Carbon Emissions KgCO2e SQ'!H13:H16) -> 0
B122: Hotel Stay (UK) | C122: =SUM('2 Input data Summary SQ'!H165:H166) -> 0 | F122: =SUM('1x2 Carbon Emissions KgCO2e SQ'!H165:H166) -> 0
B123: Home working | C123: ='2 Input data Summary SQ'!H164 -> 0 | D123: Hours | F123: ='1x2 Carbon Emissions KgCO2e SQ'!H164 -> 0
A125: Total gross CO2 Emissions (KgCO2e) | E125: =SUM(F112:F123) -> 0
A128: Quantified | B128: Non-Quanfied
A129: ='Assessment Scope'!C15 -> Yes | B129: ='Assessment Scope'!C15 -> Yes | C129: If marked Yes should show in the Quantified - if marked Non should show in the non-quantified
A130: ='Assessment Scope'!C16 -> yes | B130: ='Assessment Scope'!C16 -> yes
A131: ='Assessment Scope'!C17 -> No | B131: ='Assessment Scope'!C17 -> No
A132: ='Assessment Scope'!C18 -> Yes | B132: ='Assessment Scope'!C18 -> Yes
A133: ='Assessment Scope'!C19 -> No | B133: ='Assessment Scope'!C19 -> No
A134: ='Assessment Scope'!C20 -> No | B134: ='Assessment Scope'!C20 -> No
A135: ='Assessment Scope'!C21 -> Yes | B135: ='Assessment Scope'!C21 -> Yes
A136: ='Assessment Scope'!C22 -> No | B136: ='Assessment Scope'!C22 -> No
A137: ='Assessment Scope'!C23 -> 0 | B137: ='Assessment Scope'!C23 -> 0
A141: PRINT REPORT
A143: SUBMIT FOR REVIEW
A148: ANUAL DATA GRAPHS
A149: Category | B149: Baseline year | C149: year ??? | D149: year ??? | E149: Current emissions | F149: ...
B150: 2022/23 (kilograms CO2e) | C150: year?? (kilograms CO2e) | D150: year?? (kilograms CO2e) | E150: 2023/24 (kilogramsCO2e) | F150: year?? (kilograms CO2e)
A151: Gas
A152: Electricity
A153: Water Consumption
A154: Wastewater
A155: Waste to energy
A156: Staff Commuting
A183: Reporting Requirements in terms of GRI and Carbon Emissions:
A185: We need to include the following information for Scope 1: | B185: 2020 | C185: 2021 | D185: 2022 | E185: 2023
A186: 1. Gross direct Scope 1 GHG emissions in metric tons of CO2 equivalent | B186: ='2024 Results Graphs'!B262 -> 0 | C186: ='2024 Results Graphs'!C262 -> 0 | D186: ='2024 Results Graphs'!D262 -> 0 | E186: ='2024 Results Graphs'!E262 -> 0
A187: 2. Gases included in the calculation | B187: CO2e
A188: 3. Base year for the calculation, including: the rationale for choosing it; emissions in the base year; the context for any signficiant changes in emissions that triggered reculculations of base year emissions. | B188: ='Assessment Scope'!L201 -> 0
A189: 4. Source of emission factors. | B189: GOV UK | F189: There are references at the end of each year's CF's methodology. We could provide the link here and it would satisfy the next point as well. https://assets.publishing.service.gov.uk/media/647f50dd103ca60013039a8a/2023-ghg-cf-methodology-paper.pdf (2023)
A190: 5. Standards, methodologies, assumptions, and/or calculation tools used. | B190: The GHG Protocol was used in consultation with the UK Government's Conversion Factors. The methodology was as follows: (1) Input data in relevant units; (2) Covert to all appropriate units (e.g., bags -> litre -> kilograms; miles -> kms); (3) Multiply the data by the UK Government's Conversion Factors. The sources of the Scottish Environmental Protection Agency were consulted to convert bags to litres to kilograms/
A192: We need to include the following information for Scope 2:
A193: 1. Gross location-based energy indirect (Scope 2) GHG emissions in metric tons of CO2 equivalent. | B193: ='2024 Results Graphs'!B263 -> 0 | C193: ='2024 Results Graphs'!C263 -> 0 | D193: ='2024 Results Graphs'!D263 -> 0 | E193: ='2024 Results Graphs'!E263 -> 0
A194: 2. The gases included in the calculation. | B194: CO2e
A195: 3. Base year for the calculation, including: the rationale for choosing it; emissions in the base year; the context for any signficiant changes in emissions that triggered reculculations of base year emissions. | B195: ='Assessment Scope'!L201 -> 0
A196: 4. Source of emission factors. | B196: GOV UK
A197: 5. Standards, methodologies, assumptions, and/or calculation tools used. | B197: The GHG Protocol was used in consultation with the UK Government's Conversion Factors. The methodology was as follows: (1) Input data in relevant units; (2) Covert to all appropriate units (e.g., bags -> litre -> kilograms; miles -> kms); (3) Multiply the data by the UK Government's Conversion Factors. The sources of the Scottish Environmental Protection Agency were consulted to convert bags to litres to kilograms/
A199: We need to include the following information for Scope 3:
A200: 1. Gross other indirect (Scope 3) GHG emissions in metric tons of CO2 equivalent. | B200: ='2024 Results Graphs'!B264 -> 0 | C200: ='2024 Results Graphs'!C264 -> 0 | D200: ='2024 Results Graphs'!D264 -> 0 | E200: ='2024 Results Graphs'!E264 -> 0
A201: 2. Gases included in the calculation | B201: CO2e
A202: 3. Base year for the calculation, including: the rationale for choosing it; emissions in the base year; the context for any signficiant changes in emissions that triggered reculculations of base year emissions. | B202: ='Assessment Scope'!L201 -> 0
A203: 4. Source of emission factors. | B203: GOV UK
A204: 5. Standards, methodologies, assumptions, and/or calculation tools used. | B204: The GHG Protocol was used in consultation with the UK Government's Conversion Factors. The methodology was as follows: (1) Input data in relevant units; (2) Covert to all appropriate units (e.g., bags -> litre -> kilograms; miles -> kms); (3) Multiply the data by the UK Government's Conversion Factors. The sources of the Scottish Environmental Protection Agency were consulted to convert bags to litres to kilograms/
A206: We need to state that at this time there are no relevant GHG emissions intensity ratios for the organisation. | B206: Please write a standard statement to be used on all reports
A208: We need to include the following information for the reduction of GHG emissions
A209: 1. GHG emissions reduced as a direct result of reduction initiatives, in metric tons of CO2 equivalent. This might only be revelant in review audits and so in first time reports we need to specifically say that because we are quantifying GHG emissions for the first time there are no reductions. | C209: ='Carbon Reduction Plan'!F199 -> 0 | D209: ='Carbon Reduction Plan'!F200 -> 0 | E209: ='Carbon Reduction Plan'!F201 -> 0 | F209: Link to CRP - carbon reduction plan measures
A210: 2. Gases included in the calculation | B210: CO2e
A211: 3. Base year for the calculation including the rationale for choosing it. | B211: ='Assessment Scope'!L201 -> 0
A212: 4. Scopes in which the reductions took place. | F212: Check CRP - Carbon reduction scope
A213: 5. Standards, methodologies, assumptions, and/or calculation tools used. | B213: The GHG Protocol was used in consultation with the UK Government's Conversion Factors. The methodology was as follows: (1) Input data in relevant units; (2) Covert to all appropriate units (e.g., bags -> litre -> kilograms; miles -> kms); (3) Multiply the data by the UK Government's Conversion Factors. The sources of the Scottish Environmental Protection Agency were consulted to convert bags to litres to kilograms/
A215: Confirmation to state that the orgnisation does not utilised any ozone-depletio substances (ODS) | B215: As of January 2010, in line with the Montreal Protocol, ODS were prohibted and severely controlled. As such this organisation has no affiliation or use with these substances and are committed to reduce atmospheric emissions in this way.
A217: We need to include the following information for Nox, Sox, and other significant air emissions: (I doubt this one will be possible) | B217: At this point the NOx, SOx, and other significant air emissions are not included as a result of a lack of data.
A218: 1. Significant air emissions, in kgs or multiples of: Nox, Sox, POP, VOC, HAP, PM, other standard categories of air emissions identified in relevant regulations.
A219: 2. Source of emission factors. | B219: GOV
A220: 3. Standards, methodologies, assumptions, and/or calculation tools used. | B220: The GHG Protocol was used in consultation with the UK Government's Conversion Factors. The methodology was as follows: (1) Input data in relevant units; (2) Covert to all appropriate units (e.g., bags -> litre -> kilograms; miles -> kms); (3) Multiply the data by the UK Government's Conversion Factors. The sources of the Scottish Environmental Protection Agency were consulted to convert bags to litres to kilograms/

Sheet Carbon Reduction Plan Report
A3: Carbon Reduction Plan
A4: This carbon Reduction Plan complies with the PPN0621 Carnon Reduction Plan
A6: Organisation name: | B6: ='General Info'!C14 -> 0
A7: Publication date:
A9: Commitment to achieving Net Zero
A10: =B6 -> 0 | B10: is committed to achieving Net Zero emissions by | F10: ='Assessment Scope'!C14 -> 0
A12: Baseline Emissions Footprint
A14: Baseline emissions are a record of the greenhouse gases that have been produced in the past and were produced prior to the introduction of any strategies to reduce emissions. Baseline emissions are the reference point against which emissions reduction can be measured.
A16: Baseline Year | B16: ='Assessment Scope'!C13 -> 0
A18: ='Assessment Scope'!D13 -> Add commentary regarding your Baseline Emissions as required: e.g. historic baseline which deviates from the requirements under this measure (e.g. no prior Scope 3 emissions reporting), where there is no previous reporting and the creation of a new baseline due to substantial organisational change or restructuring]
A20: Baseline Year Emissions
A21: Scope 1 | B21: Baseline year results on tab1x2 Carbon Emissions KgCO2e - Convert to Tonnes of CO2e
A22: Scope 2 | B22: Baseline year results on tab1x2 Carbon Emissions KgCO2e - Convert to Tonnes of CO2e
A23: Scope 3 (included sources) | B23: Baseline year results on tab1x2 Carbon Emissions KgCO2e - Convert to Tonnes of CO2e
A24: Total Emissions | B24: =SUM(B21:B23) -> 0 | C24: tCO2e
A26: Current Year Emissions
A27: Scope 1 | B27: Current (2023) year results on tab1x2 Carbon Emissions KgCO2e - Convert to Tonnes of CO2e
A28: Scope 2 | B28: Current (2023) year results on tab1x2 Carbon Emissions KgCO2e - Convert to Tonnes of CO2e
A29: Scope 3 (included sources) | B29: Current (2023) year results on tab1x2 Carbon Emissions KgCO2e - Convert to Tonnes of CO2e
A30: Total Emissions | B30: =SUM(B27:B29) -> 0 | C30: tCO2e
A33: Emissions reduction targets
A35: In order to continue our progress to achieving Net Zero, we have adopted the following carbon reduction targets.
A36: We project that carbon emissions will decrease over the next five years to | G36: tCO2e by
A37: =F10 -> 0 | B37: This is a reduction of | E37: %
A39: Progress against these targets can be seen in the graph below:
A42: GRAPH FROM CARBON EMISSIONS REDUCTION - NEEDS TO SHOW PROJECTED VS ACTUAL - EXAMPLE BELOW
A52: Carbon Reduction Projects
A54: Completed Carbon Reduction Initiatives
A55: The following environmental management measures and projects have been completed or implemented since the
A56: =B16 -> 0 | B56: baseline. The carbon emission reduction achieved by these schemes equate to
A57: XX | B57: tCO2e, a | C57: XX | D57: % reduction against the | F57: 20XX | G57: baseline
A58: and the measures will be in effect when performing the contract.
A61: Declaration and Sign Off
A62: This Carbon Reduction Plan has been completed in accordance with PPN 06/21 and associated guidance and reporting standard for Carbon Reduction Plans.
A63: Emissions have been reported and recorded in accordance with the published reporting standard for Carbon Reduction Plans and the GHG Reporting Protocol corporate standard[1] and uses the appropriate Government emission conversion factors for greenhouse gas company reporting[2].
A64: Scope 1 and Scope 2 emissions have been reported in accordance with SECR requirements, and the required subset of Scope 3 emissions have been reported in accordance with the published reporting standard for Carbon Reduction Plans and the Corporate Value Chain (Scope 3) Standard[3].
A65: This Carbon Reduction Plan has been reviewed and signed off by the board of directors (or equivalent management body).
A67: Signed on behalf of the Supplier:
A69: Signature
A71: Date
A74: Reference
A75: [1]https://ghgprotocol.org/corporate-standard
A76: [2]https://www.gov.uk/government/collections/government-conversion-factors-for-company-reporting
... A83: SUBMIT FOR REVIEW

Sheet 1 Conversion Factor UK SQ
E1: Conv 2020 | F1: Conv 2021 | G1: Conv 2022 | H1: Conv 2023 | I1: Conv 2024
B2: Scope (1, 2, 3) | D2: Source
A3: Energy | B3: 2 | D3: Electricity | E3: 0.23314 | F3: 0.21233 | G3: 0.19338 | H3: 0.207074 | J3: kg CO2e/kWh | L3: T&D - UK electricity 2023&2022 = 0.01792 kg CO2e/kWh; 0.01879 in 2021
B4: 1 | D4: Gas | E4: 0.20374 | F4: 0.20297 | G4: 0.20227 | H4: 0.20267142 | J4: kg CO2e/kWh
B5: 1 | D5: Diesel | E5: 0.25568 | F5: 0.25165 | G5: 0.25631 | H5: 0.25409276 | J5: kg CO2e/kWh
B6: 1 | D6: Oil | E6: 0.2731 | F6: 0.27318 | G6: 0.27319 | H6: 0.27287699 | J6: kg CO2e/kWh
B7: 3 | D7: Transmission and distribution - T&D- UK electricity | E7: 0.02005 | F7: 0.01879 | G7: 0.01769 | H7: 0.017915111 | J7: kg CO2e/kWh | K7: Page 26 clarifies the transmission and distribution losses. https://assets.publishing.service.gov.uk/media/647f50dd103ca60013039a8a/2023-ghg-cf-methodology-paper.pdf#page27
B8: 3 | D8: Transmission and distribution - Distribution - district heat & steam | E8: 0.00908 | F8: 0.00899 | G8: 0.00899 | H8: 0.0094538779 | J8: kg CO2e/kWh
D9: Converstion factor - Other (i.e district heating) | E9: =Energy!B12 -> 0 | F9: =Energy!C12 -> 0 | G9: =Energy!D12 -> 0 | H9: =Energy!E12 -> 0 | J9: kg CO2e/kWh
B10: 1 | D10: On site energy generation (PV) | E10: =-E3 -> -0.23314 | F10: =-F3 -> -0.21233 | G10: =-G3 -> -0.19338 | H10: =-H3 -> -0.207074 | J10: kg CO2e/kWh | K10: Offsetting or avoiding Electricity use | O10: Is there any guidance on how to account for this one? Maybe it is the same as electricity??
A11: Water | B11: 3 | D11: Water | E11: 0.344 | F11: 0.149 | G11: 0.149 | H11: 0.17668455 | J11: kg CO2e/m3
B12: 3 | D12: Wastewater | E12: 0.708 | F12: 0.272 | G12: 0.272 | H12: 0.20131829 | J12: kg CO2e/m3
A13: Waste | B13: 3 | D13: Waste to landfill | E13: 458.1763 | F13: 467.0458 | G13: 467.00838 | H13: 520.33474 | J13: kg CO2e/tonne
B14: 3 | D14: Waste to energy | E14: 21.3167 | F14: 21.293566 | G14: 21.280807 | H14: 21.280807 | J14: kg CO2e/tonne
B15: 3 | D15: Waste to recycling | E15: 21.3167 | F15: 21.293566 | G15: 21.280807 | H15: 21.280807 | J15: kg CO2e/tonne
B16: 3 | D16: Waste to composting | E16: 10.2039 | F16: 8.9506977 | G16: 8.9105814 | H16: 8.9124217 | J16: kg CO2e/tonne
A17: Business Travel | B17: 3 | D17: Car (small) | Petrol | E17: 0.14836 | F17: 0.14946 | G17: 0.14652 | H17: 0.14079853 | J17: kg CO2e/km
B18: 3 | D18: Car (medium) | Petrol | E18: 0.18659 | F18: 0.18785 | G18: 0.1847 | H18: 0.17818853 | J18: kg CO2e/km
B19: 3 | D19: Car (large) | Petrol | E19: 0.27807 | F19: 0.27909 | G19: 0.27639 | H19: 0.27223853 | J19: kg CO2e/km
B20: 3 | D20: Car (average) | Petrol | E20: 0.1743 | F20: 0.17431 | G20: 0.17048 | H20: 0.16390853 | J20: kg CO2e/km
B21: 3 | D21: Car (small) | Diesel | E21: 0.13721 | F21: 0.13758 | G21: 0.13989414 | H21: 0.13930645 | J21: kg CO2e/km
B22: 3 | D22: Car (medium) | Diesel | E22: 0.16637 | F22: 0.16496 | G22: 0.16800414 | H22: 0.16715645 | J22: kg CO2e/km
B23: 3 | D23: Car (large) | Diesel | E23: 0.20419 | F23: 0.20721 | G23: 0.20953414 | H23: 0.20858645 | J23: kg CO2e/km
B24: 3 | D24: Car (average) | Diesel | E24: 0.16844 | F24: 0.16843 | G24: 0.17082414 | H24: 0.16982645 | J24: kg CO2e/km
B25: 3 | D25: Car (small) | Hybrid | E25: 0.10275 | F25: 0.10494 | G25: 0.10332 | H25: 0.10149886 | J25: kg CO2e/km
B26: 3 | D26: Car (medium) | Hybrid | E26: 0.10698 | F26: 0.10957 | G26: 0.10999 | H26: 0.10783 | J26: kg CO2e/km
B27: 3 | D27: Car (large) | Hybrid | E27: 0.1448 | F27: 0.15151 | G27: 0.15491 | H27: 0.15101 | J27: kg CO2e/km
B28: 3 | D28: Car (average) | Hybrid | E28: 0.11558 | F28: 0.11952 | G28: 0.12004 | H28: 0.11781 | J28: kg CO2e/km
B29: 3 | D29: Car (small) | Plug-in Hybrid | E29: 0.0586 | F29: 0.05568 | G29: 0.05255 | H29: 0.054022993 | J29: kg CO2e/km
... B56: 3 | D56: International (to/from non-UK) - business class | E56: 0.40379 | F56: 0.39044321 | G56: 0.40781 | H56: 0.39044321 | J56: kg CO2e/km
A57: Freighting goods | B57: 3 | D57: Average Van (up to 3.5 tonnes) (diesel) | E57: 0.2471 | F57: 0.24116 | G57: 0.23156 | H57: 0.23128403 | J57: kg CO2e/km
B58: 3 | D58: Average Van (up to 3.5 tonnes) (petrol) | E58: 0.21962 | F58: 0.21047 | G58: 0.21332 | H58: 0.20132454 | J58: kg CO2e/km
B59: 3 | D59: HGVs (diesel) | E59: 0.8654 | F59: 0.86407 | G59: 0.89061 | H59: 0.87204848 | J59: kg CO2e/km
B60: 3 | D60: Refrigerated HGVs (diesel) | E60: 1.0142 | F60: 1.01192 | G60: 1.04208 | H60: 1.0209785 | J60: kg CO2e/km
B61: 3 | D61: Freight flights (Domestic to/from UK) | E61: 2.52129 | F61: 2.3765 | G61: 2.3765 | H61: 0.87204848 | J61: kg CO2e/km
B62: 3 | D62: Freight flights (Short-haul to/from UK) | E62: 1.1681 | F62: 1.21717 | G62: 1.21717 | H62: 0.98468518 | J62: kg CO2e/km
B63: 3 | D63: Freight flights (Long haul to/from UK) | E63: 0.59943 | F63: 0.53867 | G63: 0.53867 | H63: 0.6487416 | J63: kg CO2e/km
B64: 3 | D64: Freight flights (International to/from UK) | E64: 0.59943 | F64: 0.53867 | G64: 0.53867 | H64: 0.6487416 | J64: kg CO2e/km
B65: 3 | D65: Rail (freight train) | E65: 0.02556 | F65: 0.02782 | G65: 0.02782 | H65: 0.027788071 | J65: kg CO2e/km
B66: 3 | D66: Cargo Ship (Bulk carrier) | E66: 0.003539 | F66: 0.003539 | G66: 0.003539 | H66: 0.0035338046 | J66: kg CO2e/km
B67: 3 | D67: Cargo Ship (General cargo) | E67: 0.013232 | F67: 0.013232 | G67: 0.013232 | H67: 0.013212769 | J67: kg CO2e/km
B68: 3 | D68: Cargo Ship (Container ship) | E68: 0.016142 | F68: 0.016142 | G68: 0.016142 | H68: 0.013212769 | J68: kg CO2e/km
B69: 3 | D69: Cargo Ship (Vehicle transport) | E69: 0.038581 | F69: 0.038579 | G69: 0.038579 | H69: 0.038522958 | J69: kg CO2e/km
B70: 3 | D70: Cargo Ship (Refrigerated cargo) | E70: 0.01308 | F70: 0.01308 | G70: 0.01308 | H70: 0.01306099 | J70: kg CO2e/km
A71: Staff Commute | B71: 3 | D71: Car (small) | Petrol | E71: 0.14836 | F71: 0.14946 | G71: 0.14652 | H71: 0.14079853 | J71: kg CO2e/km
B72: 3 | D72: Car (medium) | Petrol | E72: 0.18659 | F72: 0.18785 | G72: 0.1847 | H72: 0.17818853 | J72: kg CO2e/km
B73: 3 | D73: Car (large) | Petrol | E73: 0.27807 | F73: 0.27909 | G73: 0.27639 | H73: 0.27223853 | J73: kg CO2e/km
B74: 3 | D74: Car (average) | Petrol | E74: 0.1743 | F74: 0.17431 | G74: 0.17048 | H74: 0.16390853 | J74: kg CO2e/km
B75: 3 | D75: Car (small) | Diesel | E75: 0.13721 | F75: 0.13758 | G75: 0.13989414 | H75: 0.13930645 | J75: kg CO2e/km
B76: 3 | D76: Car (medium) | Diesel | E76: 0.16637 | F76: 0.16496 | G76: 0.16800414 | H76: 0.16715645 | J76: kg CO2e/km
B77: 3 | D77: Car (large) | Diesel | E77: 0.20419 | F77: 0.20721 | G77: 0.20953414 | H77: 0.20858645 | J77: kg CO2e/km
B78: 3 | D78: Car (average) | Diesel | E78: 0.16844 | F78: 0.16843 | G78: 0.17082414 | H78: 0.16982645 | J78: kg CO2e/km
B79: 3 | D79: Car (small) | Hybrid | E79: 0.10275 | F79: 0.10494 | G79: 0.10332 | H79: 0.10149886 | J79: kg CO2e/km
B80: 3 | D80: Car (medium) | Hybrid | E80: 0.10698 | F80: 0.10957 | G80: 0.10999 | H80: 0.10783 | J80: kg CO2e/km
B81: 3 | D81: Car (large) | Hybrid | E81: 0.1448 | F81: 0.15151 | G81: 0.15491 | H81: 0.15101 | J81: kg CO2e/km
B82: 3 | D82: Car (average) | Hybrid | E82: 0.11558 | F82: 0.11952 | G82: 0.12004 | H82: 0.11781 | J82: kg CO2e/km
B83: 3 | D83: Car (small) | Plug-in Hybrid | E83: 0.0586 | F83: 0.05568 | G83: 0.05255 | H83: 0.054022993 | J83: kg CO2e/km
... B110: 3 | D110: International (to/from non-UK) - business class | E110: 0.40379 | F110: 0.39044321 | G110: 0.40781 | H110: 0.39044321 | J110: kg CO2e/km
A111: Private vehicle for business use (SCOPE 2) | B111: 2 | D111: Car (small) | Petrol | E111: 0.14836 | F111: 0.14946 | G111: 0.14652 | H111: 0.14079853 | J111: kg CO2e/km
B112: 2 | D112: Car (medium) | Petrol | E112: 0.18659 | F112: 0.18785 | G112: 0.1847 | H112: 0.17818853 | J112: kg CO2e/km
B113: 2 | D113: Car (large) | Petrol | E113: 0.27807 | F113: 0.27909 | G113: 0.27639 | H113: 0.27223853 | J113: kg CO2e/km
B114: 2 | D114: Car (average) | Petrol | E114: 0.1743 | F114: 0.17431 | G114: 0.17048 | H114: 0.16390853 | J114: kg CO2e/km
B115: 2 | D115: Car (small) | Diesel | E115: 0.13721 | F115: 0.13758 | G115: 0.13989414 | H115: 0.13930645 | J115: kg CO2e/km
B116: 2 | D116: Car (medium) | Diesel | E116: 0.16637 | F116: 0.16496 | G116: 0.16800414 | H116: 0.16715645 | J116: kg CO2e/km
B117: 2 | D117: Car (large) | Diesel | E117: 0.20419 | F117: 0.20721 | G117: 0.20953414 | H117: 0.20858645 | J117: kg CO2e/km
B118: 2 | D118: Car (average) | Diesel | E118: 0.16844 | F118: 0.16843 | G118: 0.17082414 | H118: 0.16982645 | J118: kg CO2e/km
B119: 2 | D119: Car (small) | Hybrid | E119: 0.10275 | F119: 0.10494 | G119: 0.10332 | H119: 0.10149886 | J119: kg CO2e/km
B120: 2 | D120: Car (medium) | Hybrid | E120: 0.10698 | F120: 0.10957 | G120: 0.10999 | H120: 0.10783 | J120: kg CO2e/km
B121: 2 | D121: Car (large) | Hybrid | E121: 0.1448 | F121: 0.15151 | G121: 0.15491 | H121: 0.15101 | J121: kg CO2e/km
B122: 2 | D122: Car (average) | Hybrid | E122: 0.11558 | F122: 0.11952 | G122: 0.12004 | H122: 0.11781 | J122: kg CO2e/km
B123: 2 | D123: Car (small) | Plug-in Hybrid | E123: 0.0586 | F123: 0.05568 | G123: 0.05255 | H123: 0.054022993 | J123: kg CO2e/km
... B126: 2 | D126: Car (average) | Plug-in Hybrid | E126: 0.09712 | F126: 0.09694 | G126: 0.09349 | H126: 0.093916412 | J126: kg CO2e/km
A127: Company fleet and leased vehicles (SCOPE 1) | B127: 1 | D127: Average Van (up to 3.5 tonnes) (diesel) | E127: 0.2471 | F127: 0.24116 | G127: 0.23156 | H127: 0.23128403 | J127: kg CO2e/km
B128: 1 | D128: Average Van (up to 3.5 tonnes) (petrol) | E128: 0.21962 | F128: 0.21047 | G128: 0.21332 | H128: 0.20132454 | J128: kg CO2e/km
B129: 1 | D129: HGVs (diesel) | E129: 0.8654 | F129: 0.86407 | G129: 0.89061 | H129: 0.87204848 | J129: kg CO2e/km
B130: 1 | D130: Refrigerated HGVs (diesel) | E130: 1.0142 | F130: 1.01192 | G130: 1.04208 | H130: 1.0209785 | J130: kg CO2e/km
B131: 1 | D131: Freight flights (Domestic to/from UK) | E131: 2.52129 | F131: 2.3765 | G131: 2.3765 | H131: 0.87204848 | J131: kg CO2e/km
B132: 1 | D132: Freight flights (Short-haul to/from UK) | E132: 1.1681 | F132: 1.21717 | G132: 1.21717 | H132: 0.98468518 | J132: kg CO2e/km
B133: 1 | D133: Freight flights (Long haul to/from UK) | E133: 0.59943 | F133: 0.53867 | G133: 0.53867 | H133: 0.6487416 | J133: kg CO2e/km
B134: 1 | D134: Freight flights (International to/from UK) | E134: 0.59943 | F134: 0.53867 | G134: 0.53867 | H134: 0.6487416 | J134: kg CO2e/km
B135: 1 | D135: Rail (freight train) | E135: 0.02556 | F135: 0.02782 | G135: 0.02782 | H135: 0.027788071 | J135: kg CO2e/km
B136: 1 | D136: Cargo Ship (Bulk carrier) | E136: 0.003539 | F136: 0.003539 | G136: 0.003539 | H136: 0.0035338046 | J136: kg CO2e/km
B137: 1 | D137: Cargo Ship (General cargo) | E137: 0.013232 | F137: 0.013232 | G137: 0.013232 | H137: 0.013212769 | J137: kg CO2e/km
B138: 1 | D138: Cargo Ship (Container ship) | E138: 0.016142 | F138: 0.016142 | G138: 0.016142 | H138: 0.013212769 | J138: kg CO2e/km
B139: 1 | D139: Cargo Ship (Vehicle transport) | E139: 0.038581 | F139: 0.038579 | G139: 0.038579 | H139: 0.038522958 | J139: kg CO2e/km
... B156: 1 | D156: Car (average) | Plug-in Hybrid | E156: 0.09712 | F156: 0.09694 | G156: 0.09349 | H156: 0.093916412 | J156: kg CO2e/km
A157: Refrigerants | B157: 1 | D157: R404A | E157: 3922 | F157: 3922 | G157: 3922 | H157: 3943 | J157: Total kg CO2e per kg | K157: Emissions including only kyoto products
B158: 1 | D158: R407A | E158: 2107 | F158: 2107 | G158: 2107 | H158: 1923 | J158: Total kg CO2e per kg
B159: 1 | D159: R407C | E159: 1774 | F159: 1774 | G159: 1774 | H159: 1624 | J159: Total kg CO2e per kg
B160: 1 | D160: R408A | E160: 3152 | F160: 3152 | G160: 2301 | H160: 2430 | J160: Total kg CO2e per kg
B161: 1 | D161: R410A | E161: 2088 | F161: 2088 | G161: 2088 | H161: 1924 | J161: Total kg CO2e per kg
B162: 1 | D162: R134a | E162: 1430 | F162: 1430 | G162: 1430 | H162: 1300 | J162: Total kg CO2e per kg
B163: 1 | D163: Other | E163: =Refrigerants!C54 -> 0 | F163: =Refrigerants!D54 -> 0 | G163: =Refrigerants!E54 -> 0 | H163: =Refrigerants!F54 -> 0 | J163: Total kg CO2e per kg | K163: Please check Refrigerant tab - other refrigerant - user input
A164: Home working | B164: 3 | D164: Home Working | E164: N/A | F164: N/A | G164: 0.34075331 | H164: 0.3337812 | J164: kg CO2e/working hour
A165: Hotel stay (UK) | B165: 3 | D165: UK | F165: 13.9 | G165: 11.5 | H165: 11.5 | J165: kg CO2e/room/night
B166: 3 | D166: UK (London) | E166: N/A | F166: 13.8 | G166: 10.4 | H166: 10.4 | J166: kg CO2e/room/night
A167: Material use | B167: 3 | D167: Average construction (primary material production) | E167: 79.2678 | F167: 79.973673 | G167: 80.337767 | H167: 80.212818 | J167: kg CO2e/tonne
B168: 3 | D168: Aggregates (primary material production) | E168: 7.7726 | F168: 7.7589016 | G168: 7.7510183 | H168: 7.75138 | J168: kg CO2e/tonne
B169: 3 | D169: Aggregates (re-used) | E169: 2.21 | F169: 2.21 | G169: 2.21 | H169: 2.21 | J169: kg CO2e/tonne
B170: 3 | D170: Aggregates (closed-loop) | E170: 3.2068 | F170: 3.1991416 | G170: 3.1947083 | H170: 3.1949117 | J170: kg CO2e/tonne
...

Sheet 2 Input data Summary SQ
E1: 2020 | F1: 2021 | G1: 2022 | H1: 2023 | I1: 2024 | J1: 2025
B2: Scope (1, 2, 3) | D2: Source
A3: Energy | B3: 2 | D3: Electricity | E3: =Energy!B6 -> 0 | F3: =Energy!C6 -> 0 | G3: =Energy!D6 -> 0 | H3: =Energy!E6 -> 0 | I3: =Energy!F6 -> 0 | M3: T&D - UK electricity 2023&2022 = 0.01792 kg CO2e/kWh; 0.01879 in 2021
B4: 1 | D4: Gas | E4: =Energy!B7 -> 0 | F4: =Energy!C7 -> 0 | G4: =Energy!D7 -> 0 | H4: =Energy!E7 -> 0 | I4: =Energy!F7 -> 0
B5: 1 | D5: Diesel | E5: =Energy!B8 -> 0 | F5: =Energy!C8 -> 0 | G5: =Energy!D8 -> 0 | H5: =Energy!E8 -> 0 | I5: =Energy!F8 -> 0
B6: 1 | D6: Oil | E6: =Energy!B9 -> 0 | F6: =Energy!C9 -> 0 | G6: =Energy!D9 -> 0 | H6: =Energy!E9 -> 0 | I6: =Energy!F9 -> 0
B7: 3 | D7: Transmission and distribution - T&D- UK electricity | E7: =E3 -> 0 | F7: =F3 -> 0 | G7: =G3 -> 0 | H7: =H3 -> 0 | I7: =I3 -> 0 | K7: As per electricity usage - GOV Guidance
B8: 3 | D8: Transmission and distribution - Distribution - district heat & steam | E8: =Energy!B11 -> 0 | F8: =Energy!C11 -> 0 | G8: =Energy!D11 -> 0 | H8: =Energy!E11 -> 0 | I8: =Energy!F11 -> 0
D9: Other (i.e district heating) | E9: =Energy!B11 -> 0 | F9: =Energy!C11 -> 0 | G9: =Energy!D11 -> 0 | H9: =Energy!E11 -> 0 | I9: =Energy!F11 -> 0
B10: 1 | D10: On site energy generation (PV) | E10: =Energy!B10 -> 0 | F10: =Energy!C10 -> 0 | G10: =Energy!D10 -> 0 | H10: =Energy!E10 -> 0 | I10: =Energy!F10 -> 0 | L10: Offsetting or avoiding Electricity use | O10: Is there any guidance on how to account for this one? Maybe it is the same as electricity??
A11: Water | B11: 3 | D11: Water | E11: =Water!C6 -> 0 | F11: =Water!D6 -> 0 | G11: =Water!E6 -> 0 | H11: =Water!F6 -> 0 | I11: =Water!G6 -> 0
B12: 3 | D12: Wastewater | E12: =Water!C8 -> 0 | F12: =Water!D8 -> 0 | G12: =Water!E8 -> 0 | H12: =Water!F8 -> 0 | I12: =Water!G8 -> 0
A13: Waste | B13: 3 | D13: Waste to landfill | E13: ='Waste '!C8 -> 0 | F13: ='Waste '!D8 -> 0 | G13: ='Waste '!E8 -> 0 | H13: ='Waste '!F8 -> 0 | I13: ='Waste '!G8 -> 0
B14: 3 | D14: Waste to energy | E14: ='Waste '!C10 -> 0 | F14: ='Waste '!D10 -> 0 | G14: ='Waste '!E10 -> 0 | H14: ='Waste '!F10 -> 0 | I14: ='Waste '!G10 -> 0
B15: 3 | D15: Waste to recycling | E15: ='Waste '!C12 -> 0 | F15: ='Waste '!D12 -> 0 | G15: ='Waste '!E12 -> 0 | H15: ='Waste '!F12 -> 0 | I15: ='Waste '!G12 -> 0
B16: 3 | D16: Waste to composting | E16: ='Waste '!C14 -> 0 | F16: ='Waste '!D14 -> 0 | G16: ='Waste '!E14 -> 0 | H16: ='Waste '!F14 -> 0 | I16: ='Waste '!G14 -> 0
A17: Business Travel | B17: 3 | D17: Car (small) | Petrol | E17: ='Business & Staff Travel'!D14 -> 0 | F17: ='Business & Staff Travel'!E14 -> 0 | G17: ='Business & Staff Travel'!F14 -> 0 | H17: ='Business & Staff Travel'!G14 -> 0 | I17: ='Business & Staff Travel'!H14 -> 0
B18: 3 | D18: Car (medium) | Petrol | E18: ='Business & Staff Travel'!D15 -> 0 | F18: ='Business & Staff Travel'!E15 -> 0 | G18: ='Business & Staff Travel'!F15 -> 0 | H18: ='Business & Staff Travel'!G15 -> 0 | I18: ='Business & Staff Travel'!H15 -> 0
B19: 3 | D19: Car (large) | Petrol | E19: ='Business & Staff Travel'!D16 -> 0 | F19: ='Business & Staff Travel'!E16 -> 0 | G19: ='Business & Staff Travel'!F16 -> 0 | H19: ='Business & Staff Travel'!G16 -> 0 | I19: ='Business & Staff Travel'!H16 -> 0
B20: 3 | D20: Car (average) | Petrol | E20: ='Business & Staff Travel'!D17 -> 0 | F20: ='Business & Staff Travel'!E17 -> 0 | G20: ='Business & Staff Travel'!F17 -> 0 | H20: ='Business & Staff Travel'!G17 -> 0 | I20: ='Business & Staff Travel'!H17 -> 0
B21: 3 | D21: Car (small) | Diesel | E21: ='Business & Staff Travel'!D18 -> 0 | F21: ='Business & Staff Travel'!E18 -> 0 | G21: ='Business & Staff Travel'!F18 -> 0 | H21: ='Business & Staff Travel'!G18 -> 0 | I21: ='Business & Staff Travel'!H18 -> 0
B22: 3 | D22: Car (medium) | Diesel | E22: ='Business & Staff Travel'!D19 -> 0 | F22: ='Business & Staff Travel'!E19 -> 0 | G22: ='Business & Staff Travel'!F19 -> 0 | H22: ='Business & Staff Travel'!G19 -> 0 | I22: ='Business & Staff Travel'!H19 -> 0
B23: 3 | D23: Car (large) | Diesel | E23: ='Business & Staff Travel'!D20 -> 0 | F23: ='Business & Staff Travel'!E20 -> 0 | G23: ='Business & Staff Travel'!F20 -> 0 | H23: ='Business & Staff Travel'!G20 -> 0 | I23: ='Business & Staff Travel'!H20 -> 0
B24: 3 | D24: Car (average) | Diesel | E24: ='Business & Staff Travel'!D21 -> 0 | F24: ='Business & Staff Travel'!E21 -> 0 | G24: ='Business & Staff Travel'!F21 -> 0 | H24: ='Business & Staff Travel'!G21 -> 0 | I24: ='Business & Staff Travel'!H21 -> 0
B25: 3 | D25: Car (small) | Hybrid | E25: ='Business & Staff Travel'!D22 -> 0 | F25: ='Business & Staff Travel'!E22 -> 0 | G25: ='Business & Staff Travel'!F22 -> 0 | H25: ='Business & Staff Travel'!G22 -> 0 | I25: ='Business & Staff Travel'!H22 -> 0
B26: 3 | D26: Car (medium) | Hybrid | E26: ='Business & Staff Travel'!D23 -> 0 | F26: ='Business & Staff Travel'!E23 -> 0 | G26: ='Business & Staff Travel'!F23 -> 0 | H26: ='Business & Staff Travel'!G23 -> 0 | I26: ='Business & Staff Travel'!H23 -> 0
B27: 3 | D27: Car (large) | Hybrid | E27: ='Business & Staff Travel'!D24 -> 0 | F27: ='Business & Staff Travel'!E24 -> 0 | G27: ='Business & Staff Travel'!F24 -> 0 | H27: ='Business & Staff Travel'!G24 -> 0 | I27: ='Business & Staff Travel'!H24 -> 0
B28: 3 | D28: Car (average) | Hybrid | E28: ='Business & Staff Travel'!D25 -> 0 | F28: ='Business & Staff Travel'!E25 -> 0 | G28: ='Business & Staff Travel'!F25 -> 0 | H28: ='Business & Staff Travel'!G25 -> 0 | I28: ='Business & Staff Travel'!H25 -> 0
B29: 3 | D29: Car (small) | Plug-in Hybrid | E29: ='Business & Staff Travel'!D26 -> 0 | F29: ='Business & Staff Travel'!E26 -> 0 | G29: ='Business & Staff Travel'!F26 -> 0 | H29: ='Business & Staff Travel'!G26 -> 0 | I29: ='Business & Staff Travel'!H26 -> 0
... B56: 3 | D56: International (to/from non-UK) - business class | E56: ='Business & Staff Travel'!D53 -> 0 | F56: ='Business & Staff Travel'!E53 -> 0 | G56: ='Business & Staff Travel'!F53 -> 0 | H56: ='Business & Staff Travel'!G53 -> 0 | I56: ='Business & Staff Travel'!H53 -> 0
A57: Freighting goods | B57: 3 | D57: Average Van (up to 3.5 tonnes) (diesel) | E57: ='Business & Staff Travel'!D54 -> 0 | F57: ='Business & Staff Travel'!E54 -> 0 | G57: ='Business & Staff Travel'!F54 -> 0 | H57: ='Business & Staff Travel'!G54 -> 0 | I57: ='Business & Staff Travel'!H54 -> 0
B58: 3 | D58: Average Van (up to 3.5 tonnes) (petrol) | E58: ='Business & Staff Travel'!D55 -> 0 | F58: ='Business & Staff Travel'!E55 -> 0 | G58: ='Business & Staff Travel'!F55 -> 0 | H58: ='Business & Staff Travel'!G55 -> 0 | I58: ='Business & Staff Travel'!H55 -> 0
B59: 3 | D59: HGVs (diesel) | E59: ='Business & Staff Travel'!D56 -> 0 | F59: ='Business & Staff Travel'!E56 -> 0 | G59: ='Business & Staff Travel'!F56 -> 0 | H59: ='Business & Staff Travel'!G56 -> 0 | I59: ='Business & Staff Travel'!H56 -> 0
B60: 3 | D60: Refrigerated HGVs (diesel) | E60: ='Business & Staff Travel'!D57 -> 0 | F60: ='Business & Staff Travel'!E57 -> 0 | G60: ='Business & Staff Travel'!F57 -> 0 | H60: ='Business & Staff Travel'!G57 -> 0 | I60: ='Business & Staff Travel'!H57 -> 0
B61: 3 | D61: Freight flights (Domestic to/from UK) | E61: ='Business & Staff Travel'!D58 -> 0 | F61: ='Business & Staff Travel'!E58 -> 0 | G61: ='Business & Staff Travel'!F58 -> 0 | H61: ='Business & Staff Travel'!G58 -> 0 | I61: ='Business & Staff Travel'!H58 -> 0
B62: 3 | D62: Freight flights (Short-haul to/from UK) | E62: ='Business & Staff Travel'!D59 -> 0 | F62: ='Business & Staff Travel'!E59 -> 0 | G62: ='Business & Staff Travel'!F59 -> 0 | H62: ='Business & Staff Travel'!G59 -> 0 | I62: ='Business & Staff Travel'!H59 -> 0
B63: 3 | D63: Freight flights (Long haul to/from UK) | E63: ='Business & Staff Travel'!D60 -> 0 | F63: ='Business & Staff Travel'!E60 -> 0 | G63: ='Business & Staff Travel'!F60 -> 0 | H63: ='Business & Staff Travel'!G60 -> 0 | I63: ='Business & Staff Travel'!H60 -> 0
B64: 3 | D64: Freight flights (International to/from UK) | E64: ='Business & Staff Travel'!D61 -> 0 | F64: ='Business & Staff Travel'!E61 -> 0 | G64: ='Business & Staff Travel'!F61 -> 0 | H64: ='Business & Staff Travel'!G61 -> 0 | I64: ='Business & Staff Travel'!H61 -> 0
B65: 3 | D65: Rail (freight train) | E65: ='Business & Staff Travel'!D62 -> 0 | F65: ='Business & Staff Travel'!E62 -> 0 | G65: ='Business & Staff Travel'!F62 -> 0 | H65: ='Business & Staff Travel'!G62 -> 0 | I65: ='Business & Staff Travel'!H62 -> 0
B66: 3 | D66: Cargo Ship (Bulk carrier) | E66: ='Business & Staff Travel'!D63 -> 0 | F66: ='Business & Staff Travel'!E63 -> 0 | G66: ='Business & Staff Travel'!F63 -> 0 | H66: ='Business & Staff Travel'!G63 -> 0 | I66: ='Business & Staff Travel'!H63 -> 0
B67: 3 | D67: Cargo Ship (General cargo) | E67: ='Business & Staff Travel'!D64 -> 0 | F67: ='Business & Staff Travel'!E64 -> 0 | G67: ='Business & Staff Travel'!F64 -> 0 | H67: ='Business & Staff Travel'!G64 -> 0 | I67: ='Business & Staff Travel'!H64 -> 0
B68: 3 | D68: Cargo Ship (Container ship) | E68: ='Business & Staff Travel'!D65 -> 0 | F68: ='Business & Staff Travel'!E65 -> 0 | G68: ='Business & Staff Travel'!F65 -> 0 | H68: ='Business & Staff Travel'!G65 -> 0 | I68: ='Business & Staff Travel'!H65 -> 0
B69: 3 | D69: Cargo Ship (Vehicle transport) | E69: ='Business & Staff Travel'!D66 -> 0 | F69: ='Business & Staff Travel'!E66 -> 0 | G69: ='Business & Staff Travel'!F66 -> 0 | H69: ='Business & Staff Travel'!G66 -> 0 | I69: ='Business & Staff Travel'!H66 -> 0
B70: 3 | D70: Cargo Ship (Refrigerated cargo) | E70: ='Business & Staff Travel'!D67 -> 0 | F70: ='Business & Staff Travel'!E67 -> 0 | G70: ='Business & Staff Travel'!F67 -> 0 | H70: ='Business & Staff Travel'!G67 -> 0 | I70: ='Business & Staff Travel'!H67 -> 0
A71: Staff Commute | B71: 3 | D71: Car (small) | Petrol | E71: ='Business & Staff Travel'!D68 -> 0 | F71: ='Business & Staff Travel'!E68 -> 0 | G71: ='Business & Staff Travel'!F68 -> 0 | H71: ='Business & Staff Travel'!G68 -> 0 | I71: ='Business & Staff Travel'!H68 -> 0
B72: 3 | D72: Car (medium) | Petrol | E72: ='Business & Staff Travel'!D69 -> 0 | F72: ='Business & Staff Travel'!E69 -> 0 | G72: ='Business & Staff Travel'!F69 -> 0 | H72: ='Business & Staff Travel'!G69 -> 0 | I72: ='Business & Staff Travel'!H69 -> 0
B73: 3 | D73: Car (large) | Petrol | E73: ='Business & Staff Travel'!D70 -> 0 | F73: ='Business & Staff Travel'!E70 -> 0 | G73: ='Business & Staff Travel'!F70 -> 0 | H73: ='Business & Staff Travel'!G70 -> 0 | I73: ='Business & Staff Travel'!H70 -> 0
B74: 3 | D74: Car (average) | Petrol | E74: ='Business & Staff Travel'!D71 -> 0 | F74: ='Business & Staff Travel'!E71 -> 0 | G74: ='Business & Staff Travel'!F71 -> 0 | H74: ='Business & Staff Travel'!G71 -> 0 | I74: ='Business & Staff Travel'!H71 -> 0
B75: 3 | D75: Car (small) | Diesel | E75: ='Business & Staff Travel'!D72 -> 0 | F75: ='Business & Staff Travel'!E72 -> 0 | G75: ='Business & Staff Travel'!F72 -> 0 | H75: ='Business & Staff Travel'!G72 -> 0 | I75: ='Business & Staff Travel'!H72 -> 0
B76: 3 | D76: Car (medium) | Diesel | E76: ='Business & Staff Travel'!D73 -> 0 | F76: ='Business & Staff Travel'!E73 -> 0 | G76: ='Business & Staff Travel'!F73 -> 0 | H76: ='Business & Staff Travel'!G73 -> 0 | I76: ='Business & Staff Travel'!H73 -> 0
B77: 3 | D77: Car (large) | Diesel | E77: ='Business & Staff Travel'!D74 -> 0 | F77: ='Business & Staff Travel'!E74 -> 0 | G77: ='Business & Staff Travel'!F74 -> 0 | H77: ='Business & Staff Travel'!G74 -> 0 | I77: ='Business & Staff Travel'!H74 -> 0
B78: 3 | D78: Car (average) | Diesel | E78: ='Business & Staff Travel'!D75 -> 0 | F78: ='Business & Staff Travel'!E75 -> 0 | G78: ='Business & Staff Travel'!F75 -> 0 | H78: ='Business & Staff Travel'!G75 -> 0 | I78: ='Business & Staff Travel'!H75 -> 0
B79: 3 | D79: Car (small) | Hybrid | E79: ='Business & Staff Travel'!D76 -> 0 | F79: ='Business & Staff Travel'!E76 -> 0 | G79: ='Business & Staff Travel'!F76 -> 0 | H79: ='Business & Staff Travel'!G76 -> 0 | I79: ='Business & Staff Travel'!H76 -> 0
B80: 3 | D80: Car (medium) | Hybrid | E80: ='Business & Staff Travel'!D77 -> 0 | F80: ='Business & Staff Travel'!E77 -> 0 | G80: ='Business & Staff Travel'!F77 -> 0 | H80: ='Business & Staff Travel'!G77 -> 0 | I80: ='Business & Staff Travel'!H77 -> 0
B81: 3 | D81: Car (large) | Hybrid | E81: ='Business & Staff Travel'!D78 -> 0 | F81: ='Business & Staff Travel'!E78 -> 0 | G81: ='Business & Staff Travel'!F78 -> 0 | H81: ='Business & Staff Travel'!G78 -> 0 | I81: ='Business & Staff Travel'!H78 -> 0
B82: 3 | D82: Car (average) | Hybrid | E82: ='Business & Staff Travel'!D79 -> 0 | F82: ='Business & Staff Travel'!E79 -> 0 | G82: ='Business & Staff Travel'!F79 -> 0 | H82: ='Business & Staff Travel'!G79 -> 0 | I82: ='Business & Staff Travel'!H79 -> 0
B83: 3 | D83: Car (small) | Plug-in Hybrid | E83: ='Business & Staff Travel'!D80 -> 0 | F83: ='Business & Staff Travel'!E80 -> 0 | G83: ='Business & Staff Travel'!F80 -> 0 | H83: ='Business & Staff Travel'!G80 -> 0 | I83: ='Business & Staff Travel'!H80 -> 0
... B110: 3 | D110: International (to/from non-UK) - business class | E110: ='Business & Staff Travel'!D107 -> 0 | F110: ='Business & Staff Travel'!E107 -> 0 | G110: ='Business & Staff Travel'!F107 -> 0 | H110: ='Business & Staff Travel'!G107 -> 0 | I110: ='Business & Staff Travel'!H107 -> 0
A111: Private vehicle for business use (SCOPE 2) | B111: 2 | D111: Car (small) | Petrol | E111: ='Business & Staff Travel'!D108 -> 0 | F111: ='Business & Staff Travel'!E108 -> 0 | G111: ='Business & Staff Travel'!F108 -> 0 | H111: ='Business & Staff Travel'!G108 -> 0 | I111: ='Business & Staff Travel'!H108 -> 0
B112: 2 | D112: Car (medium) | Petrol | E112: ='Business & Staff Travel'!D109 -> 0 | F112: ='Business & Staff Travel'!E109 -> 0 | G112: ='Business & Staff Travel'!F109 -> 0 | H112: ='Business & Staff Travel'!G109 -> 0 | I112: ='Business & Staff Travel'!H109 -> 0
B113: 2 | D113: Car (large) | Petrol | E113: ='Business & Staff Travel'!D110 -> 0 | F113: ='Business & Staff Travel'!E110 -> 0 | G113: ='Business & Staff Travel'!F110 -> 0 | H113: ='Business & Staff Travel'!G110 -> 0 | I113: ='Business & Staff Travel'!H110 -> 0
B114: 2 | D114: Car (average) | Petrol | E114: ='Business & Staff Travel'!D111 -> 0 | F114: ='Business & Staff Travel'!E111 -> 0 | G114: ='Business & Staff Travel'!F111 -> 0 | H114: ='Business & Staff Travel'!G111 -> 0 | I114: ='Business & Staff Travel'!H111 -> 0
B115: 2 | D115: Car (small) | Diesel | E115: ='Business & Staff Travel'!D112 -> 0 | F115: ='Business & Staff Travel'!E112 -> 0 | G115: ='Business & Staff Travel'!F112 -> 0 | H115: ='Business & Staff Travel'!G112 -> 0 | I115: ='Business & Staff Travel'!H112 -> 0
B116: 2 | D116: Car (medium) | Diesel | E116: ='Business & Staff Travel'!D113 -> 0 | F116: ='Business & Staff Travel'!E113 -> 0 | G116: ='Business & Staff Travel'!F113 -> 0 | H116: ='Business & Staff Travel'!G113 -> 0 | I116: ='Business & Staff Travel'!H113 -> 0
B117: 2 | D117: Car (large) | Diesel | E117: ='Business & Staff Travel'!D114 -> 0 | F117: ='Business & Staff Travel'!E114 -> 0 | G117: ='Business & Staff Travel'!F114 -> 0 | H117: ='Business & Staff Travel'!G114 -> 0 | I117: ='Business & Staff Travel'!H114 -> 0
B118: 2 | D118: Car (average) | Diesel | E118: ='Business & Staff Travel'!D115 -> 0 | F118: ='Business & Staff Travel'!E115 -> 0 | G118: ='Business & Staff Travel'!F115 -> 0 | H118: ='Business & Staff Travel'!G115 -> 0 | I118: ='Business & Staff Travel'!H115 -> 0
B119: 2 | D119: Car (small) | Hybrid | E119: ='Business & Staff Travel'!D116 -> 0 | F119: ='Business & Staff Travel'!E116 -> 0 | G119: ='Business & Staff Travel'!F116 -> 0 | H119: ='Business & Staff Travel'!G116 -> 0 | I119: ='Business & Staff Travel'!H116 -> 0
B120: 2 | D120: Car (medium) | Hybrid | E120: ='Business & Staff Travel'!D117 -> 0 | F120: ='Business & Staff Travel'!E117 -> 0 | G120: ='Business & Staff Travel'!F117 -> 0 | H120: ='Business & Staff Travel'!G117 -> 0 | I120: ='Business & Staff Travel'!H117 -> 0
B121: 2 | D121: Car (large) | Hybrid | E121: ='Business & Staff Travel'!D118 -> 0 | F121: ='Business & Staff Travel'!E118 -> 0 | G121: ='Business & Staff Travel'!F118 -> 0 | H121: ='Business & Staff Travel'!G118 -> 0 | I121: ='Business & Staff Travel'!H118 -> 0
B122: 2 | D122: Car (average) | Hybrid | E122: ='Business & Staff Travel'!D119 -> 0 | F122: ='Business & Staff Travel'!E119 -> 0 | G122: ='Business & Staff Travel'!F119 -> 0 | H122: ='Business & Staff Travel'!G119 -> 0 | I122: ='Business & Staff Travel'!H119 -> 0
B123: 2 | D123: Car (small) | Plug-in Hybrid | E123: ='Business & Staff Travel'!D120 -> 0 | F123: ='Business & Staff Travel'!E120 -> 0 | G123: ='Business & Staff Travel'!F120 -> 0 | H123: ='Business & Staff Travel'!G120 -> 0 | I123: ='Business & Staff Travel'!H120 -> 0
... B126: 2 | D126: Car (average) | Plug-in Hybrid | E126: ='Business & Staff Travel'!D123 -> 0 | F126: ='Business & Staff Travel'!E123 -> 0 | G126: ='Business & Staff Travel'!F123 -> 0 | H126: ='Business & Staff Travel'!G123 -> 0 | I126: ='Business & Staff Travel'!H123 -> 0
A127: Company fleet and leased vehicles (SCOPE 1) | B127: 1 | D127: Average Van (up to 3.5 tonnes) (diesel) | E127: ='Business & Staff Travel'!D124 -> 0 | F127: ='Business & Staff Travel'!E124 -> 0 | G127: ='Business & Staff Travel'!F124 -> 0 | H127: ='Business & Staff Travel'!G124 -> 0 | I127: ='Business & Staff Travel'!H124 -> 0
B128: 1 | D128: Average Van (up to 3.5 tonnes) (petrol) | E128: ='Business & Staff Travel'!D125 -> 0 | F128: ='Business & Staff Travel'!E125 -> 0 | G128: ='Business & Staff Travel'!F125 -> 0 | H128: ='Business & Staff Travel'!G125 -> 0 | I128: ='Business & Staff Travel'!H125 -> 0
B129: 1 | D129: HGVs (diesel) | E129: ='Business & Staff Travel'!D126 -> 0 | F129: ='Business & Staff Travel'!E126 -> 0 | G129: ='Business & Staff Travel'!F126 -> 0 | H129: ='Business & Staff Travel'!G126 -> 0 | I129: ='Business & Staff Travel'!H126 -> 0
B130: 1 | D130: Refrigerated HGVs (diesel) | E130: ='Business & Staff Travel'!D127 -> 0 | F130: ='Business & Staff Travel'!E127 -> 0 | G130: ='Business & Staff Travel'!F127 -> 0 | H130: ='Business & Staff Travel'!G127 -> 0 | I130: ='Business & Staff Travel'!H127 -> 0
B131: 1 | D131: Freight flights (Domestic to/from UK) | E131: ='Business & Staff Travel'!D128 -> 0 | F131: ='Business & Staff Travel'!E128 -> 0 | G131: ='Business & Staff Travel'!F128 -> 0 | H131: ='Business & Staff Travel'!G128 -> 0 | I131: ='Business & Staff Travel'!H128 -> 0
B132: 1 | D132: Freight flights (Short-haul to/from UK) | E132: ='Business & Staff Travel'!D129 -> 0 | F132: ='Business & Staff Travel'!E129 -> 0 | G132: ='Business & Staff Travel'!F129 -> 0 | H132: ='Business & Staff Travel'!G129 -> 0 | I132: ='Business & Staff Travel'!H129 -> 0
B133: 1 | D133: Freight flights (Long haul to/from UK) | E133: ='Business & Staff Travel'!D130 -> 0 | F133: ='Business & Staff Travel'!E130 -> 0 | G133: ='Business & Staff Travel'!F130 -> 0 | H133: ='Business & Staff Travel'!G130 -> 0 | I133: ='Business & Staff Travel'!H130 -> 0
B134: 1 | D134: Freight flights (International to/from UK) | E134: ='Business & Staff Travel'!D131 -> 0 | F134: ='Business & Staff Travel'!E131 -> 0 | G134: ='Business & Staff Travel'!F131 -> 0 | H134: ='Business & Staff Travel'!G131 -> 0 | I134: ='Business & Staff Travel'!H131 -> 0
B135: 1 | D135: Rail (freight train) | E135: ='Business & Staff Travel'!D132 -> 0 | F135: ='Business & Staff Travel'!E132 -> 0 | G135: ='Business & Staff Travel'!F132 -> 0 | H135: ='Business & Staff Travel'!G132 -> 0 | I135: ='Business & Staff Travel'!H132 -> 0
B136: 1 | D136: Cargo Ship (Bulk carrier) | E136: ='Business & Staff Travel'!D133 -> 0 | F136: ='Business & Staff Travel'!E133 -> 0 | G136: ='Business & Staff Travel'!F133 -> 0 | H136: ='Business & Staff Travel'!G133 -> 0 | I136: ='Business & Staff Travel'!H133 -> 0
B137: 1 | D137: Cargo Ship (General cargo) | E137: ='Business & Staff Travel'!D134 -> 0 | F137: ='Business & Staff Travel'!E134 -> 0 | G137: ='Business & Staff Travel'!F134 -> 0 | H137: ='Business & Staff Travel'!G134 -> 0 | I137: ='Business & Staff Travel'!H134 -> 0
B138: 1 | D138: Cargo Ship (Container ship) | E138: ='Business & Staff Travel'!D135 -> 0 | F138: ='Business & Staff Travel'!E135 -> 0 | G138: ='Business & Staff Travel'!F135 -> 0 | H138: ='Business & Staff Travel'!G135 -> 0 | I138: ='Business & Staff Travel'!H135 -> 0
B139: 1 | D139: Cargo Ship (Vehicle transport) | E139: ='Business & Staff Travel'!D136 -> 0 | F139: ='Business & Staff Travel'!E136 -> 0 | G139: ='Business & Staff Travel'!F136 -> 0 | H139: ='Business & Staff Travel'!G136 -> 0 | I139: ='Business & Staff Travel'!H136 -> 0
... B156: 1 | D156: Car (average) | Plug-in Hybrid | E156: ='Business & Staff Travel'!D153 -> 0 | F156: ='Business & Staff Travel'!E153 -> 0 | G156: ='Business & Staff Travel'!F153 -> 0 | H156: ='Business & Staff Travel'!G153 -> 0 | I156: ='Business & Staff Travel'!H153 -> 0
A157: Refrigerants | B157: 1 | D157: R404A | E157: =Refrigerants!C10 -> 0 | F157: =Refrigerants!D10 -> 0 | G157: =Refrigerants!E10 -> 0 | H157: =Refrigerants!F10 -> 0 | I157: =Refrigerants!G10 -> 0 | L157: Emissions including only kyoto products
B158: 1 | D158: R407A | E158: =Refrigerants!C16 -> 0 | F158: =Refrigerants!D16 -> 0 | G158: =Refrigerants!E16 -> 0 | H158: =Refrigerants!F16 -> 0 | I158: =Refrigerants!G16 -> 0
B159: 1 | D159: R407C | E159: =Refrigerants!C22 -> 0 | F159: =Refrigerants!D22 -> 0 | G159: =Refrigerants!E22 -> 0 | H159: =Refrigerants!F22 -> 0 | I159: =Refrigerants!G22 -> 0
B160: 1 | D160: R408A | E160: {=Refrigerants!C28:F28} -> 0 | F160: 0 | G160: 0 | H160: 0
B161: 1 | D161: R410A | E161: {=Refrigerants!C35:F35} -> 0 | F161: 0 | G161: 0 | H161: 0
B162: 1 | D162: R134a | E162: {=Refrigerants!C42:F42} -> 0 | F162: 0 | G162: 0 | H162: 0
B163: 1 | D163: Other | E163: {=Refrigerants!C54:F54} -> 0 | F163: 0 | G163: 0 | H163: 0 | L163: Please check Refrigerant tab - other refrigerant - user input
A164: Home working | B164: 3 | D164: Home Working (hours) | E164: ='Working from Home'!C7 -> 0 | F164: ='Working from Home'!D7 -> 0 | G164: ='Working from Home'!E7 -> 0 | H164: ='Working from Home'!F7 -> 0 | I164: ='Working from Home'!G7 -> 4179.6
A165: Hotel stay (UK) | B165: 3 | D165: UK | E165: ='Hotel Stay'!C7 -> 0 | F165: ='Hotel Stay'!D7 -> 0 | G165: ='Hotel Stay'!E7 -> 0 | H165: ='Hotel Stay'!F7 -> 0 | I165: ='Hotel Stay'!G7 -> 0
B166: 3 | D166: UK (London) | E166: ='Hotel Stay'!C8 -> 0 | F166: ='Hotel Stay'!D8 -> 0 | G166: ='Hotel Stay'!E8 -> 0 | H166: ='Hotel Stay'!F8 -> 0 | I166: ='Hotel Stay'!G8 -> 0
A167: Material use | B167: 3 | D167: Average construction (primary material production) | E167: ='Material Use'!C9 -> 0 | F167: ='Material Use'!D9 -> 0 | G167: ='Material Use'!E9 -> 0 | H167: ='Material Use'!F9 -> 0 | I167: ='Material Use'!G9 -> 0
B168: 3 | D168: Aggregates (primary material production) | E168: ='Material Use'!C10 -> 0 | F168: ='Material Use'!D10 -> 0 | G168: ='Material Use'!E10 -> 0 | H168: ='Material Use'!F10 -> 0 | I168: ='Material Use'!G10 -> 0
B169: 3 | D169: Aggregates (re-used) | E169: ='Material Use'!C11 -> 0 | F169: ='Material Use'!D11 -> 0 | G169: ='Material Use'!E11 -> 0 | H169: ='Material Use'!F11 -> 0 | I169: ='Material Use'!G11 -> 0
B170: 3 | D170: Aggregates (closed-loop) | E170: ='Material Use'!C12 -> 0 | F170: ='Material Use'!D12 -> 0 | G170: ='Material Use'!E12 -> 0 | H170: ='Material Use'!F12 -> 0 | I170: ='Material Use'!G12 -> 0
...

Sheet 1x2 Carbon Emissions KgCO2e SQ
E1: 2019 20 | F1: 2021 | G1: 2022 | H1: 2023 | I1: 2024 | J1: 2025
B2: Scope (1, 2, 3) | D2: Source
A3: Energy | B3: 2 | D3: Electricity | E3: ='1 Conversion Factor UK SQ'!E3*'2 Input data Summary SQ'!E3 -> 0 | F3: ='1 Conversion Factor UK SQ'!F3*'2 Input data Summary SQ'!F3 -> 0 | G3: ='1 Conversion Factor UK SQ'!G3*'2 Input data Summary SQ'!G3 -> 0 | H3: ='1 Conversion Factor UK SQ'!H3*'2 Input data Summary SQ'!H3 -> 0 | I3: ='1 Conversion Factor UK SQ'!H3*'2 Input data Summary SQ'!I3 -> 0 | M3: T&D - UK electricity 2023&2022 = 0.01792 kg CO2e/kWh; 0.01879 in 2021
B4: 1 | D4: Gas | E4: ='1 Conversion Factor UK SQ'!E4*'2 Input data Summary SQ'!E4 -> 0 | F4: ='1 Conversion Factor UK SQ'!F4*'2 Input data Summary SQ'!F4 -> 0 | G4: ='1 Conversion Factor UK SQ'!G4*'2 Input data Summary SQ'!G4 -> 0 | H4: ='1 Conversion Factor UK SQ'!H4*'2 Input data Summary SQ'!H4 -> 0 | I4: ='1 Conversion Factor UK SQ'!H4*'2 Input data Summary SQ'!I4 -> 0
B5: 1 | D5: Diesel | E5: ='1 Conversion Factor UK SQ'!E5*'2 Input data Summary SQ'!E5 -> 0 | F5: ='1 Conversion Factor UK SQ'!F5*'2 Input data Summary SQ'!F5 -> 0 | G5: ='1 Conversion Factor UK SQ'!G5*'2 Input data Summary SQ'!G5 -> 0 | H5: ='1 Conversion Factor UK SQ'!H5*'2 Input data Summary SQ'!H5 -> 0 | I5: ='1 Conversion Factor UK SQ'!H5*'2 Input data Summary SQ'!I5 -> 0
B6: 1 | D6: Oil | E6: ='1 Conversion Factor UK SQ'!E6*'2 Input data Summary SQ'!E6 -> 0 | F6: ='1 Conversion Factor UK SQ'!F6*'2 Input data Summary SQ'!F6 -> 0 | G6: ='1 Conversion Factor UK SQ'!G6*'2 Input data Summary SQ'!G6 -> 0 | H6: ='1 Conversion Factor UK SQ'!H6*'2 Input data Summary SQ'!H6 -> 0 | I6: ='1 Conversion Factor UK SQ'!H6*'2 Input data Summary SQ'!I6 -> 0
B7: 3 | D7: Transmission and distribution - T&D- UK electricity | E7: ='1 Conversion Factor UK SQ'!E7*'2 Input data Summary SQ'!E7 -> 0 | F7: ='1 Conversion Factor UK SQ'!F7*'2 Input data Summary SQ'!F7 -> 0 | G7: ='1 Conversion Factor UK SQ'!G7*'2 Input data Summary SQ'!G7 -> 0 | H7: ='1 Conversion Factor UK SQ'!H7*'2 Input data Summary SQ'!H7 -> 0 | I7: ='1 Conversion Factor UK SQ'!H7*'2 Input data Summary SQ'!I7 -> 0 | K7: As per electricity usage - GOV Guidance
B8: 3 | D8: Transmission and distribution - Distribution - district heat & steam | E8: ='1 Conversion Factor UK SQ'!E8*'2 Input data Summary SQ'!E8 -> 0 | F8: ='1 Conversion Factor UK SQ'!F8*'2 Input data Summary SQ'!F8 -> 0 | G8: ='1 Conversion Factor UK SQ'!G8*'2 Input data Summary SQ'!G8 -> 0 | H8: ='1 Conversion Factor UK SQ'!H8*'2 Input data Summary SQ'!H8 -> 0 | I8: ='1 Conversion Factor UK SQ'!H8*'2 Input data Summary SQ'!I8 -> 0
D9: Other (i.e district heating) | E9: ='1 Conversion Factor UK SQ'!E9*'2 Input data Summary SQ'!E9 -> 0 | F9: ='1 Conversion Factor UK SQ'!F9*'2 Input data Summary SQ'!F9 -> 0 | G9: ='1 Conversion Factor UK SQ'!G9*'2 Input data Summary SQ'!G9 -> 0 | H9: ='1 Conversion Factor UK SQ'!H9*'2 Input data Summary SQ'!H9 -> 0 | I9: ='1 Conversion Factor UK SQ'!H9*'2 Input data Summary SQ'!I9 -> 0
B10: 1 | D10: On site energy generation (PV) | E10: ='1 Conversion Factor UK SQ'!E10*'2 Input data Summary SQ'!E10 -> 0 | F10: ='1 Conversion Factor UK SQ'!F10*'2 Input data Summary SQ'!F10 -> 0 | G10: ='1 Conversion Factor UK SQ'!G10*'2 Input data Summary SQ'!G10 -> 0 | H10: ='1 Conversion Factor UK SQ'!H10*'2 Input data Summary SQ'!H10 -> 0 | I10: ='1 Conversion Factor UK SQ'!H10*'2 Input data Summary SQ'!I10 -> 0 | L10: Is there any guidance on how to account for this one? Maybe it is the same as electricity??
A11: Water | B11: 3 | D11: Water | E11: ='1 Conversion Factor UK SQ'!E11*'2 Input data Summary SQ'!E11 -> 0 | F11: ='1 Conversion Factor UK SQ'!F11*'2 Input data Summary SQ'!F11 -> 0 | G11: ='1 Conversion Factor UK SQ'!G11*'2 Input data Summary SQ'!G11 -> 0 | H11: ='1 Conversion Factor UK SQ'!H11*'2 Input data Summary SQ'!H11 -> 0 | I11: ='1 Conversion Factor UK SQ'!H11*'2 Input data Summary SQ'!I11 -> 0
B12: 3 | D12: Wastewater | E12: ='1 Conversion Factor UK SQ'!E12*'2 Input data Summary SQ'!E12 -> 0 | F12: ='1 Conversion Factor UK SQ'!F12*'2 Input data Summary SQ'!F12 -> 0 | G12: ='1 Conversion Factor UK SQ'!G12*'2 Input data Summary SQ'!G12 -> 0 | H12: ='1 Conversion Factor UK SQ'!H12*'2 Input data Summary SQ'!H12 -> 0 | I12: ='1 Conversion Factor UK SQ'!H12*'2 Input data Summary SQ'!I12 -> 0
A13: Waste | B13: 3 | D13: Waste to landfill | E13: ='1 Conversion Factor UK SQ'!E13*'2 Input data Summary SQ'!E13 -> 0 | F13: ='1 Conversion Factor UK SQ'!F13*'2 Input data Summary SQ'!F13 -> 0 | G13: ='1 Conversion Factor UK SQ'!G13*'2 Input data Summary SQ'!G13 -> 0 | H13: ='1 Conversion Factor UK SQ'!H13*'2 Input data Summary SQ'!H13 -> 0 | I13: ='1 Conversion Factor UK SQ'!H13*'2 Input data Summary SQ'!I13 -> 0
B14: 3 | D14: Waste to energy | E14: ='1 Conversion Factor UK SQ'!E14*'2 Input data Summary SQ'!E14 -> 0 | F14: ='1 Conversion Factor UK SQ'!F14*'2 Input data Summary SQ'!F14 -> 0 | G14: ='1 Conversion Factor UK SQ'!G14*'2 Input data Summary SQ'!G14 -> 0 | H14: ='1 Conversion Factor UK SQ'!H14*'2 Input data Summary SQ'!H14 -> 0 | I14: ='1 Conversion Factor UK SQ'!H14*'2 Input data Summary SQ'!I14 -> 0
B15: 3 | D15: Waste to recycling | E15: ='1 Conversion Factor UK SQ'!E15*'2 Input data Summary SQ'!E15 -> 0 | F15: ='1 Conversion Factor UK SQ'!F15*'2 Input data Summary SQ'!F15 -> 0 | G15: ='1 Conversion Factor UK SQ'!G15*'2 Input data Summary SQ'!G15 -> 0 | H15: ='1 Conversion Factor UK SQ'!H15*'2 Input data Summary SQ'!H15 -> 0 | I15: ='1 Conversion Factor UK SQ'!H15*'2 Input data Summary SQ'!I15 -> 0
B16: 3 | D16: Waste to composting | E16: ='1 Conversion Factor UK SQ'!E16*'2 Input data Summary SQ'!E16 -> 0 | F16: ='1 Conversion Factor UK SQ'!F16*'2 Input data Summary SQ'!F16 -> 0 | G16: ='1 Conversion Factor UK SQ'!G16*'2 Input data Summary SQ'!G16 -> 0 | H16: ='1 Conversion Factor UK SQ'!H16*'2 Input data Summary SQ'!H16 -> 0 | I16: ='1 Conversion Factor UK SQ'!H16*'2 Input data Summary SQ'!I16 -> 0
A17: Business Travel | B17: 3 | D17: Car (small) | Petrol | E17: ='1 Conversion Factor UK SQ'!E17*'2 Input data Summary SQ'!E17 -> 0 | F17: ='1 Conversion Factor UK SQ'!F17*'2 Input data Summary SQ'!F17 -> 0 | G17: ='1 Conversion Factor UK SQ'!G17*'2 Input data Summary SQ'!G17 -> 0 | H17: ='1 Conversion Factor UK SQ'!H17*'2 Input data Summary SQ'!H17 -> 0 | I17: ='1 Conversion Factor UK SQ'!H17*'2 Input data Summary SQ'!I17 -> 0
B18: 3 | D18: Car (medium) | Petrol | E18: ='1 Conversion Factor UK SQ'!E18*'2 Input data Summary SQ'!E18 -> 0 | F18: ='1 Conversion Factor UK SQ'!F18*'2 Input data Summary SQ'!F18 -> 0 | G18: ='1 Conversion Factor UK SQ'!G18*'2 Input data Summary SQ'!G18 -> 0 | H18: ='1 Conversion Factor UK SQ'!H18*'2 Input data Summary SQ'!H18 -> 0 | I18: ='1 Conversion Factor UK SQ'!H18*'2 Input data Summary SQ'!I18 -> 0
B19: 3 | D19: Car (large) | Petrol | E19: ='1 Conversion Factor UK SQ'!E19*'2 Input data Summary SQ'!E19 -> 0 | F19: ='1 Conversion Factor UK SQ'!F19*'2 Input data Summary SQ'!F19 -> 0 | G19: ='1 Conversion Factor UK SQ'!G19*'2 Input data Summary SQ'!G19 -> 0 | H19: ='1 Conversion Factor UK SQ'!H19*'2 Input data Summary SQ'!H19 -> 0 | I19: ='1 Conversion Factor UK SQ'!H19*'2 Input data Summary SQ'!I19 -> 0
B20: 3 | D20: Car (average) | Petrol | E20: ='1 Conversion Factor UK SQ'!E20*'2 Input data Summary SQ'!E20 -> 0 | F20: ='1 Conversion Factor UK SQ'!F20*'2 Input data Summary SQ'!F20 -> 0 | G20: ='1 Conversion Factor UK SQ'!G20*'2 Input data Summary SQ'!G20 -> 0 | H20: ='1 Conversion Factor UK SQ'!H20*'2 Input data Summary SQ'!H20 -> 0 | I20: ='1 Conversion Factor UK SQ'!H20*'2 Input data Summary SQ'!I20 -> 0
B21: 3 | D21: Car (small) | Diesel | E21: ='1 Conversion Factor UK SQ'!E21*'2 Input data Summary SQ'!E21 -> 0 | F21: ='1 Conversion Factor UK SQ'!F21*'2 Input data Summary SQ'!F21 -> 0 | G21: ='1 Conversion Factor UK SQ'!G21*'2 Input data Summary SQ'!G21 -> 0 | H21: ='1 Conversion Factor UK SQ'!H21*'2 Input data Summary SQ'!H21 -> 0 | I21: ='1 Conversion Factor UK SQ'!H21*'2 Input data Summary SQ'!I21 -> 0
B22: 3 | D22: Car (medium) | Diesel | E22: ='1 Conversion Factor UK SQ'!E22*'2 Input data Summary SQ'!E22 -> 0 | F22: ='1 Conversion Factor UK SQ'!F22*'2 Input data Summary SQ'!F22 -> 0 | G22: ='1 Conversion Factor UK SQ'!G22*'2 Input data Summary SQ'!G22 -> 0 | H22: ='1 Conversion Factor UK SQ'!H22*'2 Input data Summary SQ'!H22 -> 0 | I22: ='1 Conversion Factor UK SQ'!H22*'2 Input data Summary SQ'!I22 -> 0
B23: 3 | D23: Car (large) | Diesel | E23: ='1 Conversion Factor UK SQ'!E23*'2 Input data Summary SQ'!E23 -> 0 | F23: ='1 Conversion Factor UK SQ'!F23*'2 Input data Summary SQ'!F23 -> 0 | G23: ='1 Conversion Factor UK SQ'!G23*'2 Input data Summary SQ'!G23 -> 0 | H23: ='1 Conversion Factor UK SQ'!H23*'2 Input data Summary SQ'!H23 -> 0 | I23: ='1 Conversion Factor UK SQ'!H23*'2 Input data Summary SQ'!I23 -> 0
B24: 3 | D24: Car (average) | Diesel | E24: ='1 Conversion Factor UK SQ'!E24*'2 Input data Summary SQ'!E24 -> 0 | F24: ='1 Conversion Factor UK SQ'!F24*'2 Input data Summary SQ'!F24 -> 0 | G24: ='1 Conversion Factor UK SQ'!G24*'2 Input data Summary SQ'!G24 -> 0 | H24: ='1 Conversion Factor UK SQ'!H24*'2 Input data Summary SQ'!H24 -> 0 | I24: ='1 Conversion Factor UK SQ'!H24*'2 Input data Summary SQ'!I24 -> 0
B25: 3 | D25: Car (small) | Hybrid | E25: ='1 Conversion Factor UK SQ'!E25*'2 Input data Summary SQ'!E25 -> 0 | F25: ='1 Conversion Factor UK SQ'!F25*'2 Input data Summary SQ'!F25 -> 0 | G25: ='1 Conversion Factor UK SQ'!G25*'2 Input data Summary SQ'!G25 -> 0 | H25: ='1 Conversion Factor UK SQ'!H25*'2 Input data Summary SQ'!H25 -> 0 | I25: ='1 Conversion Factor UK SQ'!H25*'2 Input data Summary SQ'!I25 -> 0
B26: 3 | D26: Car (medium) | Hybrid | E26: ='1 Conversion Factor UK SQ'!E26*'2 Input data Summary SQ'!E26 -> 0 | F26: ='1 Conversion Factor UK SQ'!F26*'2 Input data Summary SQ'!F26 -> 0 | G26: ='1 Conversion Factor UK SQ'!G26*'2 Input data Summary SQ'!G26 -> 0 | H26: ='1 Conversion Factor UK SQ'!H26*'2 Input data Summary SQ'!H26 -> 0 | I26: ='1 Conversion Factor UK SQ'!H26*'2 Input data Summary SQ'!I26 -> 0
B27: 3 | D27: Car (large) | Hybrid | E27: ='1 Conversion Factor UK SQ'!E27*'2 Input data Summary SQ'!E27 -> 0 | F27: ='1 Conversion Factor UK SQ'!F27*'2 Input data Summary SQ'!F27 -> 0 | G27: ='1 Conversion Factor UK SQ'!G27*'2 Input data Summary SQ'!G27 -> 0 | H27: ='1 Conversion Factor UK SQ'!H27*'2 Input data Summary SQ'!H27 -> 0 | I27: ='1 Conversion Factor UK SQ'!H27*'2 Input data Summary SQ'!I27 -> 0
B28: 3 | D28: Car (average) | Hybrid | E28: ='1 Conversion Factor UK SQ'!E28*'2 Input data Summary SQ'!E28 -> 0 | F28: ='1 Conversion Factor UK SQ'!F28*'2 Input data Summary SQ'!F28 -> 0 | G28: ='1 Conversion Factor UK SQ'!G28*'2 Input data Summary SQ'!G28 -> 0 | H28: ='1 Conversion Factor UK SQ'!H28*'2 Input data Summary SQ'!H28 -> 0 | I28: ='1 Conversion Factor UK SQ'!H28*'2 Input data Summary SQ'!I28 -> 0
B29: 3 | D29: Car (small) | Plug-in Hybrid | E29: ='1 Conversion Factor UK SQ'!E29*'2 Input data Summary SQ'!E29 -> 0 | F29: ='1 Conversion Factor UK SQ'!F29*'2 Input data Summary SQ'!F29 -> 0 | G29: ='1 Conversion Factor UK SQ'!G29*'2 Input data Summary SQ'!G29 -> 0 | H29: ='1 Conversion Factor UK SQ'!H29*'2 Input data Summary SQ'!H29 -> 0 | I29: ='1 Conversion Factor UK SQ'!H29*'2 Input data Summary SQ'!I29 -> 0
... B56: 3 | D56: International (to/from non-UK) - business class | E56: ='1 Conversion Factor UK SQ'!E56*'2 Input data Summary SQ'!E56 -> 0 | F56: ='1 Conversion Factor UK SQ'!F56*'2 Input data Summary SQ'!F56 -> 0 | G56: ='1 Conversion Factor UK SQ'!G56*'2 Input data Summary SQ'!G56 -> 0 | H56: ='1 Conversion Factor UK SQ'!H56*'2 Input data Summary SQ'!H56 -> 0 | I56: ='1 Conversion Factor UK SQ'!H56*'2 Input data Summary SQ'!I56 -> 0
A57: Freighting goods | B57: 3 | D57: Average Van (up to 3.5 tonnes) (diesel) | E57: ='1 Conversion Factor UK SQ'!E57*'2 Input data Summary SQ'!E57 -> 0 | F57: ='1 Conversion Factor UK SQ'!F57*'2 Input data Summary SQ'!F57 -> 0 | G57: ='1 Conversion Factor UK SQ'!G57*'2 Input data Summary SQ'!G57 -> 0 | H57: ='1 Conversion Factor UK SQ'!H57*'2 Input data Summary SQ'!H57 -> 0 | I57: ='1 Conversion Factor UK SQ'!H57*'2 Input data Summary SQ'!I57 -> 0
B58: 3 | D58: Average Van (up to 3.5 tonnes) (petrol) | E58: ='1 Conversion Factor UK SQ'!E58*'2 Input data Summary SQ'!E58 -> 0 | F58: ='1 Conversion Factor UK SQ'!F58*'2 Input data Summary SQ'!F58 -> 0 | G58: ='1 Conversion Factor UK SQ'!G58*'2 Input data Summary SQ'!G58 -> 0 | H58: ='1 Conversion Factor UK SQ'!H58*'2 Input data Summary SQ'!H58 -> 0 | I58: ='1 Conversion Factor UK SQ'!H58*'2 Input data Summary SQ'!I58 -> 0
B59: 3 | D59: HGVs (diesel) | E59: ='1 Conversion Factor UK SQ'!E59*'2 Input data Summary SQ'!E59 -> 0 | F59: ='1 Conversion Factor UK SQ'!F59*'2 Input data Summary SQ'!F59 -> 0 | G59: ='1 Conversion Factor UK SQ'!G59*'2 Input data Summary SQ'!G59 -> 0 | H59: ='1 Conversion Factor UK SQ'!H59*'2 Input data Summary SQ'!H59 -> 0 | I59: ='1 Conversion Factor UK SQ'!H59*'2 Input data Summary SQ'!I59 -> 0
B60: 3 | D60: Refrigerated HGVs (diesel) | E60: ='1 Conversion Factor UK SQ'!E60*'2 Input data Summary SQ'!E60 -> 0 | F60: ='1 Conversion Factor UK SQ'!F60*'2 Input data Summary SQ'!F60 -> 0 | G60: ='1 Conversion Factor UK SQ'!G60*'2 Input data Summary SQ'!G60 -> 0 | H60: ='1 Conversion Factor UK SQ'!H60*'2 Input data Summary SQ'!H60 -> 0 | I60: ='1 Conversion Factor UK SQ'!H60*'2 Input data Summary SQ'!I60 -> 0
B61: 3 | D61: Freight flights (Domestic to/from UK) | E61: ='1 Conversion Factor UK SQ'!E61*'2 Input data Summary SQ'!E61 -> 0 | F61: ='1 Conversion Factor UK SQ'!F61*'2 Input data Summary SQ'!F61 -> 0 | G61: ='1 Conversion Factor UK SQ'!G61*'2 Input data Summary SQ'!G61 -> 0 | H61: ='1 Conversion Factor UK SQ'!H61*'2 Input data Summary SQ'!H61 -> 0 | I61: ='1 Conversion Factor UK SQ'!H61*'2 Input data Summary SQ'!I61 -> 0
B62: 3 | D62: Freight flights (Short-haul to/from UK) | E62: ='1 Conversion Factor UK SQ'!E62*'2 Input data Summary SQ'!E62 -> 0 | F62: ='1 Conversion Factor UK SQ'!F62*'2 Input data Summary SQ'!F62 -> 0 | G62: ='1 Conversion Factor UK SQ'!G62*'2 Input data Summary SQ'!G62 -> 0 | H62: ='1 Conversion Factor UK SQ'!H62*'2 Input data Summary SQ'!H62 -> 0 | I62: ='1 Conversion Factor UK SQ'!H62*'2 Input data Summary SQ'!I62 -> 0
B63: 3 | D63: Freight flights (Long haul to/from UK) | E63: ='1 Conversion Factor UK SQ'!E63*'2 Input data Summary SQ'!E63 -> 0 | F63: ='1 Conversion Factor UK SQ'!F63*'2 Input data Summary SQ'!F63 -> 0 | G63: ='1 Conversion Factor UK SQ'!G63*'2 Input data Summary SQ'!G63 -> 0 | H63: ='1 Conversion Factor UK SQ'!H63*'2 Input data Summary SQ'!H63 -> 0 | I63: ='1 Conversion Factor UK SQ'!H63*'2 Input data Summary SQ'!I63 -> 0
B64: 3 | D64: Freight flights (International to/from UK) | E64: ='1 Conversion Factor UK SQ'!E64*'2 Input data Summary SQ'!E64 -> 0 | F64: ='1 Conversion Factor UK SQ'!F64*'2 Input data Summary SQ'!F64 -> 0 | G64: ='1 Conversion Factor UK SQ'!G64*'2 Input data Summary SQ'!G64 -> 0 | H64: ='1 Conversion Factor UK SQ'!H64*'2 Input data Summary SQ'!H64 -> 0 | I64: ='1 Conversion Factor UK SQ'!H64*'2 Input data Summary SQ'!I64 -> 0
B65: 3 | D65: Rail (freight train) | E65: ='1 Conversion Factor UK SQ'!E65*'2 Input data Summary SQ'!E65 -> 0 | F65: ='1 Conversion Factor UK SQ'!F65*'2 Input data Summary SQ'!F65 -> 0 | G65: ='1 Conversion Factor UK SQ'!G65*'2 Input data Summary SQ'!G65 -> 0 | H65: ='1 Conversion Factor UK SQ'!H65*'2 Input data Summary SQ'!H65 -> 0 | I65: ='1 Conversion Factor UK SQ'!H65*'2 Input data Summary SQ'!I65 -> 0
B66: 3 | D66: Cargo Ship (Bulk carrier) | E66: ='1 Conversion Factor UK SQ'!E66*'2 Input data Summary SQ'!E66 -> 0 | F66: ='1 Conversion Factor UK SQ'!F66*'2 Input data Summary SQ'!F66 -> 0 | G66: ='1 Conversion Factor UK SQ'!G66*'2 Input data Summary SQ'!G66 -> 0 | H66: ='1 Conversion Factor UK SQ'!H66*'2 Input data Summary SQ'!H66 -> 0 | I66: ='1 Conversion Factor UK SQ'!H66*'2 Input data Summary SQ'!I66 -> 0
B67: 3 | D67: Cargo Ship (General cargo) | E67: ='1 Conversion Factor UK SQ'!E67*'2 Input data Summary SQ'!E67 -> 0 | F67: ='1 Conversion Factor UK SQ'!F67*'2 Input data Summary SQ'!F67 -> 0 | G67: ='1 Conversion Factor UK SQ'!G67*'2 Input data Summary SQ'!G67 -> 0 | H67: ='1 Conversion Factor UK SQ'!H67*'2 Input data Summary SQ'!H67 -> 0 | I67: ='1 Conversion Factor UK SQ'!H67*'2 Input data Summary SQ'!I67 -> 0
B68: 3 | D68: Cargo Ship (Container ship) | E68: ='1 Conversion Factor UK SQ'!E68*'2 Input data Summary SQ'!E68 -> 0 | F68: ='1 Conversion Factor UK SQ'!F68*'2 Input data Summary SQ'!F68 -> 0 | G68: ='1 Conversion Factor UK SQ'!G68*'2 Input data Summary SQ'!G68 -> 0 | H68: ='1 Conversion Factor UK SQ'!H68*'2 Input data Summary SQ'!H68 -> 0 | I68: ='1 Conversion Factor UK SQ'!H68*'2 Input data Summary SQ'!I68 -> 0
B69: 3 | D69: Cargo Ship (Vehicle transport) | E69: ='1 Conversion Factor UK SQ'!E69*'2 Input data Summary SQ'!E69 -> 0 | F69: ='1 Conversion Factor UK SQ'!F69*'2 Input data Summary SQ'!F69 -> 0 | G69: ='1 Conversion Factor UK SQ'!G69*'2 Input data Summary SQ'!G69 -> 0 | H69: ='1 Conversion Factor UK SQ'!H69*'2 Input data Summary SQ'!H69 -> 0 | I69: ='1 Conversion Factor UK SQ'!H69*'2 Input data Summary SQ'!I69 -> 0
B70: 3 | D70: Cargo Ship (Refrigerated cargo) | E70: ='1 Conversion Factor UK SQ'!E70*'2 Input data Summary SQ'!E70 -> 0 | F70: ='1 Conversion Factor UK SQ'!F70*'2 Input data Summary SQ'!F70 -> 0 | G70: ='1 Conversion Factor UK SQ'!G70*'2 Input data Summary SQ'!G70 -> 0 | H70: ='1 Conversion Factor UK SQ'!H70*'2 Input data Summary SQ'!H70 -> 0 | I70: ='1 Conversion Factor UK SQ'!H70*'2 Input data Summary SQ'!I70 -> 0
A71: Staff Commute | B71: 3 | D71: Car (small) | Petrol | E71: ='1 Conversion Factor UK SQ'!E71*'2 Input data Summary SQ'!E71 -> 0 | F71: ='1 Conversion Factor UK SQ'!F71*'2 Input data Summary SQ'!F71 -> 0 | G71: ='1 Conversion Factor UK SQ'!G71*'2 Input data Summary SQ'!G71 -> 0 | H71: ='1 Conversion Factor UK SQ'!H71*'2 Input data Summary SQ'!H71 -> 0 | I71: ='1 Conversion Factor UK SQ'!H71*'2 Input data Summary SQ'!I71 -> 0
B72: 3 | D72: Car (medium) | Petrol | E72: ='1 Conversion Factor UK SQ'!E72*'2 Input data Summary SQ'!E72 -> 0 | F72: ='1 Conversion Factor UK SQ'!F72*'2 Input data Summary SQ'!F72 -> 0 | G72: ='1 Conversion Factor UK SQ'!G72*'2 Input data Summary SQ'!G72 -> 0 | H72: ='1 Conversion Factor UK SQ'!H72*'2 Input data Summary SQ'!H72 -> 0 | I72: ='1 Conversion Factor UK SQ'!H72*'2 Input data Summary SQ'!I72 -> 0
B73: 3 | D73: Car (large) | Petrol | E73: ='1 Conversion Factor UK SQ'!E73*'2 Input data Summary SQ'!E73 -> 0 | F73: ='1 Conversion Factor UK SQ'!F73*'2 Input data Summary SQ'!F73 -> 0 | G73: ='1 Conversion Factor UK SQ'!G73*'2 Input data Summary SQ'!G73 -> 0 | H73: ='1 Conversion Factor UK SQ'!H73*'2 Input data Summary SQ'!H73 -> 0 | I73: ='1 Conversion Factor UK SQ'!H73*'2 Input data Summary SQ'!I73 -> 0
B74: 3 | D74: Car (average) | Petrol | E74: ='1 Conversion Factor UK SQ'!E74*'2 Input data Summary SQ'!E74 -> 0 | F74: ='1 Conversion Factor UK SQ'!F74*'2 Input data Summary SQ'!F74 -> 0 | G74: ='1 Conversion Factor UK SQ'!G74*'2 Input data Summary SQ'!G74 -> 0 | H74: ='1 Conversion Factor UK SQ'!H74*'2 Input data Summary SQ'!H74 -> 0 | I74: ='1 Conversion Factor UK SQ'!H74*'2 Input data Summary SQ'!I74 -> 0
B75: 3 | D75: Car (small) | Diesel | E75: ='1 Conversion Factor UK SQ'!E75*'2 Input data Summary SQ'!E75 -> 0 | F75: ='1 Conversion Factor UK SQ'!F75*'2 Input data Summary SQ'!F75 -> 0 | G75: ='1 Conversion Factor UK SQ'!G75*'2 Input data Summary SQ'!G75 -> 0 | H75: ='1 Conversion Factor UK SQ'!H75*'2 Input data Summary SQ'!H75 -> 0 | I75: ='1 Conversion Factor UK SQ'!H75*'2 Input data Summary SQ'!I75 -> 0
B76: 3 | D76: Car (medium) | Diesel | E76: ='1 Conversion Factor UK SQ'!E76*'2 Input data Summary SQ'!E76 -> 0 | F76: ='1 Conversion Factor UK SQ'!F76*'2 Input data Summary SQ'!F76 -> 0 | G76: ='1 Conversion Factor UK SQ'!G76*'2 Input data Summary SQ'!G76 -> 0 | H76: ='1 Conversion Factor UK SQ'!H76*'2 Input data Summary SQ'!H76 -> 0 | I76: ='1 Conversion Factor UK SQ'!H76*'2 Input data Summary SQ'!I76 -> 0
B77: 3 | D77: Car (large) | Diesel | E77: ='1 Conversion Factor UK SQ'!E77*'2 Input data Summary SQ'!E77 -> 0 | F77: ='1 Conversion Factor UK SQ'!F77*'2 Input data Summary SQ'!F77 -> 0 | G77: ='1 Conversion Factor UK SQ'!G77*'2 Input data Summary SQ'!G77 -> 0 | H77: ='1 Conversion Factor UK SQ'!H77*'2 Input data Summary SQ'!H77 -> 0 | I77: ='1 Conversion Factor UK SQ'!H77*'2 Input data Summary SQ'!I77 -> 0
B78: 3 | D78: Car (average) | Diesel | E78: ='1 Conversion Factor UK SQ'!E78*'2 Input data Summary SQ'!E78 -> 0 | F78: ='1 Conversion Factor UK SQ'!F78*'2 Input data Summary SQ'!F78 -> 0 | G78: ='1 Conversion Factor UK SQ'!G78*'2 Input data Summary SQ'!G78 -> 0 | H78: ='1 Conversion Factor UK SQ'!H78*'2 Input data Summary SQ'!H78 -> 0 | I78: ='1 Conversion Factor UK SQ'!H78*'2 Input data Summary SQ'!I78 -> 0
B79: 3 | D79: Car (small) | Hybrid | E79: ='1 Conversion Factor UK SQ'!E79*'2 Input data Summary SQ'!E79 -> 0 | F79: ='1 Conversion Factor UK SQ'!F79*'2 Input data Summary SQ'!F79 -> 0 | G79: ='1 Conversion Factor UK SQ'!G79*'2 Input data Summary SQ'!G79 -> 0 | H79: ='1 Conversion Factor UK SQ'!H79*'2 Input data Summary SQ'!H79 -> 0 | I79: ='1 Conversion Factor UK SQ'!H79*'2 Input data Summary SQ'!I79 -> 0
B80: 3 | D80: Car (medium) | Hybrid | E80: ='1 Conversion Factor UK SQ'!E80*'2 Input data Summary SQ'!E80 -> 0 | F80: ='1 Conversion Factor UK SQ'!F80*'2 Input data Summary SQ'!F80 -> 0 | G80: ='1 Conversion Factor UK SQ'!G80*'2 Input data Summary SQ'!G80 -> 0 | H80: ='1 Conversion Factor UK SQ'!H80*'2 Input data Summary SQ'!H80 -> 0 | I80: ='1 Conversion Factor UK SQ'!H80*'2 Input data Summary SQ'!I80 -> 0
B81: 3 | D81: Car (large) | Hybrid | E81: ='1 Conversion Factor UK SQ'!E81*'2 Input data Summary SQ'!E81 -> 0 | F81: ='1 Conversion Factor UK SQ'!F81*'2 Input data Summary SQ'!F81 -> 0 | G81: ='1 Conversion Factor UK SQ'!G81*'2 Input data Summary SQ'!G81 -> 0 | H81: ='1 Conversion Factor UK SQ'!H81*'2 Input data Summary SQ'!H81 -> 0 | I81: ='1 Conversion Factor UK SQ'!H81*'2 Input data Summary SQ'!I81 -> 0
B82: 3 | D82: Car (average) | Hybrid | E82: ='1 Conversion Factor UK SQ'!E82*'2 Input data Summary SQ'!E82 -> 0 | F82: ='1 Conversion Factor UK SQ'!F82*'2 Input data Summary SQ'!F82 -> 0 | G82: ='1 Conversion Factor UK SQ'!G82*'2 Input data Summary SQ'!G82 -> 0 | H82: ='1 Conversion Factor UK SQ'!H82*'2 Input data Summary SQ'!H82 -> 0 | I82: ='1 Conversion Factor UK SQ'!H82*'2 Input data Summary SQ'!I82 -> 0
B83: 3 | D83: Car (small) | Plug-in Hybrid | E83: ='1 Conversion Factor UK SQ'!E83*'2 Input data Summary SQ'!E83 -> 0 | F83: ='1 Conversion Factor UK SQ'!F83*'2 Input data Summary SQ'!F83 -> 0 | G83: ='1 Conversion Factor UK SQ'!G83*'2 Input data Summary SQ'!G83 -> 0 | H83: ='1 Conversion Factor UK SQ'!H83*'2 Input data Summary SQ'!H83 -> 0 | I83: ='1 Conversion Factor UK SQ'!H83*'2 Input data Summary SQ'!I83 -> 0
... B110: 3 | D110: International (to/from non-UK) - business class | E110: ='1 Conversion Factor UK SQ'!E110*'2 Input data Summary SQ'!E110 -> 0 | F110: ='1 Conversion Factor UK SQ'!F110*'2 Input data Summary SQ'!F110 -> 0 | G110: ='1 Conversion Factor UK SQ'!G110*'2 Input data Summary SQ'!G110 -> 0 | H110: ='1 Conversion Factor UK SQ'!H110*'2 Input data Summary SQ'!H110 -> 0 | I110: ='1 Conversion Factor UK SQ'!H110*'2 Input data Summary SQ'!I110 -> 0
A111: Private vehicle for business use (SCOPE 2) | B111: 2 | D111: Car (small) | Petrol | E111: ='1 Conversion Factor UK SQ'!E111*'2 Input data Summary SQ'!E111 -> 0 | F111: ='1 Conversion Factor UK SQ'!F111*'2 Input data Summary SQ'!F111 -> 0 | G111: ='1 Conversion Factor UK SQ'!G111*'2 Input data Summary SQ'!G111 -> 0 | H111: ='1 Conversion Factor UK SQ'!H111*'2 Input data Summary SQ'!H111 -> 0 | I111: ='1 Conversion Factor UK SQ'!H111*'2 Input data Summary SQ'!I111 -> 0
B112: 2 | D112: Car (medium) | Petrol | E112: ='1 Conversion Factor UK SQ'!E112*'2 Input data Summary SQ'!E112 -> 0 | F112: ='1 Conversion Factor UK SQ'!F112*'2 Input data Summary SQ'!F112 -> 0 | G112: ='1 Conversion Factor UK SQ'!G112*'2 Input data Summary SQ'!G112 -> 0 | H112: ='1 Conversion Factor UK SQ'!H112*'2 Input data Summary SQ'!H112 -> 0 | I112: ='1 Conversion Factor UK SQ'!H112*'2 Input data Summary SQ'!I112 -> 0
B113: 2 | D113: Car (large) | Petrol | E113: ='1 Conversion Factor UK SQ'!E113*'2 Input data Summary SQ'!E113 -> 0 | F113: ='1 Conversion Factor UK SQ'!F113*'2 Input data Summary SQ'!F113 -> 0 | G113: ='1 Conversion Factor UK SQ'!G113*'2 Input data Summary SQ'!G113 -> 0 | H113: ='1 Conversion Factor UK SQ'!H113*'2 Input data Summary SQ'!H113 -> 0 | I113: ='1 Conversion Factor UK SQ'!H113*'2 Input data Summary SQ'!I113 -> 0
B114: 2 | D114: Car (average) | Petrol | E114: ='1 Conversion Factor UK SQ'!E114*'2 Input data Summary SQ'!E114 -> 0 | F114: ='1 Conversion Factor UK SQ'!F114*'2 Input data Summary SQ'!F114 -> 0 | G114: ='1 Conversion Factor UK SQ'!G114*'2 Input data Summary SQ'!G114 -> 0 | H114: ='1 Conversion Factor UK SQ'!H114*'2 Input data Summary SQ'!H114 -> 0 | I114: ='1 Conversion Factor UK SQ'!H114*'2 Input data Summary SQ'!I114 -> 0
B115: 2 | D115: Car (small) | Diesel | E115: ='1 Conversion Factor UK SQ'!E115*'2 Input data Summary SQ'!E115 -> 0 | F115: ='1 Conversion Factor UK SQ'!F115*'2 Input data Summary SQ'!F115 -> 0 | G115: ='1 Conversion Factor UK SQ'!G115*'2 Input data Summary SQ'!G115 -> 0 | H115: ='1 Conversion Factor UK SQ'!H115*'2 Input data Summary SQ'!H115 -> 0 | I115: ='1 Conversion Factor UK SQ'!H115*'2 Input data Summary SQ'!I115 -> 0
B116: 2 | D116: Car (medium) | Diesel | E116: ='1 Conversion Factor UK SQ'!E116*'2 Input data Summary SQ'!E116 -> 0 | F116: ='1 Conversion Factor UK SQ'!F116*'2 Input data Summary SQ'!F116 -> 0 | G116: ='1 Conversion Factor UK SQ'!G116*'2 Input data Summary SQ'!G116 -> 0 | H116: ='1 Conversion Factor UK SQ'!H116*'2 Input data Summary SQ'!H116 -> 0 | I116: ='1 Conversion Factor UK SQ'!H116*'2 Input data Summary SQ'!I116 -> 0
B117: 2 | D117: Car (large) | Diesel | E117: ='1 Conversion Factor UK SQ'!E117*'2 Input data Summary SQ'!E117 -> 0 | F117: ='1 Conversion Factor UK SQ'!F117*'2 Input data Summary SQ'!F117 -> 0 | G117: ='1 Conversion Factor UK SQ'!G117*'2 Input data Summary SQ'!G117 -> 0 | H117: ='1 Conversion Factor UK SQ'!H117*'2 Input data Summary SQ'!H117 -> 0 | I117: ='1 Conversion Factor UK SQ'!H117*'2 Input data Summary SQ'!I117 -> 0
B118: 2 | D118: Car (average) | Diesel | E118: ='1 Conversion Factor UK SQ'!E118*'2 Input data Summary SQ'!E118 -> 0 | F118: ='1 Conversion Factor UK SQ'!F118*'2 Input data Summary SQ'!F118 -> 0 | G118: ='1 Conversion Factor UK SQ'!G118*'2 Input data Summary SQ'!G118 -> 0 | H118: ='1 Conversion Factor UK SQ'!H118*'2 Input data Summary SQ'!H118 -> 0 | I118: ='1 Conversion Factor UK SQ'!H118*'2 Input data Summary SQ'!I118 -> 0
B119: 2 | D119: Car (small) | Hybrid | E119: ='1 Conversion Factor UK SQ'!E119*'2 Input data Summary SQ'!E119 -> 0 | F119: ='1 Conversion Factor UK SQ'!F119*'2 Input data Summary SQ'!F119 -> 0 | G119: ='1 Conversion Factor UK SQ'!G119*'2 Input data Summary SQ'!G119 -> 0 | H119: ='1 Conversion Factor UK SQ'!H119*'2 Input data Summary SQ'!H119 -> 0 | I119: ='1 Conversion Factor UK SQ'!H119*'2 Input data Summary SQ'!I119 -> 0
B120: 2 | D120: Car (medium) | Hybrid | E120: ='1 Conversion Factor UK SQ'!E120*'2 Input data Summary SQ'!E120 -> 0 | F120: ='1 Conversion Factor UK SQ'!F120*'2 Input data Summary SQ'!F120 -> 0 | G120: ='1 Conversion Factor UK SQ'!G120*'2 Input data Summary SQ'!G120 -> 0 | H120: ='1 Conversion Factor UK SQ'!H120*'2 Input data Summary SQ'!H120 -> 0 | I120: ='1 Conversion Factor UK SQ'!H120*'2 Input data Summary SQ'!I120 -> 0
B121: 2 | D121: Car (large) | Hybrid | E121: ='1 Conversion Factor UK SQ'!E121*'2 Input data Summary SQ'!E121 -> 0 | F121: ='1 Conversion Factor UK SQ'!F121*'2 Input data Summary SQ'!F121 -> 0 | G121: ='1 Conversion Factor UK SQ'!G121*'2 Input data Summary SQ'!G121 -> 0 | H121: ='1 Conversion Factor UK SQ'!H121*'2 Input data Summary SQ'!H121 -> 0 | I121: ='1 Conversion Factor UK SQ'!H121*'2 Input data Summary SQ'!I121 -> 0
B122: 2 | D122: Car (average) | Hybrid | E122: ='1 Conversion Factor UK SQ'!E122*'2 Input data Summary SQ'!E122 -> 0 | F122: ='1 Conversion Factor UK SQ'!F122*'2 Input data Summary SQ'!F122 -> 0 | G122: ='1 Conversion Factor UK SQ'!G122*'2 Input data Summary SQ'!G122 -> 0 | H122: ='1 Conversion Factor UK SQ'!H122*'2 Input data Summary SQ'!H122 -> 0 | I122: ='1 Conversion Factor UK SQ'!H122*'2 Input data Summary SQ'!I122 -> 0
B123: 2 | D123: Car (small) | Plug-in Hybrid | E123: ='1 Conversion Factor UK SQ'!E123*'2 Input data Summary SQ'!E123 -> 0 | F123: ='1 Conversion Factor UK SQ'!F123*'2 Input data Summary SQ'!F123 -> 0 | G123: ='1 Conversion Factor UK SQ'!G123*'2 Input data Summary SQ'!G123 -> 0 | H123: ='1 Conversion Factor UK SQ'!H123*'2 Input data Summary SQ'!H123 -> 0 | I123: ='1 Conversion Factor UK SQ'!H123*'2 Input data Summary SQ'!I123 -> 0
... B126: 2 | D126: Car (average) | Plug-in Hybrid | E126: ='1 Conversion Factor UK SQ'!E126*'2 Input data Summary SQ'!E126 -> 0 | F126: ='1 Conversion Factor UK SQ'!F126*'2 Input data Summary SQ'!F126 -> 0 | G126: ='1 Conversion Factor UK SQ'!G126*'2 Input data Summary SQ'!G126 -> 0 | H126: ='1 Conversion Factor UK SQ'!H126*'2 Input data Summary SQ'!H126 -> 0 | I126: ='1 Conversion Factor UK SQ'!H126*'2 Input data Summary SQ'!I126 -> 0
A127: Company fleet and leased vehicles (SCOPE 1) | B127: 1 | D127: Average Van (up to 3.5 tonnes) (diesel) | E127: ='1 Conversion Factor UK SQ'!E127*'2 Input data Summary SQ'!E127 -> 0 | F127: ='1 Conversion Factor UK SQ'!F127*'2 Input data Summary SQ'!F127 -> 0 | G127: ='1 Conversion Factor UK SQ'!G127*'2 Input data Summary SQ'!G127 -> 0 | H127: ='1 Conversion Factor UK SQ'!H127*'2 Input data Summary SQ'!H127 -> 0 | I127: ='1 Conversion Factor UK SQ'!H127*'2 Input data Summary SQ'!I127 -> 0
B128: 1 | D128: Average Van (up to 3.5 tonnes) (petrol) | E128: ='1 Conversion Factor UK SQ'!E128*'2 Input data Summary SQ'!E128 -> 0 | F128: ='1 Conversion Factor UK SQ'!F128*'2 Input data Summary SQ'!F128 -> 0 | G128: ='1 Conversion Factor UK SQ'!G128*'2 Input data Summary SQ'!G128 -> 0 | H128: ='1 Conversion Factor UK SQ'!H128*'2 Input data Summary SQ'!H128 -> 0 | I128: ='1 Conversion Factor UK SQ'!H128*'2 Input data Summary SQ'!I128 -> 0
B129: 1 | D129: HGVs (diesel) | E129: ='1 Conversion Factor UK SQ'!E129*'2 Input data Summary SQ'!E129 -> 0 | F129: ='1 Conversion Factor UK SQ'!F129*'2 Input data Summary SQ'!F129 -> 0 | G129: ='1 Conversion Factor UK SQ'!G129*'2 Input data Summary SQ'!G129 -> 0 | H129: ='1 Conversion Factor UK SQ'!H129*'2 Input data Summary SQ'!H129 -> 0 | I129: ='1 Conversion Factor UK SQ'!H129*'2 Input data Summary SQ'!I129 -> 0
B130: 1 | D130: Refrigerated HGVs (diesel) | E130: ='1 Conversion Factor UK SQ'!E130*'2 Input data Summary SQ'!E130 -> 0 | F130: ='1 Conversion Factor UK SQ'!F130*'2 Input data Summary SQ'!F130 -> 0 | G130: ='1 Conversion Factor UK SQ'!G130*'2 Input data Summary SQ'!G130 -> 0 | H130: ='1 Conversion Factor UK SQ'!H130*'2 Input data Summary SQ'!H130 -> 0 | I130: ='1 Conversion Factor UK SQ'!H130*'2 Input data Summary SQ'!I130 -> 0
B131: 1 | D131: Freight flights (Domestic to/from UK) | E131: ='1 Conversion Factor UK SQ'!E131*'2 Input data Summary SQ'!E131 -> 0 | F131: ='1 Conversion Factor UK SQ'!F131*'2 Input data Summary SQ'!F131 -> 0 | G131: ='1 Conversion Factor UK SQ'!G131*'2 Input data Summary SQ'!G131 -> 0 | H131: ='1 Conversion Factor UK SQ'!H131*'2 Input data Summary SQ'!H131 -> 0 | I131: ='1 Conversion Factor UK SQ'!H131*'2 Input data Summary SQ'!I131 -> 0
B132: 1 | D132: Freight flights (Short-haul to/from UK) | E132: ='1 Conversion Factor UK SQ'!E132*'2 Input data Summary SQ'!E132 -> 0 | F132: ='1 Conversion Factor UK SQ'!F132*'2 Input data Summary SQ'!F132 -> 0 | G132: ='1 Conversion Factor UK SQ'!G132*'2 Input data Summary SQ'!G132 -> 0 | H132: ='1 Conversion Factor UK SQ'!H132*'2 Input data Summary SQ'!H132 -> 0 | I132: ='1 Conversion Factor UK SQ'!H132*'2 Input data Summary SQ'!I132 -> 0
B133: 1 | D133: Freight flights (Long haul to/from UK) | E133: ='1 Conversion Factor UK SQ'!E133*'2 Input data Summary SQ'!E133 -> 0 | F133: ='1 Conversion Factor UK SQ'!F133*'2 Input data Summary SQ'!F133 -> 0 | G133: ='1 Conversion Factor UK SQ'!G133*'2 Input data Summary SQ'!G133 -> 0 | H133: ='1 Conversion Factor UK SQ'!H133*'2 Input data Summary SQ'!H133 -> 0 | I133: ='1 Conversion Factor UK SQ'!H133*'2 Input data Summary SQ'!I133 -> 0
B134: 1 | D134: Freight flights (International to/from UK) | E134: ='1 Conversion Factor UK SQ'!E134*'2 Input data Summary SQ'!E134 -> 0 | F134: ='1 Conversion Factor UK SQ'!F134*'2 Input data Summary SQ'!F134 -> 0 | G134: ='1 Conversion Factor UK SQ'!G134*'2 Input data Summary SQ'!G134 -> 0 | H134: ='1 Conversion Factor UK SQ'!H134*'2 Input data Summary SQ'!H134 -> 0 | I134: ='1 Conversion Factor UK SQ'!H134*'2 Input data Summary SQ'!I134 -> 0
B135: 1 | D135: Rail (freight train) | E135: ='1 Conversion Factor UK SQ'!E135*'2 Input data Summary SQ'!E135 -> 0 | F135: ='1 Conversion Factor UK SQ'!F135*'2 Input data Summary SQ'!F135 -> 0 | G135: ='1 Conversion Factor UK SQ'!G135*'2 Input data Summary SQ'!G135 -> 0 | H135: ='1 Conversion Factor UK SQ'!H135*'2 Input data Summary SQ'!H135 -> 0 | I135: ='1 Conversion Factor UK SQ'!H135*'2 Input data Summary SQ'!I135 -> 0
B136: 1 | D136: Cargo Ship (Bulk carrier) | E136: ='1 Conversion Factor UK SQ'!E136*'2 Input data Summary SQ'!E136 -> 0 | F136: ='1 Conversion Factor UK SQ'!F136*'2 Input data Summary SQ'!F136 -> 0 | G136: ='1 Conversion Factor UK SQ'!G136*'2 Input data Summary SQ'!G136 -> 0 | H136: ='1 Conversion Factor UK SQ'!H136*'2 Input data Summary SQ'!H136 -> 0 | I136: ='1 Conversion Factor UK SQ'!H136*'2 Input data Summary SQ'!I136 -> 0
B137: 1 | D137: Cargo Ship (General cargo) | E137: ='1 Conversion Factor UK SQ'!E137*'2 Input data Summary SQ'!E137 -> 0 | F137: ='1 Conversion Factor UK SQ'!F137*'2 Input data Summary SQ'!F137 -> 0 | G137: ='1 Conversion Factor UK SQ'!G137*'2 Input data Summary SQ'!G137 -> 0 | H137: ='1 Conversion Factor UK SQ'!H137*'2 Input data Summary SQ'!H137 -> 0 | I137: ='1 Conversion Factor UK SQ'!H137*'2 Input data Summary SQ'!I137 -> 0
B138: 1 | D138: Cargo Ship (Container ship) | E138: ='1 Conversion Factor UK SQ'!E138*'2 Input data Summary SQ'!E138 -> 0 | F138: ='1 Conversion Factor UK SQ'!F138*'2 Input data Summary SQ'!F138 -> 0 | G138: ='1 Conversion Factor UK SQ'!G138*'2 Input data Summary SQ'!G138 -> 0 | H138: ='1 Conversion Factor UK SQ'!H138*'2 Input data Summary SQ'!H138 -> 0 | I138: ='1 Conversion Factor UK SQ'!H138*'2 Input data Summary SQ'!I138 -> 0
B139: 1 | D139: Cargo Ship (Vehicle transport) | E139: ='1 Conversion Factor UK SQ'!E139*'2 Input data Summary SQ'!E139 -> 0 | F139: ='1 Conversion Factor UK SQ'!F139*'2 Input data Summary SQ'!F139 -> 0 | G139: ='1 Conversion Factor UK SQ'!G139*'2 Input data Summary SQ'!G139 -> 0 | H139: ='1 Conversion Factor UK SQ'!H139*'2 Input data Summary SQ'!H139 -> 0 | I139: ='1 Conversion Factor UK SQ'!H139*'2 Input data Summary SQ'!I139 -> 0
... B156: 1 | D156: Car (average) | Plug-in Hybrid | E156: ='1 Conversion Factor UK SQ'!E156*'2 Input data Summary SQ'!E156 -> 0 | F156: ='1 Conversion Factor UK SQ'!F156*'2 Input data Summary SQ'!F156 -> 0 | G156: ='1 Conversion Factor UK SQ'!G156*'2 Input data Summary SQ'!G156 -> 0 | H156: ='1 Conversion Factor UK SQ'!H156*'2 Input data Summary SQ'!H156 -> 0 | I156: ='1 Conversion Factor UK SQ'!H156*'2 Input data Summary SQ'!I156 -> 0
A157: Refrigerants | B157: 1 | D157: R404A | E157: ='1 Conversion Factor UK SQ'!E157*'2 Input data Summary SQ'!E157 -> 0 | F157: ='1 Conversion Factor UK SQ'!F157*'2 Input data Summary SQ'!F157 -> 0 | G157: ='1 Conversion Factor UK SQ'!G157*'2 Input data Summary SQ'!G157 -> 0 | H157: ='1 Conversion Factor UK SQ'!H157*'2 Input data Summary SQ'!H157 -> 0 | I157: ='1 Conversion Factor UK SQ'!H157*'2 Input data Summary SQ'!I157 -> 0 | L157: Emissions including only kyoto products
B158: 1 | D158: R407A | E158: ='1 Conversion Factor UK SQ'!E158*'2 Input data Summary SQ'!E158 -> 0 | F158: ='1 Conversion Factor UK SQ'!F158*'2 Input data Summary SQ'!F158 -> 0 | G158: ='1 Conversion Factor UK SQ'!G158*'2 Input data Summary SQ'!G158 -> 0 | H158: ='1 Conversion Factor UK SQ'!H158*'2 Input data Summary SQ'!H158 -> 0 | I158: ='1 Conversion Factor UK SQ'!H158*'2 Input data Summary SQ'!I158 -> 0
B159: 1 | D159: R407C | E159: ='1 Conversion Factor UK SQ'!E159*'2 Input data Summary SQ'!E159 -> 0 | F159: ='1 Conversion Factor UK SQ'!F159*'2 Input data Summary SQ'!F159 -> 0 | G159: ='1 Conversion Factor UK SQ'!G159*'2 Input data Summary SQ'!G159 -> 0 | H159: ='1 Conversion Factor UK SQ'!H159*'2 Input data Summary SQ'!H159 -> 0 | I159: ='1 Conversion Factor UK SQ'!H159*'2 Input data Summary SQ'!I159 -> 0
B160: 1 | D160: R408A | E160: ='1 Conversion Factor UK SQ'!E160*'2 Input data Summary SQ'!E160 -> 0 | F160: ='1 Conversion Factor UK SQ'!F160*'2 Input data Summary SQ'!F160 -> 0 | G160: ='1 Conversion Factor UK SQ'!G160*'2 Input data Summary SQ'!G160 -> 0 | H160: ='1 Conversion Factor UK SQ'!H160*'2 Input data Summary SQ'!H160 -> 0 | I160: ='1 Conversion Factor UK SQ'!H160*'2 Input data Summary SQ'!I160 -> 0
B161: 1 | D161: R410A | E161: ='1 Conversion Factor UK SQ'!E161*'2 Input data Summary SQ'!E161 -> 0 | F161: ='1 Conversion Factor UK SQ'!F161*'2 Input data Summary SQ'!F161 -> 0 | G161: ='1 Conversion Factor UK SQ'!G161*'2 Input data Summary SQ'!G161 -> 0 | H161: ='1 Conversion Factor UK SQ'!H161*'2 Input data Summary SQ'!H161 -> 0 | I161: ='1 Conversion Factor UK SQ'!H161*'2 Input data Summary SQ'!I161 -> 0
B162: 1 | D162: R134a | E162: ='1 Conversion Factor UK SQ'!E162*'2 Input data Summary SQ'!E162 -> 0 | F162: ='1 Conversion Factor UK SQ'!F162*'2 Input data Summary SQ'!F162 -> 0 | G162: ='1 Conversion Factor UK SQ'!G162*'2 Input data Summary SQ'!G162 -> 0 | H162: ='1 Conversion Factor UK SQ'!H162*'2 Input data Summary SQ'!H162 -> 0 | I162: ='1 Conversion Factor UK SQ'!H162*'2 Input data Summary SQ'!I162 -> 0
B163: 1 | D163: Other | E163: ='1 Conversion Factor UK SQ'!E163*'2 Input data Summary SQ'!E163 -> 0 | F163: ='1 Conversion Factor UK SQ'!F163*'2 Input data Summary SQ'!F163 -> 0 | G163: ='1 Conversion Factor UK SQ'!G163*'2 Input data Summary SQ'!G163 -> 0 | H163: ='1 Conversion Factor UK SQ'!H163*'2 Input data Summary SQ'!H163 -> 0 | I163: ='1 Conversion Factor UK SQ'!H163*'2 Input data Summary SQ'!I163 -> 0 | L163: Please check Refrigerant tab - other refrigerant - user input
A164: Home working | B164: 3 | D164: Home Working (hours) | E164: N/A | F164: N/A | G164: ='1 Conversion Factor UK SQ'!G164*'2 Input data Summary SQ'!G164 -> 0 | H164: ='1 Conversion Factor UK SQ'!H164*'2 Input data Summary SQ'!H164 -> 0 | I164: ='1 Conversion Factor UK SQ'!H164*'2 Input data Summary SQ'!I164 -> 1395.0719
A165: Hotel stay (UK) | B165: 3 | D165: UK | E165: ='1 Conversion Factor UK SQ'!E165*'2 Input data Summary SQ'!E165 -> 0 | F165: ='1 Conversion Factor UK SQ'!F165*'2 Input data Summary SQ'!F165 -> 0 | G165: ='1 Conversion Factor UK SQ'!G165*'2 Input data Summary SQ'!G165 -> 0 | H165: ='1 Conversion Factor UK SQ'!H165*'2 Input data Summary SQ'!H165 -> 0 | I165: ='1 Conversion Factor UK SQ'!H165*'2 Input data Summary SQ'!I165 -> 0
B166: 3 | D166: UK (London) | E166: N/A | F166: ='1 Conversion Factor UK SQ'!F166*'2 Input data Summary SQ'!F166 -> 0 | G166: ='1 Conversion Factor UK SQ'!G166*'2 Input data Summary SQ'!G166 -> 0 | H166: ='1 Conversion Factor UK SQ'!H166*'2 Input data Summary SQ'!H166 -> 0 | I166: ='1 Conversion Factor UK SQ'!H166*'2 Input data Summary SQ'!I166 -> 0
A167: Material use | B167: 3 | D167: Average construction (primary material production) | E167: ='1 Conversion Factor UK SQ'!E167*'2 Input data Summary SQ'!E167 -> 0 | F167: ='1 Conversion Factor UK SQ'!F167*'2 Input data Summary SQ'!F167 -> 0 | G167: ='1 Conversion Factor UK SQ'!G167*'2 Input data Summary SQ'!G167 -> 0 | H167: ='1 Conversion Factor UK SQ'!H167*'2 Input data Summary SQ'!H167 -> 0 | I167: ='1 Conversion Factor UK SQ'!H167*'2 Input data Summary SQ'!I167 -> 0
B168: 3 | D168: Aggregates (primary material production) | E168: ='1 Conversion Factor UK SQ'!E168*'2 Input data Summary SQ'!E168 -> 0 | F168: ='1 Conversion Factor UK SQ'!F168*'2 Input data Summary SQ'!F168 -> 0 | G168: ='1 Conversion Factor UK SQ'!G168*'2 Input data Summary SQ'!G168 -> 0 | H168: ='1 Conversion Factor UK SQ'!H168*'2 Input data Summary SQ'!H168 -> 0 | I168: ='1 Conversion Factor UK SQ'!H168*'2 Input data Summary SQ'!I168 -> 0
B169: 3 | D169: Aggregates (re-used) | E169: ='1 Conversion Factor UK SQ'!E169*'2 Input data Summary SQ'!E169 -> 0 | F169: ='1 Conversion Factor UK SQ'!F169*'2 Input data Summary SQ'!F169 -> 0 | G169: ='1 Conversion Factor UK SQ'!G169*'2 Input data Summary SQ'!G169 -> 0 | H169: ='1 Conversion Factor UK SQ'!H169*'2 Input data Summary SQ'!H169 -> 0 | I169: ='1 Conversion Factor UK SQ'!H169*'2 Input data Summary SQ'!I169 -> 0
B170: 3 | D170: Aggregates (closed-loop) | E170: ='1 Conversion Factor UK SQ'!E170*'2 Input data Summary SQ'!E170 -> 0 | F170: ='1 Conversion Factor UK SQ'!F170*'2 Input data Summary SQ'!F170 -> 0 | G170: ='1 Conversion Factor UK SQ'!G170*'2 Input data Summary SQ'!G170 -> 0 | H170: ='1 Conversion Factor UK SQ'!H170*'2 Input data Summary SQ'!H170 -> 0 | I170: ='1 Conversion Factor UK SQ'!H170*'2 Input data Summary SQ'!I170 -> 0
...

Sheet Catering data input
A1: DO NOT USE - THIS IS A TEMPLATE FROM A SPECIFIC PROJECT
A5: MENU 2022
D7: STARTERS | M7: MAIN COURSE | U7: DESSERT | AC7: BEVERAGES
A8: Ingredients | B8: Portion* | C8: Emissions (kg CO2e) | D8: Conv. factor unit | E8: Conv. factor | F8: Reference **** | G8: Notes | L8: Emissions(kg CO2) | M8: Conv. factor unit | N8: Conv. factor | O8: Reference | P8: Notes | T8: Emissions (kg CO2e) | U8: Conv.factor unit | V8: Conv. actor | W8: Reference | X8: Notes | AB8: Emissions (kg CO2e) | AC8: Conv.factor unit | AD8: Conv.factor | AE8: Reference | AF8: Notes
A9: Tuna | B9: 170 g | C9: =0.17*E9 -> 0.442 | D9: kg | E9: 2.6 | F9: WRAP emissions per stage L625 | I9: Dover Sole | K9: 170g | L9: =0.17*N9 -> 1.1475 | M9: kg | N9: 6.75 | O9: 534/L | R9: LEMON ETON MESS | Z9: White Wine | AA9: 150g | AB9: =0.15*AD9 -> 0.1665 | AC9: kg | AD9: 1.11 | AE9: 1568/L
A10: Green Beans | B10: 80 g | C10: =0.08*E10 -> 0.448 | D10: kg | E10: 5.6 | F10: WRAP emissions per stage L50 | I10: Provencal Vegetables: | R10: Thickened cream | S10: 90g | T10: =0.09*V10 -> 0.4788 | U10: kg | V10: 5.32 | W10: J473 | Z10: Red Wine | AA10: 150g | AB10: =0.15*AD10 -> 0.1665 | AC10: kg | AD10: 1.11 | AE10: 1573/L
A11: San Marzano Tomatoes | B11: 80 g | C11: =0.08*E11 -> 0.1 | D11: kg | E11: 1.25 | F11: L1514 | I11: Courgette | K11: 40g | L11: =0.04*N11 -> 0.0236 | M11: kg | N11: 0.59 | O11: 459/L | R11: Lemon Juice | S11: 40g | T11: =0.04*V11 -> 0.024 | U11: kg | V11: 0.6 | W11: 982/L | Z11: Champagne | AA11: 150g | AB11: =0.15*AD11 -> 0.084 | AC11: kg | AD11: 0.56 | AE11: 797/J
A12: Caviar | B12: 30 g | C12: 0.15858 | D12: kg | E12: 5.286 | F12: My emissions | I12: Onion | K12: 20g | L12: =0.02*N12 -> 0.0116 | M12: kg | N12: 0.58 | O12: 1259/L | R12: Marshmallows | S12: 25g | T12: =0.025*V12 -> 0.0603 | U12: kg | V12: 2.412 | W12: My emissions | X12: ** | Z12: Cognac | AA12: 50g | AB12: N/A | AC12: N/A | AD12: N/A | AE12: N/A
A13: CRESS | B13: 25 g | C13: =0.025*E13 -> 0.040225 | D13: kg | E13: 1.609 | F13: My emissions | G13: ** | I13: Garlic | K13: 4g | L13: =0.004*N13 -> 0.00228 | M13: kg | N13: 0.57 | O13: 642/L | R13: Meringue | S13: 25g | T13: =0.025*V13 -> 0.0255 | U13: kg | V13: 1.02 | W13: 912/L | AA13: Total | AB13: =SUM(AB9:AB11) -> 0.417
A14: Orange Juice | B14: 60g | C14: =0.06*E14 -> 0.021 | D14: kg | E14: 0.35 | F14: L1274 | I14: Tomatoes | K14: 30g | L14: =0.03*N14 -> 0.0375 | M14: kg | N14: 1.25 | O14: 1514/L | R14: ShortBreads | S14: 21g | T14: =0.021*V14 -> 0.027363 | U14: kg | V14: 1.303 | W14: My emissions | X14: **
A15: Soy sauce | B15: 16g | C15: =0.016*E15 -> 0.003552 | D15: kg | E15: 0.222 | F15: My emissions | G15: ** | I15: Peppers | K15: 40g | L15: =0.04*N15 -> 0.0668 | M15: kg | N15: 1.67 | O15: 1307/L | R15: Audemus Spirits Covert Liqueur | S15: 25g | T15: N/A | U15: N/A | V15: N/A | W15: N/A
A16: Herbs and Spice | B16: 20g | C16: 0.0226 | D16: kg | E16: 1.13 | F16: My emissions | G16: ** | I16: Roasted San Marzano Sauce | K16: 90g | L16: =0.09*N16 -> 0.1611 | M16: kg | N16: 1.79 | O16: 1553/L | S16: Total | T16: =SUM(T10:T14) -> 0.615963
B17: Total | C17: =SUM(C9:C16) -> 1.235957 | J17: Total | L17: =SUM(L9:L16) -> 1.45038 | Q17: =L17*371 -> 538.09098
S18: 1
A19: VEGAN | I19: VEGETARIAN
A20: Aubergine | B20: 150g | C20: =0.15*E20 -> 0.3075 | D20: kg | E20: 2.05 | F20: (29/L) | I20: Portobello Mushroom | K20: 150g | L20: =0.15*N20 -> 0.0405 | M20: kg | N20: 0.27 | O20: 467/L
A21: Green Beans | B21: 80 g | C21: =0.08*E21 -> 0.0032 | D21: kg | E21: 0.04 | F21: (50/L) | I21: Black Cabbage | K21: 80g | L21: =0.08*N21 -> 0.0256 | M21: kg | N21: 0.32 | O21: 179/L
A22: San Marzano Tomatoes | B22: 80g | C22: =0.08*E22 -> 0.1 | D22: kg | E22: 1.25 | F22: 1514/L | I22: Goat's cheese | K22: 30g | L22: =0.03*N22 -> 0.2658 | M22: kg | N22: 8.86 | O22: 265/L
A23: Caviar | B23: 30 g | C23: =0.03*E23 -> 0.15858 | D23: kg | E23: 5.286 | F23: My emissions | G23: ** | I23: Shallot | K23: 40g and 3g | L23: =0.043*N23 -> 0.02494 | M23: kg | N23: 0.58 | O23: 1259/L
A24: Cress | B24: 25g | C24: =0.025*E24 -> 0.040225 | D24: kg | E24: 1.609 | F24: My emissions | G24: ** | I24: French Beans | K24: 80g | L24: =0.08*N24 -> 0.0464 | M24: kg | N24: 0.58 | O24: 1647/J
A25: Orange Juice | B25: 60g | C25: =0.06*E25 -> 0.021 | D25: kg | E25: 0.35 | F25: (1274/L) | J25: Total | L25: =SUM(L20:L24) -> 0.40324 | Q25: =23*L25 -> 9.27452
A26: Soy sauce | B26: 16g | C26: =0.016*E26 -> 0.003552 | D26: kg | E26: 0.222 | F26: My emissions | G26: ** | I26: VEGAN
A27: Herbs and Spice | B27: 20g | C27: =0.02*E27 -> 0.0226 | D27: kg | E27: 1.13 | F27: My emissions | G27: ** | I27: Portobello Mushroom | K27: 150g | L27: =0.15*N27 -> 0.0405 | M27: kg | N27: 0.27 | O27: 467/L
B28: Total | C28: =SUM(C20:C27) -> 0.656657 | I28: Black Cabbage | K28: 80g | L28: =0.08*N28 -> 0.0256 | M28: kg | N28: 0.32 | O28: 179/L
I29: Shallot | K29: 40g and 3 g | L29: =0.043*N29 -> 0.02494 | M29: kg | N29: 0.58 | O29: 1259/L
I30: French Beans | K30: 80g | L30: =0.08*N30 -> 0.0464 | M30: kg | N30: 0.58 | O30: 1647/J
J31: Total | L31: =SUM(L27:L30) -> 0.13744 | Q31: =9*L31 -> 1.23696
P33: total | Q33: =SUM(Q17:Q31) -> 548.60246 | R33: kg CO2 emissions
Q34: 0.548 | R34: t CO2 emissions
A35: * these values were estimated on the basis of the research reached out;
A37: ** these values were not found in the documents provided by WRAP, have been replaced and also estimated by the My Emissions calculator;
A38: My Emissions follows a data-driven life cycle assessment approach to efficiently calculate the carbon footprint of a product or meal.
A39: We collect information about each food product and meal, and rely on a mix of primary data from clients and secondary data from research to complete our calculations. All of our secondary data comes from ‘life cycle assessments’ published in peer-reviewed journals, and we are constantly adding new values as more research is completed.
A41: **** WRAP Emissions factor Database for Scope 3 GHG Measurement and reporting_1 version 1 from 22-Aug-22
A42: https://wrap.org.uk/resources/guide/scope-3-ghg-measurement-and-reporting-protocols-food-and-drink#download-file

Sheet Final Report
A1: Cover
A3: Content Page
A5: Executive Summary
A7: Introduction
A8: GRI / SASB
A9: Organisation Details
A11: Standards, methodologies, assumptions, and/or calculation tools used. Gases included in the calculation. Source of emission factors. 3. Base year for the calculation, including: the rationale for choosing it; emissions in the base year; the context for any signficiant changes in emissions that triggered reculculations of base year emissions.
A12: BREEAM, FIT WELL - SCIENCE BASED?
A13: Carbon Emissions Calculations Including results
A14: RESULTS - GHG protocol - GRAPHS
A15: Carbon Emission Reduction Plan
A16: GRAPHS + PLAN
... A31: GRI appendix

Sheet CIBSE BENCHMARK
A1: CIBSE Benchmarking Tool (BETA VERSION)
A2: https://www.cibse.org/Knowledge/Benchmarking
A4: General information - Asset 1 | C4: Description
A5: Building type (e.g. community group, office, theatre, museum, gallery) | C5: ='General Info'!C47 -> 0 | D5: Complete the Building General Information (cell C30)
A6: Mains electricity use | C6: ='2 Input data Summary SQ'!H3 -> 0 | D6: Complete the Energy Tab
A7: Mains gas use | C7: ='2 Input data Summary SQ'!H4 -> 0
A9: *Tool manager to input the data above and print the CIBSE Energy Benchmark tool dashboard
A13: Sample below

Sheet EDGE

Sheet FIT WELL

Sheet Science Based Targets 

Sheet Paper Mass Calcs
A1: PAPER weights
A2: Source | B2: weights of sheets of the ISO 216 A paper sizes for various common grammages
B3: https://www.papersizes.org/paper-weights.htm
A5: Size | B5: 75gsm | C5: 80gsm | D5: 90gsm | E5: 100gsm | F5: 110gsm | G5: 120gsm | H5: 160gsm
A6: unit | B6: gram | C6: gram | D6: gram | E6: gram | F6: gram | G6: gram | H6: gram
A7: 4A0 | B7: 300 | C7: 320 | D7: 360 | E7: 400 | F7: 440 | G7: 480 | H7: 640
A8: 2A0 | B8: 150 | C8: =C7/2 -> 160 | D8: =D7/2 -> 180 | E8: =E7/2 -> 200 | F8: =F7/2 -> 220 | G8: =G7/2 -> 240 | H8: =H7/2 -> 320
A9: A0 | B9: 75 | C9: =C8/2 -> 80 | D9: =D8/2 -> 90 | E9: =E8/2 -> 100 | F9: =F8/2 -> 110 | G9: =G8/2 -> 120 | H9: =H8/2 -> 160
A10: A1 | B10: 37.5 | C10: =C9/2 -> 40 | D10: =D9/2 -> 45 | E10: =E9/2 -> 50 | F10: =F9/2 -> 55 | G10: =G9/2 -> 60 | H10: =H9/2 -> 80
A11: A2 | B11: 18.75 | C11: =C10/2 -> 20 | D11: =D10/2 -> 22.5 | E11: =E10/2 -> 25 | F11: =F10/2 -> 27.5 | G11: =G10/2 -> 30 | H11: =H10/2 -> 40
A12: A3 | B12: 9.38 | C12: =C11/2 -> 10 | D12: =D11/2 -> 11.25 | E12: =E11/2 -> 12.5 | F12: =F11/2 -> 13.75 | G12: =G11/2 -> 15 | H12: =H11/2 -> 20
A13: A4 | B13: 4.69 | C13: =C12/2 -> 5 | D13: =D12/2 -> 5.625 | E13: =E12/2 -> 6.25 | F13: =F12/2 -> 6.875 | G13: =G12/2 -> 7.5 | H13: =H12/2 -> 10
A14: A5 | B14: 2.34 | C14: =C13/2 -> 2.5 | D14: =D13/2 -> 2.8125 | E14: =E13/2 -> 3.125 | F14: =F13/2 -> 3.4375 | G14: =G13/2 -> 3.75 | H14: =H13/2 -> 5
A15: A6 | B15: 1.17 | C15: =C14/2 -> 1.25 | D15: =D14/2 -> 1.40625 | E15: =E14/2 -> 1.5625 | F15: =F14/2 -> 1.71875 | G15: =G14/2 -> 1.875 | H15: =H14/2 -> 2.5
A16: A7 | B16: 0.59 | C16: =C15/2 -> 0.625 | D16: =D15/2 -> 0.703125 | E16: =E15/2 -> 0.78125 | F16: =F15/2 -> 0.859375 | G16: =G15/2 -> 0.9375 | H16: =H15/2 -> 1.25
A17: A8 | B17: 0.29 | C17: =C16/2 -> 0.3125 | D17: =D16/2 -> 0.3515625 | E17: =E16/2 -> 0.390625 | F17: =F16/2 -> 0.4296875 | G17: =G16/2 -> 0.46875 | H17: =H16/2 -> 0.625
A18: A9 | B18: 0.15 | C18: =C17/2 -> 0.15625 | D18: =D17/2 -> 0.17578125 | E18: =E17/2 -> 0.1953125 | F18: =F17/2 -> 0.21484375 | G18: =G17/2 -> 0.234375 | H18: =H17/2 -> 0.3125
A19: A10 | B19: 0.07 | C19: =C18/2 -> 0.078125 | D19: =D18/2 -> 0.087890625 | E19: =E18/2 -> 0.09765625 | F19: =F18/2 -> 0.10742188 | G19: =G18/2 -> 0.1171875 | H19: =H18/2 -> 0.15625
A21: Number of sheets in a reem | D21: 500 | E21: sheets
A22: mass conversion (gram to tonne ratio) | D22: =1/1000000 -> 1e-06
A24: Weight of Reems
A25: Size | B25: 75gsm | C25: 80gsm | D25: 90gsm | E25: 100gsm | F25: 110gsm | G25: 120gsm | H25: 160gsm
A26: unit | B26: tonnes | C26: tonnes | D26: tonnes | E26: tonnes | F26: tonnes | G26: tonnes | H26: tonnes
A27: 4A0 | B27: =(B7*$D$21)*$D$22 -> 0.15 | C27: =(C7*$D$21)*$D$22 -> 0.16 | D27: =(D7*$D$21)*$D$22 -> 0.18 | E27: =(E7*$D$21)*$D$22 -> 0.2 | F27: =(F7*$D$21)*$D$22 -> 0.22 | G27: =(G7*$D$21)*$D$22 -> 0.24 | H27: =(H7*$D$21)*$D$22 -> 0.32
A28: 2A0 | B28: =(B8*$D$21)*$D$22 -> 0.075 | C28: =(C8*$D$21)*$D$22 -> 0.08 | D28: =(D8*$D$21)*$D$22 -> 0.09 | E28: =(E8*$D$21)*$D$22 -> 0.1 | F28: =(F8*$D$21)*$D$22 -> 0.11 | G28: =(G8*$D$21)*$D$22 -> 0.12 | H28: =(H8*$D$21)*$D$22 -> 0.16
A29: A0 | B29: =(B9*$D$21)*$D$22 -> 0.0375 | C29: =(C9*$D$21)*$D$22 -> 0.04 | D29: =(D9*$D$21)*$D$22 -> 0.045 | E29: =(E9*$D$21)*$D$22 -> 0.05 | F29: =(F9*$D$21)*$D$22 -> 0.055 | G29: =(G9*$D$21)*$D$22 -> 0.06 | H29: =(H9*$D$21)*$D$22 -> 0.08
A30: A1 | B30: =(B10*$D$21)*$D$22 -> 0.01875 | C30: =(C10*$D$21)*$D$22 -> 0.02 | D30: =(D10*$D$21)*$D$22 -> 0.0225 | E30: =(E10*$D$21)*$D$22 -> 0.025 | F30: =(F10*$D$21)*$D$22 -> 0.0275 | G30: =(G10*$D$21)*$D$22 -> 0.03 | H30: =(H10*$D$21)*$D$22 -> 0.04
A31: A2 | B31: =(B11*$D$21)*$D$22 -> 0.009375 | C31: =(C11*$D$21)*$D$22 -> 0.01 | D31: =(D11*$D$21)*$D$22 -> 0.01125 | E31: =(E11*$D$21)*$D$22 -> 0.0125 | F31: =(F11*$D$21)*$D$22 -> 0.01375 | G31: =(G11*$D$21)*$D$22 -> 0.015 | H31: =(H11*$D$21)*$D$22 -> 0.02
A32: A3 | B32: =(B12*$D$21)*$D$22 -> 0.00469 | C32: =(C12*$D$21)*$D$22 -> 0.005 | D32: =(D12*$D$21)*$D$22 -> 0.005625 | E32: =(E12*$D$21)*$D$22 -> 0.00625 | F32: =(F12*$D$21)*$D$22 -> 0.006875 | G32: =(G12*$D$21)*$D$22 -> 0.0075 | H32: =(H12*$D$21)*$D$22 -> 0.01
A33: A4 | B33: =(B13*$D$21)*$D$22 -> 0.002345 | C33: =(C13*$D$21)*$D$22 -> 0.0025 | D33: =(D13*$D$21)*$D$22 -> 0.0028125 | E33: =(E13*$D$21)*$D$22 -> 0.003125 | F33: =(F13*$D$21)*$D$22 -> 0.0034375 | G33: =(G13*$D$21)*$D$22 -> 0.00375 | H33: =(H13*$D$21)*$D$22 -> 0.005
A34: A5 | B34: =(B14*$D$21)*$D$22 -> 0.00117 | C34: =(C14*$D$21)*$D$22 -> 0.00125 | D34: =(D14*$D$21)*$D$22 -> 0.00140625 | E34: =(E14*$D$21)*$D$22 -> 0.0015625 | F34: =(F14*$D$21)*$D$22 -> 0.00171875 | G34: =(G14*$D$21)*$D$22 -> 0.001875 | H34: =(H14*$D$21)*$D$22 -> 0.0025
A35: A6 | B35: =(B15*$D$21)*$D$22 -> 0.000585 | C35: =(C15*$D$21)*$D$22 -> 0.000625 | D35: =(D15*$D$21)*$D$22 -> 0.000703125 | E35: =(E15*$D$21)*$D$22 -> 0.00078125 | F35: =(F15*$D$21)*$D$22 -> 0.000859375 | G35: =(G15*$D$21)*$D$22 -> 0.0009375 | H35: =(H15*$D$21)*$D$22 -> 0.00125
A36: A7 | B36: =(B16*$D$21)*$D$22 -> 0.000295 | C36: =(C16*$D$21)*$D$22 -> 0.0003125 | D36: =(D16*$D$21)*$D$22 -> 0.0003515625 | E36: =(E16*$D$21)*$D$22 -> 0.000390625 | F36: =(F16*$D$21)*$D$22 -> 0.0004296875 | G36: =(G16*$D$21)*$D$22 -> 0.00046875 | H36: =(H16*$D$21)*$D$22 -> 0.000625
A37: A8 | B37: =(B17*$D$21)*$D$22 -> 0.000145 | C37: =(C17*$D$21)*$D$22 -> 0.00015625 | D37: =(D17*$D$21)*$D$22 -> 0.00017578125 | E37: =(E17*$D$21)*$D$22 -> 0.0001953125 | F37: =(F17*$D$21)*$D$22 -> 0.00021484375 | G37: =(G17*$D$21)*$D$22 -> 0.000234375 | H37: =(H17*$D$21)*$D$22 -> 0.0003125
A38: A9 | B38: =(B18*$D$21)*$D$22 -> 7.5e-05 | C38: =(C18*$D$21)*$D$22 -> 7.8125e-05 | D38: =(D18*$D$21)*$D$22 -> 8.7890625e-05 | E38: =(E18*$D$21)*$D$22 -> 9.765625e-05 | F38: =(F18*$D$21)*$D$22 -> 0.00010742188 | G38: =(G18*$D$21)*$D$22 -> 0.0001171875 | H38: =(H18*$D$21)*$D$22 -> 0.00015625
A39: A10 | B39: =(B19*$D$21)*$D$22 -> 3.5e-05 | C39: =(C19*$D$21)*$D$22 -> 3.90625e-05 | D39: =(D19*$D$21)*$D$22 -> 4.3945312e-05 | E39: =(E19*$D$21)*$D$22 -> 4.8828125e-05 | F39: =(F19*$D$21)*$D$22 -> 5.3710938e-05 | G39: =(G19*$D$21)*$D$22 -> 5.859375e-05 | H39: =(H19*$D$21)*$D$22 -> 7.8125e-05

Sheet SASB, SFDR

Sheet European Legislation 
A11: References
A12: https://finance.ec.europa.eu/capital-markets-union-and-financial-markets/company-reporting-and-auditing/company-reporting/corporate-sustainability-reporting_en
A13: https://www.fca.org.uk/publications/policy-statements/ps23-16-sustainability-disclosure-requirements-investment-labels
A14: https://eur-lex.europa.eu/legal-content/EN/TXT/?uri=celex%3A32014L0095
A16: https://normative.io/carbon-legislation/
A17: https://normative.io/insight/sfdr-explained/
A18: https://normative.io/insight/secr-explained/
A19: https://normative.io/insight/sec-proposal/
A21: https://www.eumonitor.eu/9353000/1/j9vvik7m1c3gyxp/vkmiobvzi1x7?ctx=vg9pk7ho53zu
A22: https://normative.io/insight/csrd-explained/
A24: https://climate.ec.europa.eu/eu-action/transport/road-transport-reducing-co2-emissions-vehicles/co2-emission-performance-standards-cars-and-vans_en
A25: https://www.eca.europa.eu/lists/ecadocuments/sr14_14/qjab14014enc.pdf

Sheet Eco Audit Questions
A1: ADD ECO AUDITS QUESTIONS

Sheet Eco Church
A1: Aec
A7: References
A8: https://ecochurch.arocha.org.uk
A9: https://ecochurch.arocha.org.uk/how-eco-church-works/
A10: https://ecochurch.arocha.org.uk/wp-content/uploads/2022/09/Eco-Church-Survey-printable-copy-September-2022.pdf
A12: https://ecochurch.arocha.org.uk/wp-content/uploads/2021/10/B1-Carbon-footprint-measurement-and-offset.pdf
A13: https://www.churchofengland.org/about/policy-and-thinking/our-views/environment-and-climate-change/about-our-environment/energy-footprint-tool
A14: https://360carbon.org/en-gb/
A15: https://www.climatestewards.org/resources/lower-carbon-living/
A16: https://www.carbontrust.com/resources/carbon-footprinting-guide

Sheet Conversion Factor country 1...

Sheet CREEEM
A4: https://www.crrem.org/wp-content/uploads/2020/10/CRREM-Guide-to-using-the-Tool-outside-the-EU-v1.2-15.10.2020.pdf
A6: https://www.crrem.org/pathways/
A8: https://www.crrem.org
A10: https://www.gresb.com/nl-en/carbon-risk-real-estate-monitor-crrem/

Sheet NABERS EQUIVALENT 

Sheet Waste Mass calcs & miles to km
A17: Weight vs volume
A18: Whilst this document provides assumptions to convert waste volumes to weight based on industry averages, it is stressed that the use of actual weights should always be preferable. Dynamic weighing is a service provided by most reputable service providers, in particular, for residual waste and Dry Mixed Recycling. Managing Agents and property owners are encouraged to request for
A19: this as part of their procurement specifications. See Improving UK Waste Management Practices: Procurement Specifications for more information.
A25: References
A26: https://www.sepa.org.uk/media/163323/uk-conversion-factors-for-waste.xlsx
A27: https://www.managingagentspartnership.co.uk/sites/default/files/media/attachment/BBP_MAP_Waste%20Management%20practices_Standardised%20reporting%20template%20and%20weight%20conversions.pdf
A28: https://wrap.org.uk/resources/report/carbon-waste-and-resources-metric
A31: https://www.nisbets.co.uk/which-bin-bag
A32: https://assets.publishing.service.gov.uk/media/6152d0b78fa8f5610b9c222b/Waste_classification_technical_guidance_WM3.pdf
A37: https://www.aqua-calc.com/calculate/volume-to-weight/substance/garbage-coma-and-blank-household-blank-rubbish
A38: https://www.merseysidewda.gov.uk/volume-to-kgs/
A39: https://www.sustainabilityexchange.ac.uk/conversion_factors_for_calculation_of_weight_to_vo
A46: https://wrap.org.uk/resources/report/carbon-waste-and-resources-metric
B50: miles to kms
B51: To convert the distance into kms, we use the “convert” formula… =convert(number, “from” , “to”) eg from miles to kms
B54: bags to litres to kilograms | E54: NOTE: bag = 60l
B68: =0.261*1000/52 -> 5.0192308 | C68: kgs of waste per bag | K68: =0.209*1000/51 -> 4.0980392 | L68: kgs of waste per bag | V68: =0.991*1000/52 -> 19.057692 | W68: kgs of waste per bag
B69: =B68/60 -> 0.083653846 | C69: kgs of waste kgs of waste per litre | K69: =K68/60 -> 0.068300654 | L69: kgs of waste kgs of waste per litre | V69: =V68/60 -> 0.31762821 | W69: kgs of waste kgs of waste per litre
L83: https://www.merseysidewda.gov.uk/volume-to-kgs/
B106: There is also conversion factors fro the US EPA but they are in yards3 and not litres/m3
B107: https://www.epa.gov/sites/default/files/2016-04/documents/volume_to_weight_conversion_factors_memorandum_04192016_508fnl.pdf
B110: SEPA conversion factors
B111: https://www.sepa.org.uk/media/163323/uk-conversion-factors-for-waste.xlsx
L112: I assume this to be general waste
B126: FINAL CALCULATION METHOD FROM BAGS --> KILOGRAMS
C127: bags --> kg | D127: litres --> kg
B128: General Waste | C128: 5.0192308 | D128: 0.08365385
B129: Recycling | C129: 4.0980392 | D129: 0.06830065
B130: Mixed Food | C130: 19.057692 | D130: 0.3176281

Sheet GRI Carbon Emissions Criteria
A2: Reporting Requirements in terms of GRI and Carbon Emissions:
A4: We need to include the following information for Scope 1: | B4: 2020 | C4: 2021 | D4: 2022 | E4: 2023
A5: 1. Gross direct Scope 1 GHG emissions in metric tons of CO2 equivalent | B5: ='2024 Results Graphs'!B81 -> 0 | C5: ='2024 Results Graphs'!C81 -> 0 | D5: ='2024 Results Graphs'!D81 -> 0 | E5: ='2024 Results Graphs'!E81 -> 0
A6: 2. Gases included in the calculation | B6: CO2e
A7: 3. Base year for the calculation, including: the rationale for choosing it; emissions in the base year; the context for any signficiant changes in emissions that triggered reculculations of base year emissions. | B7: ='Assessment Scope'!L20 -> 0
A8: 4. Source of emission factors. | B8: GOV UK | F8: There are references at the end of each year's CF's methodology. We could provide the link here and it would satisfy the next point as well. https://assets.publishing.service.gov.uk/media/647f50dd103ca60013039a8a/2023-ghg-cf-methodology-paper.pdf (2023)
A9: 5. Standards, methodologies, assumptions, and/or calculation tools used. | B9: The GHG Protocol was used in consultation with the UK Government's Conversion Factors. The methodology was as follows: (1) Input data in relevant units; (2) Covert to all appropriate units (e.g., bags -> litre -> kilograms; miles -> kms); (3) Multiply the data by the UK Government's Conversion Factors. The sources of the Scottish Environmental Protection Agency were consulted to convert bags to litres to kilograms/
A11: We need to include the following information for Scope 2:
A12: 1. Gross location-based energy indirect (Scope 2) GHG emissions in metric tons of CO2 equivalent. | B12: ='2024 Results Graphs'!B82 -> 0 | C12: ='2024 Results Graphs'!C82 -> 0 | D12: ='2024 Results Graphs'!D82 -> 0 | E12: ='2024 Results Graphs'!E82 -> 0
A13: 2. The gases included in the calculation. | B13: CO2e
A14: 3. Base year for the calculation, including: the rationale for choosing it; emissions in the base year; the context for any signficiant changes in emissions that triggered reculculations of base year emissions. | B14: ='Assessment Scope'!L20 -> 0
A15: 4. Source of emission factors. | B15: GOV UK
A16: 5. Standards, methodologies, assumptions, and/or calculation tools used. | B16: The GHG Protocol was used in consultation with the UK Government's Conversion Factors. The methodology was as follows: (1) Input data in relevant units; (2) Covert to all appropriate units (e.g., bags -> litre -> kilograms; miles -> kms); (3) Multiply the data by the UK Government's Conversion Factors. The sources of the Scottish Environmental Protection Agency were consulted to convert bags to litres to kilograms/
A18: We need to include the following information for Scope 3:
A19: 1. Gross other indirect (Scope 3) GHG emissions in metric tons of CO2 equivalent. | B19: ='2024 Results Graphs'!B83 -> 0 | C19: ='2024 Results Graphs'!C83 -> 0 | D19: ='2024 Results Graphs'!D83 -> 0 | E19: ='2024 Results Graphs'!E83 -> 0
A20: 2. Gases included in the calculation | B20: CO2e
A21: 3. Base year for the calculation, including: the rationale for choosing it; emissions in the base year; the context for any signficiant changes in emissions that triggered reculculations of base year emissions. | B21: ='Assessment Scope'!L20 -> 0
A22: 4. Source of emission factors. | B22: GOV UK
A23: 5. Standards, methodologies, assumptions, and/or calculation tools used. | B23: The GHG Protocol was used in consultation with the UK Government's Conversion Factors. The methodology was as follows: (1) Input data in relevant units; (2) Covert to all appropriate units (e.g., bags -> litre -> kilograms; miles -> kms); (3) Multiply the data by the UK Government's Conversion Factors. The sources of the Scottish Environmental Protection Agency were consulted to convert bags to litres to kilograms/
A25: We need to state that at this time there are no relevant GHG emissions intensity ratios for the organisation. | B25: Please write a standard statement to be used on all reports
A27: We need to include the following information for the reduction of GHG emissions
A28: 1. GHG emissions reduced as a direct result of reduction initiatives, in metric tons of CO2 equivalent. This might only be revelant in review audits and so in first time reports we need to specifically say that because we are quantifying GHG emissions for the first time there are no reductions. | C28: ='Carbon Reduction Plan'!F18 -> 0 | D28: ='Carbon Reduction Plan'!F19 -> 0 | E28: ='Carbon Reduction Plan'!F20 -> 0 | F28: Link to CRP - carbon reduction plan measures
A29: 2. Gases included in the calculation | B29: CO2e
A30: 3. Base year for the calculation including the rationale for choosing it. | B30: ='Assessment Scope'!L20 -> 0
A31: 4. Scopes in which the reductions took place. | F31: Check CRP - Carbon reduction scope
A32: 5. Standards, methodologies, assumptions, and/or calculation tools used. | B32: The GHG Protocol was used in consultation with the UK Government's Conversion Factors. The methodology was as follows: (1) Input data in relevant units; (2) Covert to all appropriate units (e.g., bags -> litre -> kilograms; miles -> kms); (3) Multiply the data by the UK Government's Conversion Factors. The sources of the Scottish Environmental Protection Agency were consulted to convert bags to litres to kilograms/
A34: Confirmation to state that the orgnisation does not utilised any ozone-depletio substances (ODS) | B34: As of January 2010, in line with the Montreal Protocol, ODS were prohibted and severely controlled. As such this organisation has no affiliation or use with these substances and are committed to reduce atmospheric emissions in this way.
A36: We need to include the following information for Nox, Sox, and other significant air emissions: (I doubt this one will be possible) | B36: At this point the NOx, SOx, and other significant air emissions are not included as a result of a lack of data.
A37: 1. Significant air emissions, in kgs or multiples of: Nox, Sox, POP, VOC, HAP, PM, other standard categories of air emissions identified in relevant regulations.
A38: 2. Source of emission factors. | B38: GOV
A39: 3. Standards, methodologies, assumptions, and/or calculation tools used. | B39: The GHG Protocol was used in consultation with the UK Government's Conversion Factors. The methodology was as follows: (1) Input data in relevant units; (2) Covert to all appropriate units (e.g., bags -> litre -> kilograms; miles -> kms); (3) Multiply the data by the UK Government's Conversion Factors. The sources of the Scottish Environmental Protection Agency were consulted to convert bags to litres to kilograms/

Sheet How to use the tool checklists
A2: WE NEED TO HAVE A FULL GUIDANCE ON HOW TO USE THE TOOL
A4: Overall Guidance
A6: Please complete relevant areas/fields when applicable. If you require assistance please emai:l info@sustainquality.co.uk
A9: Energy
A12: Water
A14: Waste
A16: Waste Mass Calculator
A18: Business Travel
A20: Staff Commute
A22: Refrigerant
A24: Results
A26: Reports
A29: In order to calculate the organisation’s footprint, you will need the following information for your chosen reporting year: | C29: Check list (OK?)
A31: Fuel consumption - Fuel consumed by the organisation in its sites and owned vehicles. This can be natural gas, diesel or LPG. You may find this information in bills, fuel card data or meters
A32: Energy consumption - Electricity used in your sites. You may find this information through meter readings, utility bills, or automatic meter readings
A33: Top ups made to air conditioning units - Many refrigeration, fire protection and air conditioning equipment contain a type of F gas (Fluorinated greenhouse gas), which has a large carbon footprint. Please include the type and quantity of top up that has been done during the reporting year. You can find this information in the service sheets provided by your air conditioning or refrigeration contractor
A35: It is important that the reported data covers the chosen 12 months of data. If you don’t have data exactly for the whole year, you should estimate the consumption using the average energy or fuel consumed per month. Please note that there can be seasonal changes in energy demand due to production levels, need for heating / cooling and use and replacement of equipment.
